Workbook

Sheet Übersicht
A1: Quartalsübersicht 2025Q3 - Zusammenfassung aller Mitarbeiter
A3: --- Monatliche Summen ---
A4: Monat | B4: Gesamtstunden | C4: Bonusberechtigte Stunden | D4: Bonusberechtigte Stunden Sonderprojekt
A5: Juli 2025 | B5: =SUM('A. Kokott'!F31,'C. Trapp SV'!F24,'D. Brucker'!F16,'E. Bieler'!F42,'E. Iago Barros de Oliveira'!F8,'H. Bektas'!F23,'J. Dorchies'!F15,'J. Dorn'!F37,'M. Bandlofsky'!F18,'M. Bandlofsky CAD'!F9,'O. Haag BS-CAD'!F43,'P. Bergner'!F13,'R. Böttiger'!F23,'R. Wagen CAD'!F23,'S. Schüler'!F45,'T. Trautmann'!F20,'U. Sutter ADM'!F20) | C5: =SUM('A. Kokott'!F32,'C. Trapp SV'!F25,'D. Brucker'!F17,'E. Bieler'!F43,'E. Iago Barros de Oliveira'!F9,'H. Bektas'!F24,'J. Dorchies'!F16,'J. Dorn'!F38,'M. Bandlofsky'!F19,'M. Bandlofsky CAD'!F10,'O. Haag BS-CAD'!F44,'P. Bergner'!F14,'R. Böttiger'!F24,'R. Wagen CAD'!F24,'S. Schüler'!F46,'T. Trautmann'!F21,'U. Sutter ADM'!F21) | D5: =SUM('A. Kokott'!F33,'C. Trapp SV'!F26,'D. Brucker'!F18,'E. Bieler'!F44,'E. Iago Barros de Oliveira'!F10,'H. Bektas'!F25,'J. Dorchies'!F17,'J. Dorn'!F39,'M. Bandlofsky'!F20,'M. Bandlofsky CAD'!F11,'O. Haag BS-CAD'!F45,'P. Bergner'!F15,'R. Böttiger'!F25,'R. Wagen CAD'!F25,'S. Schüler'!F47,'T. Trautmann'!F22,'U. Sutter ADM'!F22)
A6: August 2025 | B6: =SUM('A. Kokott'!F77,'C. Trapp SV'!F48,'D. Brucker'!F25,'E. Bieler'!F53,'H. Bektas'!F39,'J. Dorchies'!F24,'J. Dorn'!F75,'M. Bandlofsky'!F37,'M. Warner'!F14,'O. Haag BS-CAD'!F84,'P. Bergner'!F34,'R. Böttiger'!F47,'R. Wagen CAD'!F49,'S. Roßkopf'!F10,'S. Schüler'!F85,'T. Trautmann'!F64,'U. Sutter ADM'!F43) | C6: =SUM('A. Kokott'!F78,'C. Trapp SV'!F49,'D. Brucker'!F26,'E. Bieler'!F54,'H. Bektas'!F40,'J. Dorchies'!F25,'J. Dorn'!F76,'M. Bandlofsky'!F38,'M. Warner'!F15,'O. Haag BS-CAD'!F85,'P. Bergner'!F35,'R. Böttiger'!F48,'R. Wagen CAD'!F50,'S. Roßkopf'!F11,'S. Schüler'!F86,'T. Trautmann'!F65,'U. Sutter ADM'!F44) | D6: =SUM('A. Kokott'!F79,'C. Trapp SV'!F50,'D. Brucker'!F27,'E. Bieler'!F55,'H. Bektas'!F41,'J. Dorchies'!F26,'J. Dorn'!F77,'M. Bandlofsky'!F39,'M. Warner'!F16,'O. Haag BS-CAD'!F86,'P. Bergner'!F36,'R. Böttiger'!F49,'R. Wagen CAD'!F51,'S. Roßkopf'!F12,'S. Schüler'!F87,'T. Trautmann'!F66,'U. Sutter ADM'!F45)
A7: September 2025 | B7: =SUM('A. Kokott'!F123,'C. Trapp SV'!F66,'D. Brucker'!F39,'E. Bieler'!F63,'H. Bektas'!F56,'J. Dorn'!F103,'M. Bandlofsky'!F64,'M. Bandlofsky CAD'!F19,'M. Warner'!F29,'O. Haag BS-CAD'!F127,'P. Bergner'!F55,'R. Böttiger'!F70,'R. Wagen CAD'!F63,'S. Roßkopf'!F22,'S. Schüler'!F118,'T. Trautmann'!F97,'U. Sutter ADM'!F60) | C7: =SUM('A. Kokott'!F124,'C. Trapp SV'!F67,'D. Brucker'!F40,'E. Bieler'!F64,'H. Bektas'!F57,'J. Dorn'!F104,'M. Bandlofsky'!F65,'M. Bandlofsky CAD'!F20,'M. Warner'!F30,'O. Haag BS-CAD'!F128,'P. Bergner'!F56,'R. Böttiger'!F71,'R. Wagen CAD'!F64,'S. Roßkopf'!F23,'S. Schüler'!F119,'T. Trautmann'!F98,'U. Sutter ADM'!F61) | D7: =SUM('A. Kokott'!F125,'C. Trapp SV'!F68,'D. Brucker'!F41,'E. Bieler'!F65,'H. Bektas'!F58,'J. Dorn'!F105,'M. Bandlofsky'!F66,'M. Bandlofsky CAD'!F21,'M. Warner'!F31,'O. Haag BS-CAD'!F129,'P. Bergner'!F57,'R. Böttiger'!F72,'R. Wagen CAD'!F65,'S. Roßkopf'!F24,'S. Schüler'!F120,'T. Trautmann'!F99,'U. Sutter ADM'!F62)
A9: --- Quartalssummen ---
A10: Gesamt eingetragene Stunden: | B10: =SUM('A. Kokott'!B136,'C. Trapp SV'!B82,'D. Brucker'!B52,'E. Bieler'!B76,'E. Iago Barros de Oliveira'!B19,'H. Bektas'!B69,'J. Dorchies'!B36,'J. Dorn'!B116,'M. Bandlofsky'!B80,'M. Bandlofsky CAD'!B31,'M. Warner'!B41,'O. Haag BS-CAD'!B140,'P. Bergner'!B71,'R. Böttiger'!B83,'R. Wagen CAD'!B76,'S. Roßkopf'!B34,'S. Schüler'!B131,'T. Trautmann'!B110,'U. Sutter ADM'!B73)
A11: Bonusberechtigte Stunden (Quartal): | B11: =SUM('A. Kokott'!B138,'C. Trapp SV'!B84,'D. Brucker'!B54,'E. Bieler'!B78,'E. Iago Barros de Oliveira'!B21,'H. Bektas'!B71,'J. Dorchies'!B38,'J. Dorn'!B118,'M. Bandlofsky'!B82,'M. Bandlofsky CAD'!B33,'M. Warner'!B43,'O. Haag BS-CAD'!B142,'P. Bergner'!B73,'R. Böttiger'!B85,'R. Wagen CAD'!B78,'S. Roßkopf'!B36,'S. Schüler'!B133,'T. Trautmann'!B112,'U. Sutter ADM'!B75)
A12: Bonusberechtigte Stunden Sonderprojekt (Quartal): | B12: =SUM('A. Kokott'!B139,'C. Trapp SV'!B85,'D. Brucker'!B55,'E. Bieler'!B79,'E. Iago Barros de Oliveira'!B22,'H. Bektas'!B72,'J. Dorchies'!B39,'J. Dorn'!B119,'M. Bandlofsky'!B83,'M. Bandlofsky CAD'!B34,'M. Warner'!B44,'O. Haag BS-CAD'!B143,'P. Bergner'!B74,'R. Böttiger'!B86,'R. Wagen CAD'!B79,'S. Roßkopf'!B37,'S. Schüler'!B134,'T. Trautmann'!B113,'U. Sutter ADM'!B76)
A14: --- Mitarbeiter in diesem Quartal ---
A15: A. Kokott
A16: C. Trapp SV
A17: D. Brucker
A18: E. Bieler
A19: E. Iago Barros de Oliveira
A20: H. Bektas
A21: J. Dorchies
A22: J. Dorn
A23: M. Bandlofsky
A24: M. Bandlofsky CAD
A25: M. Warner
... A33: U. Sutter ADM

Sheet Projekt-Budget-Übersicht
A1: Projekt-Budget-Übersicht
A3: Hinweis: Rote Zellen = Manuelle Eingabe erforderlich | Gelbe Zellen = Optional manuell anpassen
A5: Projekt | B5: Obermeilenstein | C5: Abrechnungsart | D5: Status | E5: Gesamtbudget (€) | F5: Abgerechnet (€) | G5: Verfügbar (€) | H5: Stundensatz SV (€/h) | I5: Stundensatz CAD (€/h) | J5: Stundensatz ADM (€/h) | K5: Bemerkung
A6: 0.1000 PM Allgemeinprojekt | B6: ● PM Projektvorbereitung/Dokumentation | C6: Unbekannt | D6: ⚠ Manual erforderlich | F6: 0 | G6: =E6-F6 | K6: Abrechnungsart wählen; Stundensätze eingeben
A7: 0.1000 PM Allgemeinprojekt | B7: ● PM Einarbeitung neuer Mitarbeiter | C7: Unbekannt | D7: ⚠ Manual erforderlich | F7: 0 | G7: =E7-F7 | K7: Abrechnungsart wählen; Stundensätze eingeben
A8: 0.1000 PM Allgemeinprojekt | B8: ● PM Teilnahme Meetings | C8: Unbekannt | D8: ⚠ Manual erforderlich | F8: 0 | G8: =E8-F8 | K8: Abrechnungsart wählen; Stundensätze eingeben
A9: 0.1000 PM Allgemeinprojekt | B9: ● PM Onboarding | C9: Unbekannt | D9: ⚠ Manual erforderlich | F9: 0 | G9: =E9-F9 | K9: Abrechnungsart wählen; Stundensätze eingeben
A10: 0.1000 PM Allgemeinprojekt | B10: ● PM Vertragswesen | C10: Unbekannt | D10: ⚠ Manual erforderlich | F10: 0 | G10: =E10-F10 | K10: Abrechnungsart wählen; Stundensätze eingeben
A11: 0.1000 PM Allgemeinprojekt | B11: ● PM Portalanlage und Pflege | C11: Unbekannt | D11: ⚠ Manual erforderlich | F11: 0 | G11: =E11-F11 | K11: Abrechnungsart wählen; Stundensätze eingeben
A12: 0.1000 PM Allgemeinprojekt | B12: ● SAP Schulungen | C12: Unbekannt | D12: ⚠ Manual erforderlich | F12: 0 | G12: =E12-F12 | K12: Abrechnungsart wählen; Stundensätze eingeben
A13: 0.1000 PM Allgemeinprojekt | B13: ● SAP Projekt | C13: Unbekannt | D13: ⚠ Manual erforderlich | F13: 0 | G13: =E13-F13 | K13: Abrechnungsart wählen; Stundensätze eingeben
A14: 0.1000 PM Allgemeinprojekt | B14: ● uStrich Umstellung uStrich/X4 | C14: Unbekannt | D14: ⚠ Manual erforderlich | F14: 0 | G14: =E14-F14 | K14: Abrechnungsart wählen; Stundensätze eingeben
A15: 0000 Sonderprojekt für Bonus | B15: ● Erfassung für | C15: Unbekannt | D15: ⚠ Manual erforderlich | F15: 0 | G15: =E15-F15 | K15: Abrechnungsart wählen; Stundensätze eingeben
A16: 0283.05 D+R-BAB-Lokalbhf-Dreieichstr59-FFM | B16: ● (p) Pos. 1 Feuerwehrpläne | C16: Pauschale | D16: ⚠ Manual erforderlich | F16: 0 | G16: =E16-F16 | H16: 0 | I16: 0 | J16: 0 | K16: Stundensätze eingeben
A17: 0283.05 D+R-BAB-Lokalbhf-Dreieichstr59-FFM | B17: ● (aN) BAB | C17: Nachweis | D17: ⚠ Manual erforderlich | F17: 0 | G17: =E17-F17 | K17: Stundensätze eingeben
A18: 0299.02 BSK-Franziska Schervier-Lange-Straße-10-16-Ffm-Altenpflegeheim | B18: ● (p) Pos.1 Fortschr. bestehendes BSK | C18: Pauschale | D18: ⚠ Manual erforderlich | F18: 0 | G18: =E18-F18 | H18: 0 | I18: 0 | J18: 0 | K18: Stundensätze eingeben
A19: 0299.02 BSK-Franziska Schervier-Lange-Straße-10-16-Ffm-Altenpflegeheim | B19: ● (a.N.) Pos.2 BAB + Qualitätsüberwachung | C19: Nachweis | D19: ⚠ Manual erforderlich | F19: 0 | G19: =E19-F19 | K19: Stundensätze eingeben
A20: 0569.03 RUR-BSK-Gutleutstr85-Frankfurt-Hotel-Roomers | B20: ● • (p) Pos. 1 Erstellung BSK | C20: Pauschale | D20: ⚠ Manual erforderlich | F20: 0 | G20: =E20-F20 | H20: 0 | I20: 0 | J20: 0 | K20: Stundensätze eingeben
A21: 0569.03 RUR-BSK-Gutleutstr85-Frankfurt-Hotel-Roomers | B21: ● • (p) Pos. 2 Auftragsbearbeitung (ADM) | C21: Pauschale | D21: ⚠ Manual erforderlich | F21: 0 | G21: =E21-F21 | H21: 0 | I21: 0 | J21: 0 | K21: Stundensätze eingeben
A22: 0683.07 BSK-Hanauer-Landstraße-147-149-Ffm | B22: ● (a.N.) BTB zur Nutzungsänderung 2. OG | C22: Nachweis | D22: ⚠ Manual erforderlich | F22: 0 | G22: =E22-F22 | K22: Stundensätze eingeben
A23: 0683.07 BSK-Hanauer-Landstraße-147-149-Ffm | B23: ● (p) Fortschr. BSK Teilumnutzung Souterrain als Kantine | C23: Pauschale | D23: ⚠ Manual erforderlich | F23: 0 | G23: =E23-F23 | H23: 0 | I23: 0 | J23: 0 | K23: Stundensätze eingeben
A24: 0683.07 BSK-Hanauer-Landstraße-147-149-Ffm | B24: ● (a.N.) Abstimmung Genehmigungsbehörden | C24: Nachweis | D24: ⚠ Manual erforderlich | F24: 0 | G24: =E24-F24 | K24: Stundensätze eingeben
A25: 0683.07 BSK-Hanauer-Landstraße-147-149-Ffm | B25: ● (a.N.) BAB | C25: Nachweis | D25: ⚠ Manual erforderlich | F25: 0 | G25: =E25-F25 | K25: Stundensätze eingeben
A26: 0710.01 Zeilpavillon-Zeil-104-Frankfurt-Weidenhof | B26: ● 2000-Vorplanung | C26: Unbekannt | D26: ⚠ Manual erforderlich | F26: 0 | G26: =E26-F26 | K26: Abrechnungsart wählen; Stundensätze eingeben
A27: 0757.17 Patrizia GrundInvest Objekt Hofheim GmbH & Co. KG | B27: ● (aN) Pos.1 KOF Umnutzung Fitnessstudio | C27: Nachweis | D27: ⚠ Manual erforderlich | F27: 0 | G27: =E27-F27 | K27: Stundensätze eingeben
A28: 0757.19 GermanReal-BST-Chinon-Platz-Hofheim-Chinon-Center-Eiswagen | B28: ● (aN) Pos.1 BST bezüglich des Eiswagens am Chinon Center | C28: Nachweis | D28: ⚠ Manual erforderlich | F28: 0 | G28: =E28-F28 | K28: Stundensätze eingeben
A29: 0815.07 Beratung-MPI-Hirnforschung-Ffm | B29: ● 3000-Entwurfsplanung | C29: Unbekannt | D29: ⚠ Manual erforderlich | F29: 0 | G29: =E29-F29 | K29: Abrechnungsart wählen; Stundensätze eingeben
A30: 0815.09 MPI-BTB-Z-HIRN-Umbau-Max-von-Laue-Str4-FFM | B30: ● (aN) Pos. 1 Brandschutztechnische Beratung in der Planungsphase | C30: Nachweis | D30: ⚠ Manual erforderlich | F30: 0 | G30: =E30-F30 | K30: Stundensätze eingeben
A31: 0815.10 MPI-Fortschr-BSK-Z-HIRN-Umbau-Tierhaus-Max-von-Laue-Str4-FFM | B31: ● (p) Pos. 1 Fortschr | C31: Pauschale | D31: ⚠ Manual erforderlich | F31: 0 | G31: =E31-F31 | H31: 0 | I31: 0 | J31: 0 | K31: Stundensätze eingeben
A32: 1015.02 VuBBaWü-BTB-Kurfürstenanlage15-HD-Justizzentrum | B32: ● (aN) 3.1.1.1 Überprüfung des Brandschutzkonzepts und brandschutztechnische Beratung | C32: Nachweis | D32: ⚠ Manual erforderlich | F32: 0 | G32: =E32-F32 | K32: Stundensätze eingeben
A33: 1015.02 VuBBaWü-BTB-Kurfürstenanlage15-HD-Justizzentrum | B33: ● (aN) 3.1.1.2 Begleitung bei der Durchführung der Maßnahmen | C33: Nachweis | D33: ⚠ Manual erforderlich | F33: 0 | G33: =E33-F33 | K33: Stundensätze eingeben
A34: 1015.02 VuBBaWü-BTB-Kurfürstenanlage15-HD-Justizzentrum | B34: ● (p) 3.1.1.3 Fortschreibung des Brandschutzkonzepts bzgl. der Überarbeitung des Sicherheitskonzepts | C34: Pauschale | D34: ⚠ Manual erforderlich | F34: 0 | G34: =E34-F34 | H34: 0 | I34: 0 | J34: 0 | K34: Stundensätze eingeben
A35: 1015.02 VuBBaWü-BTB-Kurfürstenanlage15-HD-Justizzentrum | B35: ● ADM | C35: Unbekannt | D35: ⚠ Manual erforderlich | F35: 0 | G35: =E35-F35 | K35: Abrechnungsart wählen; Stundensätze eingeben
A36: 1123.04 Fortschr.-BSK-U-Bahnstation-Dom-Römer-Frankfurt | B36: ● (p) Pos.1 Fortschr. BSK für Stadtbahnstation Dom/Römer | C36: Pauschale | D36: ⚠ Manual erforderlich | F36: 0 | G36: =E36-F36 | H36: 0 | I36: 0 | J36: 0 | K36: Stundensätze eingeben
A37: 1159.01 Lilienthalstraße-7-Regensburg-EON | B37: ● Beurteilung erhöhter Personenbelegung (pauschal) | C37: Unbekannt | D37: ⚠ Manual erforderlich | F37: 0 | G37: =E37-F37 | K37: Abrechnungsart wählen; Stundensätze eingeben
A38: 1159.01 Lilienthalstraße-7-Regensburg-EON | B38: ● Fortschr. BSK Personenbelegung (pauschal) | C38: Unbekannt | D38: ⚠ Manual erforderlich | F38: 0 | G38: =E38-F38 | K38: Abrechnungsart wählen; Stundensätze eingeben
A39: 1208.04 NT01-BTB-Gymnasium-Riedberg-Friedrich-Dessauer-Str-2-Ffm-Batteriespeicher | B39: ● (aN) Pos.1 BTB zur Abnahme und Bewertung des Batteriespeichers | C39: Nachweis | D39: ⚠ Manual erforderlich | F39: 0 | G39: =E39-F39 | K39: Stundensätze eingeben
A40: 1257.03 LP3-8-Germersheim-Army-Depot-Gebäude-7915 | B40: ● 3000-Entwurfsplanung | C40: Unbekannt | D40: ⚠ Manual erforderlich | F40: 0 | G40: =E40-F40 | K40: Abrechnungsart wählen; Stundensätze eingeben
A41: 1257.03 LP3-8-Germersheim-Army-Depot-Gebäude-7915 | B41: ● 5000-Ausführungsplanung | C41: Unbekannt | D41: ⚠ Manual erforderlich | F41: 0 | G41: =E41-F41 | K41: Abrechnungsart wählen; Stundensätze eingeben
A42: 1257.03 LP3-8-Germersheim-Army-Depot-Gebäude-7915 | B42: ● 8000-Objektüberwachung | C42: Unbekannt | D42: ⚠ Manual erforderlich | F42: 0 | G42: =E42-F42 | K42: Abrechnungsart wählen; Stundensätze eingeben
A43: 1257.03 LP3-8-Germersheim-Army-Depot-Gebäude-7915 | B43: ● Beratung/erneute Einarbeitung (pauschal) | C43: Unbekannt | D43: ⚠ Manual erforderlich | F43: 0 | G43: =E43-F43 | K43: Abrechnungsart wählen; Stundensätze eingeben
A44: 1257.06 Tektur-BSK-Army-Depot-Geb7915-Germersheim | B44: ● (p.) Tektur BSK | C44: Unbekannt | D44: ⚠ Manual erforderlich | F44: 0 | G44: =E44-F44 | K44: Abrechnungsart wählen; Stundensätze eingeben
A45: 1257.06 Tektur-BSK-Army-Depot-Geb7915-Germersheim | B45: ● (p.) FuR | C45: Unbekannt | D45: ⚠ Manual erforderlich | F45: 0 | G45: =E45-F45 | K45: Abrechnungsart wählen; Stundensätze eingeben
A46: 1257.07 Rauchversuch-Army-Depot-Geb7915-Germersheim | B46: ● (p) Durchführung Rauchversuch/Dokumentation | C46: Pauschale | D46: ⚠ Manual erforderlich | F46: 0 | G46: =E46-F46 | H46: 0 | I46: 0 | J46: 0 | K46: Stundensätze eingeben
A47: 1257.08 Elektro-Krück-Überprüfung-FWP-Geb-7915-Germersheim | B47: ● (p) Pos. 1 Feuerwehrpläne | C47: Pauschale | D47: ⚠ Manual erforderlich | F47: 0 | G47: =E47-F47 | H47: 0 | I47: 0 | J47: 0 | K47: Stundensätze eingeben
A48: 1257.08 Elektro-Krück-Überprüfung-FWP-Geb-7915-Germersheim | B48: ● (aN) Pos. 2 Begehung (CAD) | C48: Nachweis | D48: ⚠ Manual erforderlich | F48: 0 | G48: =E48-F48 | K48: Stundensätze eingeben
A49: 1294.01 BSH-Mannheimer-Straße-16-Frankfurt | B49: ● BSO A-C (pauschal) | C49: Unbekannt | D49: ⚠ Manual erforderlich | F49: 0 | G49: =E49-F49 | K49: Abrechnungsart wählen; Stundensätze eingeben
A50: 1294.01 BSH-Mannheimer-Straße-16-Frankfurt | B50: ● FuR-Pläne (pauschal) | C50: Unbekannt | D50: ⚠ Manual erforderlich | F50: 0 | G50: =E50-F50 | K50: Abrechnungsart wählen; Stundensätze eingeben
A51: 1294.01 BSH-Mannheimer-Straße-16-Frankfurt | B51: ● FW-Pläne (pauschal) | C51: Unbekannt | D51: ⚠ Manual erforderlich | F51: 0 | G51: =E51-F51 | K51: Abrechnungsart wählen; Stundensätze eingeben
A52: 1294.01 BSH-Mannheimer-Straße-16-Frankfurt | B52: ● Bestandserfassung (pauschal) | C52: Unbekannt | D52: ⚠ Manual erforderlich | F52: 0 | G52: =E52-F52 | K52: Abrechnungsart wählen; Stundensätze eingeben
A53: 1294.01 BSH-Mannheimer-Straße-16-Frankfurt | B53: ● Räumungsübung (pauschal) | C53: Unbekannt | D53: ⚠ Manual erforderlich | F53: 0 | G53: =E53-F53 | K53: Abrechnungsart wählen; Stundensätze eingeben
A54: 1294.01 BSH-Mannheimer-Straße-16-Frankfurt | B54: ● Helferschulung Theorie + Praxis (pauschal) | C54: Unbekannt | D54: ⚠ Manual erforderlich | F54: 0 | G54: =E54-F54 | K54: Abrechnungsart wählen; Stundensätze eingeben
A55: 1294.08 BSB-2025-Mannheimer-Straße-16-Frankfurt | B55: ● (a.N.) Brandschutzbeauftragter 2025 | C55: Nachweis | D55: ⚠ Manual erforderlich | F55: 0 | G55: =E55-F55 | K55: Stundensätze eingeben
A56: 1406.04 BTB-Ludwig-Erhard-Strasse-6-Eschborn | B56: ● (aN) Pos.1 BTB zu Erstellung der Konformitätsbescheinigung | C56: Nachweis | D56: ⚠ Manual erforderlich | F56: 0 | G56: =E56-F56 | K56: Stundensätze eingeben
A57: 1524.09 BSB-2024-Schützenbleiche-9-11-Frankfurt | B57: ● 9000-Objektbetreuung und Dokumentation | C57: Unbekannt | D57: ⚠ Manual erforderlich | F57: 0 | G57: =E57-F57 | K57: Abrechnungsart wählen; Stundensätze eingeben
A58: 1524.10 BSB-2025-Schützenbleiche-9-11-Frankfurt | B58: ● (aN) Pos.1 Verpflichtung eines externen BSB 2025 | C58: Nachweis | D58: ⚠ Manual erforderlich | F58: 0 | G58: =E58-F58 | K58: Stundensätze eingeben
A59: 1599.13 BSB 2023-IKT-Zanderstraße-7-Frankfurt | B59: ● (a.N.) BSB | C59: Nachweis | D59: ⚠ Manual erforderlich | F59: 0 | G59: =E59-F59 | K59: Stundensätze eingeben
... A74: 1660.07 BTB-Vorstadt-2-Oberursel-Bären-Arkaden-Großraumbüro-1.OG | B74: ● (aN) Pos.1 BTB zu Feuerlöscher und Fluchtwegbeschilderung zum Mieterausbau im 1. OG | C74: Nachweis | D74: ⚠ Manual erforderlich | F74: 0 | G74: =E74-F74 | K74: Stundensätze eingeben
A75: 1686.04 GemLinsengericht-FWP-Hauptstr29-Linsengericht-Bürgersaal | B75: ● (p) Pos. 1 Aktualisierung Feuerwehrpläne | C75: Pauschale | D75: ⚠ Manual erforderlich | F75: 0 | G75: =E75-F75 | H75: 0 | I75: 0 | J75: 0 | K75: Stundensätze eingeben
A76: 1686.04 GemLinsengericht-FWP-Hauptstr29-Linsengericht-Bürgersaal | B76: ● (p) Pos. 2 Aktualisierung der Bestuhlungspläne mit den Varianten 1,2,3,5 | C76: Pauschale | D76: ⚠ Manual erforderlich | F76: 0 | G76: =E76-F76 | H76: 0 | I76: 0 | J76: 0 | K76: Stundensätze eingeben
A77: 1686.04 GemLinsengericht-FWP-Hauptstr29-Linsengericht-Bürgersaal | B77: ● ADM | C77: Unbekannt | D77: ⚠ Manual erforderlich | F77: 0 | G77: =E77-F77 | K77: Abrechnungsart wählen; Stundensätze eingeben
A78: 1732.02 BSK-Europa-Allee-120-126-Ffm-TG | B78: ● (p) Pos.1 Ergänzung des bestehenden BSK zur Installation v. Fluchtwegterminals in Rettungswege | C78: Pauschale | D78: ⚠ Manual erforderlich | F78: 0 | G78: =E78-F78 | H78: 0 | I78: 0 | J78: 0 | K78: Stundensätze eingeben
A79: 1732.02 BSK-Europa-Allee-120-126-Ffm-TG | B79: ● (aN) Pos.2 Baubegl. Brandschutzberatung +Qualitätsüberwachung für d.Durchführung d. BM | C79: Nachweis | D79: ⚠ Manual erforderlich | F79: 0 | G79: =E79-F79 | K79: Stundensätze eingeben
A80: 1732.02 BSK-Europa-Allee-120-126-Ffm-TG | B80: ● (p) Pos.3 Erstellung FWP inkl. Objektbegehung | C80: Pauschale | D80: ⚠ Manual erforderlich | F80: 0 | G80: =E80-F80 | H80: 0 | I80: 0 | J80: 0 | K80: Stundensätze eingeben
A81: 1810.01 BSK-Restnutzung-Bahnhof-Lorch | B81: ● BSK bahnbetriebl. Restnutzung (pauschal) | C81: Unbekannt | D81: ⚠ Manual erforderlich | F81: 0 | G81: =E81-F81 | K81: Abrechnungsart wählen; Stundensätze eingeben
A82: 1810.02 KOF-Bahnhof-Lorch | B82: ● (p) Pos.1 Erstellen Schlussabnahmebescheinigung | C82: Pauschale | D82: ⚠ Manual erforderlich | F82: 0 | G82: =E82-F82 | H82: 0 | I82: 0 | J82: 0 | K82: Stundensätze eingeben
A83: 1834.01 BSK-uPva-Karlsplatz-Mieter10 | B83: ● 3000-Entwurfsplanung | C83: Unbekannt | D83: ⚠ Manual erforderlich | F83: 0 | G83: =E83-F83 | K83: Abrechnungsart wählen; Stundensätze eingeben
A84: 1834.01 BSK-uPva-Karlsplatz-Mieter10 | B84: ● 8000-Objektüberwachung | C84: Unbekannt | D84: ⚠ Manual erforderlich | F84: 0 | G84: =E84-F84 | K84: Abrechnungsart wählen; Stundensätze eingeben
A85: 1834.02 BSK-uPva-Karlsplatz-Mieter10a | B85: ● 3000-Entwurfsplanung | C85: Unbekannt | D85: ⚠ Manual erforderlich | F85: 0 | G85: =E85-F85 | K85: Abrechnungsart wählen; Stundensätze eingeben
A86: 1834.02 BSK-uPva-Karlsplatz-Mieter10a | B86: ● 8000-Objektüberwachung | C86: Unbekannt | D86: ⚠ Manual erforderlich | F86: 0 | G86: =E86-F86 | K86: Abrechnungsart wählen; Stundensätze eingeben
A87: 1914.02 LP5-Fraport-Terminal-T3 | B87: ● 5000-Ausführungsplanung | C87: Unbekannt | D87: ⚠ Manual erforderlich | F87: 0 | G87: =E87-F87 | K87: Abrechnungsart wählen; Stundensätze eingeben
A88: 1914.100 Fraport-Retailer-T3-übergeordnet-NAT107 | B88: ● (p) Pos. 1 Brandschutztechnische Beratung | C88: Pauschale | D88: ⚠ Manual erforderlich | F88: 0 | G88: =E88-F88 | H88: 0 | I88: 0 | J88: 0 | K88: Stundensätze eingeben
A89: 1914.1000 Fraport-Terminal3-div.Nacharbeiten | B89: ● BST Promotionsflächen | C89: Unbekannt | D89: ⚠ Manual erforderlich | F89: 0 | G89: =E89-F89 | K89: Abrechnungsart wählen; Stundensätze eingeben
A90: 1914.1000 Fraport-Terminal3-div.Nacharbeiten | B90: ● BTB Lining | C90: Unbekannt | D90: ⚠ Manual erforderlich | F90: 0 | G90: =E90-F90 | K90: Abrechnungsart wählen; Stundensätze eingeben
A91: 1914.1000 Fraport-Terminal3-div.Nacharbeiten | B91: ● Alarmierung ELA/EAN T3 | C91: Unbekannt | D91: ⚠ Manual erforderlich | F91: 0 | G91: =E91-F91 | K91: Abrechnungsart wählen; Stundensätze eingeben
A92: 1914.1000 Fraport-Terminal3-div.Nacharbeiten | B92: ● Projektassistenz | C92: Unbekannt | D92: ⚠ Manual erforderlich | F92: 0 | G92: =E92-F92 | K92: Abrechnungsart wählen; Stundensätze eingeben
A93: 1914.1000 Fraport-Terminal3-div.Nacharbeiten | B93: ● Parkhaus | C93: Unbekannt | D93: ⚠ Manual erforderlich | F93: 0 | G93: =E93-F93 | K93: Abrechnungsart wählen; Stundensätze eingeben
A94: 1914.1000 Fraport-Terminal3-div.Nacharbeiten | B94: ● ORAT Brandschutz | C94: Unbekannt | D94: ⚠ Manual erforderlich | F94: 0 | G94: =E94-F94 | K94: Abrechnungsart wählen; Stundensätze eingeben
A95: 1914.1000 Fraport-Terminal3-div.Nacharbeiten | B95: ● Nachbearbeitung Rauchversuche | C95: Unbekannt | D95: ⚠ Manual erforderlich | F95: 0 | G95: =E95-F95 | K95: Abrechnungsart wählen; Stundensätze eingeben
A96: 1914.1000 Fraport-Terminal3-div.Nacharbeiten | B96: ● Aufstellung BBA Bereiche | C96: Unbekannt | D96: ⚠ Manual erforderlich | F96: 0 | G96: =E96-F96 | K96: Abrechnungsart wählen; Stundensätze eingeben
A97: 1914.1000 Fraport-Terminal3-div.Nacharbeiten | B97: ● PTS - Fluchtwegbeschilderung | C97: Unbekannt | D97: ⚠ Manual erforderlich | F97: 0 | G97: =E97-F97 | K97: Abrechnungsart wählen; Stundensätze eingeben
A98: 1914.1000 Fraport-Terminal3-div.Nacharbeiten | B98: ● E-Wagenstellplätze THG + PTS | C98: Unbekannt | D98: ⚠ Manual erforderlich | F98: 0 | G98: =E98-F98 | K98: Abrechnungsart wählen; Stundensätze eingeben
A99: 1914.1000 Fraport-Terminal3-div.Nacharbeiten | B99: ● Umbauten Airline-Büros | C99: Unbekannt | D99: ⚠ Manual erforderlich | F99: 0 | G99: =E99-F99 | K99: Abrechnungsart wählen; Stundensätze eingeben
A100: 1914.101 Retailer-T3-Lagardère Travel Retail Deutschland GmbH | B100: ● (aN) Brandschutztechnische Beratung | C100: Nachweis | D100: ⚠ Manual erforderlich | F100: 0 | G100: =E100-F100 | K100: Stundensätze eingeben
... A115: 1914.105_1 Retailer-BAB-Sunglass-Hut-T3-Luxottica | B115: ● (aN) BAB | C115: Nachweis | D115: ⚠ Manual erforderlich | F115: 0 | G115: =E115-F115 | K115: Stundensätze eingeben
A116: 1914.105_1 Retailer-BAB-Sunglass-Hut-T3-Luxottica | B116: ● (p) Admin | C116: Pauschale | D116: ⚠ Manual erforderlich | F116: 0 | G116: =E116-F116 | H116: 0 | I116: 0 | J116: 0 | K116: Stundensätze eingeben
A117: 1914.106 Retailer-Global-Blue | B117: ● (aN) Brandschutztechnische Beratung | C117: Nachweis | D117: ⚠ Manual erforderlich | F117: 0 | G117: =E117-F117 | K117: Stundensätze eingeben
A118: 1914.106 Retailer-Global-Blue | B118: ● (aN) Erstellung Brandschutztechnische Stellungnahme | C118: Nachweis | D118: ⚠ Manual erforderlich | F118: 0 | G118: =E118-F118 | K118: Stundensätze eingeben
A119: 1914.106 Retailer-Global-Blue | B119: ● (aN) Teilnahme an Besprechungen | C119: Nachweis | D119: ⚠ Manual erforderlich | F119: 0 | G119: =E119-F119 | K119: Stundensätze eingeben
A120: 1914.107 Retailer-Ganter-Interior-GmbH-Longchamp | B120: ● (aN) Brandschutztechnische Beratung | C120: Nachweis | D120: ⚠ Manual erforderlich | F120: 0 | G120: =E120-F120 | K120: Stundensätze eingeben
A121: 1914.107 Retailer-Ganter-Interior-GmbH-Longchamp | B121: ● (aN) Erstellung Brandschutztechnische Stellungnahme | C121: Nachweis | D121: ⚠ Manual erforderlich | F121: 0 | G121: =E121-F121 | K121: Stundensätze eingeben
A122: 1914.107 Retailer-Ganter-Interior-GmbH-Longchamp | B122: ● (aN) Teilnahme an Besprechungen | C122: Nachweis | D122: ⚠ Manual erforderlich | F122: 0 | G122: =E122-F122 | K122: Stundensätze eingeben
A123: 1914.107_1 Retailer-BAB-Ganter-Interior-GmbH-Longchamp | B123: ● (aN) BAB | C123: Nachweis | D123: ⚠ Manual erforderlich | F123: 0 | G123: =E123-F123 | K123: Stundensätze eingeben
A124: 1914.107_1 Retailer-BAB-Ganter-Interior-GmbH-Longchamp | B124: ● (p) Admin | C124: Pauschale | D124: ⚠ Manual erforderlich | F124: 0 | G124: =E124-F124 | H124: 0 | I124: 0 | J124: 0 | K124: Stundensätze eingeben
A125: 1914.108 Retailer-Sixt | B125: ● (aN) Brandschutztechnische Beratung | C125: Nachweis | D125: ⚠ Manual erforderlich | F125: 0 | G125: =E125-F125 | K125: Stundensätze eingeben
A126: 1914.108 Retailer-Sixt | B126: ● (aN) Erstellung Brandschutztechnische Stellungnahme | C126: Nachweis | D126: ⚠ Manual erforderlich | F126: 0 | G126: =E126-F126 | K126: Stundensätze eingeben
A127: 1914.108 Retailer-Sixt | B127: ● (aN) Teilnahme an Besprechungen | C127: Nachweis | D127: ⚠ Manual erforderlich | F127: 0 | G127: =E127-F127 | K127: Stundensätze eingeben
A128: 1914.109 Retailer-Avolta | B128: ● ANG BTB (aN) Brandschutztechnische Beratung | C128: Nachweis | D128: ⚠ Manual erforderlich | F128: 0 | G128: =E128-F128 | K128: Stundensätze eingeben
A129: 1914.109 Retailer-Avolta | B129: ● ANG BTB (aN) Erstellung Brandschutztechnische Stellungnahme | C129: Nachweis | D129: ⚠ Manual erforderlich | F129: 0 | G129: =E129-F129 | K129: Stundensätze eingeben
A130: 1914.109 Retailer-Avolta | B130: ● ANG BTB (aN) Teilnahme an Besprechungen | C130: Nachweis | D130: ⚠ Manual erforderlich | F130: 0 | G130: =E130-F130 | K130: Stundensätze eingeben
...

Sheet A. Kokott
A1: A. Kokott - Quartalsreport 2025Q3
A2: Position: | B2: SV
A4: --- Juli 2025 ---
A5: Projekt | B5: Meilenstein | C5: Typ | D5: Soll (h) | E5: Ist (h) | F5: Juli 2025 (h) | G5: % | H5: Bonus-Anpassung (h) | I5: Differenz (h) | J5: Zuordnen an | K5: Von anderen (h) | L5: Stundensatz (€/h) | M5: Umsatz (€) | N5: Budget Gesamt (€) | O5: Budget Ist (€) | P5: Budget Erwirtschaftet (€)
A6: 0000 Sonderprojekt für Bonus | B6: Angebote-Ausschreibungen-Kalkulationen (max. 8h/Monat pro MA) | C6: M | D6: 8 | E6: 8 | F6: 8 | G6: 100 | I6: =IF(H6=0,"",F6-H6) | K6: =IF('D. Brucker'!J6="A. Kokott",'D. Brucker'!I6,0)+IF('E. Bieler'!J6="A. Kokott",'E. Bieler'!I6,0)+IF('J. Dorchies'!J6="A. Kokott",'J. Dorchies'!I6,0)+IF('O. Haag BS-CAD'!J6="A. Kokott",'O. Haag BS-CAD'!I6,0)+IF('S. Schüler'!J6="A. Kokott",'S. Schüler'!I6,0)+IF('T. Trautmann'!J6="A. Kokott",'T. Trautmann'!I6,0)+IF('U. Sutter ADM'!J6="A. Kokott",'U. Sutter ADM'!I6,0) | L6: =IF($B$2="-","",IF($B$2="Pauschale",IFERROR(INDEX('Projekt-Budget-Übersicht'!$H:$H,MATCH(A6,'Projekt-Budget-Übersicht'!$A:$A,0)),""),IF($B$2="SV",IFERROR(INDEX('Projekt-Budget-Übersicht'!$H:$H,MATCH(A6,'Projekt-Budget-Übersicht'!$A:$A,0)),""),IF($B$2="CAD",IFERROR(INDEX('Projekt-Budget-Übersicht'!$I:$I,MATCH(A6,'Projekt-Budget-Übersicht'!$A:$A,0)),""),IF($B$2="ADM",IFERROR(INDEX('Projekt-Budget-Übersicht'!$J:$J,MATCH(A6,'Projekt-Budget-Übersicht'!$A:$A,0)),""),""))))) | M6: =IF($B$2="-","",L6*(F6+I6+K6)) | N6: =IFERROR(INDEX('Projekt-Budget-Übersicht'!$E:$E,MATCH(A6,'Projekt-Budget-Übersicht'!$A:$A,0)),"")
B7: Einarbeitung neuer Mitarbeiter (max. 8h/Monat pro MA) | C7: M | D7: 8 | E7: 8 | F7: 8 | G7: 100 | I7: =IF(H7=0,"",F7-H7) | K7: =IF('C. Trapp SV'!J6="A. Kokott",'C. Trapp SV'!I6,0)+IF('D. Brucker'!J7="A. Kokott",'D. Brucker'!I7,0)+IF('E. Bieler'!J7="A. Kokott",'E. Bieler'!I7,0)+IF('J. Dorchies'!J7="A. Kokott",'J. Dorchies'!I7,0)+IF('J. Dorn'!J6="A. Kokott",'J. Dorn'!I6,0)+IF('M. Bandlofsky'!J6="A. Kokott",'M. Bandlofsky'!I6,0)+IF('T. Trautmann'!J7="A. Kokott",'T. Trautmann'!I7,0)+IF('U. Sutter ADM'!J7="A. Kokott",'U. Sutter ADM'!I7,0) | L7: =IF($B$2="-","",IF($B$2="Pauschale",IFERROR(INDEX('Projekt-Budget-Übersicht'!$H:$H,MATCH(A7,'Projekt-Budget-Übersicht'!$A:$A,0)),""),IF($B$2="SV",IFERROR(INDEX('Projekt-Budget-Übersicht'!$H:$H,MATCH(A7,'Projekt-Budget-Übersicht'!$A:$A,0)),""),IF($B$2="CAD",IFERROR(INDEX('Projekt-Budget-Übersicht'!$I:$I,MATCH(A7,'Projekt-Budget-Übersicht'!$A:$A,0)),""),IF($B$2="ADM",IFERROR(INDEX('Projekt-Budget-Übersicht'!$J:$J,MATCH(A7,'Projekt-Budget-Übersicht'!$A:$A,0)),""),""))))) | M7: =IF($B$2="-","",L7*(F7+I7+K7)) | N7: =IFERROR(INDEX('Projekt-Budget-Übersicht'!$E:$E,MATCH(A7,'Projekt-Budget-Übersicht'!$A:$A,0)),"")
A8: 0014 Urlaubstage | B8: 0001-Stunden ohne Leistungsphase | C8: G | D8: 0 | E8: 0 | F8: 50 | G8: 0 | I8: =IF(H8=0,"",F8-H8) | K8: 0 | L8: =IF($B$2="-","",IF($B$2="Pauschale",IFERROR(INDEX('Projekt-Budget-Übersicht'!$H:$H,MATCH(A8,'Projekt-Budget-Übersicht'!$A:$A,0)),""),IF($B$2="SV",IFERROR(INDEX('Projekt-Budget-Übersicht'!$H:$H,MATCH(A8,'Projekt-Budget-Übersicht'!$A:$A,0)),""),IF($B$2="CAD",IFERROR(INDEX('Projekt-Budget-Übersicht'!$I:$I,MATCH(A8,'Projekt-Budget-Übersicht'!$A:$A,0)),""),IF($B$2="ADM",IFERROR(INDEX('Projekt-Budget-Übersicht'!$J:$J,MATCH(A8,'Projekt-Budget-Übersicht'!$A:$A,0)),""),""))))) | M8: =IF($B$2="-","",L8*(F8+I8+K8)) | N8: =IFERROR(INDEX('Projekt-Budget-Übersicht'!$E:$E,MATCH(A8,'Projekt-Budget-Übersicht'!$A:$A,0)),"")
A9: 3869.24 KES-BST-1.OG-Bestandsgebäude-Marktstr1-3-Stuttgart | B9: ADM | C9: G | D9: 1 | E9: 1.25 | F9: 0.5 | G9: 125 | I9: =IF(H9=0,"",F9-H9) | K9: 0 | L9: =IF($B$2="-","",IF($B$2="Pauschale",IFERROR(INDEX('Projekt-Budget-Übersicht'!$H:$H,MATCH(A9,'Projekt-Budget-Übersicht'!$A:$A,0)),""),IF($B$2="SV",IFERROR(INDEX('Projekt-Budget-Übersicht'!$H:$H,MATCH(A9,'Projekt-Budget-Übersicht'!$A:$A,0)),""),IF($B$2="CAD",IFERROR(INDEX('Projekt-Budget-Übersicht'!$I:$I,MATCH(A9,'Projekt-Budget-Übersicht'!$A:$A,0)),""),IF($B$2="ADM",IFERROR(INDEX('Projekt-Budget-Übersicht'!$J:$J,MATCH(A9,'Projekt-Budget-Übersicht'!$A:$A,0)),""),""))))) | M9: =IF($B$2="-","",L9*(F9+I9+K9)) | N9: =IFERROR(INDEX('Projekt-Budget-Übersicht'!$E:$E,MATCH(A9,'Projekt-Budget-Übersicht'!$A:$A,0)),"")
A10: 5607.05 BAB-NB-J4-Zentralinstitut-für-seelische-Gesundheit-Mannheim | B10: 3100-Erarbeiten des Brandschutzkonzept/Nachweis/Stellungnahme | C10: G | D10: 29.75 | E10: 79.75 | F10: 0.5 | G10: 268.07 | I10: =IF(H10=0,"",F10-H10) | K10: 0 | L10: =IF($B$2="-","",IF($B$2="Pauschale",IFERROR(INDEX('Projekt-Budget-Übersicht'!$H:$H,MATCH(A10,'Projekt-Budget-Übersicht'!$A:$A,0)),""),IF($B$2="SV",IFERROR(INDEX('Projekt-Budget-Übersicht'!$H:$H,MATCH(A10,'Projekt-Budget-Übersicht'!$A:$A,0)),""),IF($B$2="CAD",IFERROR(INDEX('Projekt-Budget-Übersicht'!$I:$I,MATCH(A10,'Projekt-Budget-Übersicht'!$A:$A,0)),""),IF($B$2="ADM",IFERROR(INDEX('Projekt-Budget-Übersicht'!$J:$J,MATCH(A10,'Projekt-Budget-Übersicht'!$A:$A,0)),""),""))))) | M10: =IF($B$2="-","",L10*(F10+I10+K10)) | N10: =IFERROR(INDEX('Projekt-Budget-Übersicht'!$E:$E,MATCH(A10,'Projekt-Budget-Übersicht'!$A:$A,0)),"")
A11: 5640.12 Swisslife-BTB-BSK-HCIII-Salutem-4.OG-Eppelheimerstr8-Heidelberg | B11: CAD | C11: G | D11: 6 | E11: 2.75 | F11: 0.5 | G11: 45.83 | I11: =IF(H11=0,"",F11-H11) | K11: 0 | L11: =IF($B$2="-","",IF($B$2="Pauschale",IFERROR(INDEX('Projekt-Budget-Übersicht'!$H:$H,MATCH(A11,'Projekt-Budget-Übersicht'!$A:$A,0)),""),IF($B$2="SV",IFERROR(INDEX('Projekt-Budget-Übersicht'!$H:$H,MATCH(A11,'Projekt-Budget-Übersicht'!$A:$A,0)),""),IF($B$2="CAD",IFERROR(INDEX('Projekt-Budget-Übersicht'!$I:$I,MATCH(A11,'Projekt-Budget-Übersicht'!$A:$A,0)),""),IF($B$2="ADM",IFERROR(INDEX('Projekt-Budget-Übersicht'!$J:$J,MATCH(A11,'Projekt-Budget-Übersicht'!$A:$A,0)),""),""))))) | M11: =IF($B$2="-","",L11*(F11+I11+K11)) | N11: =IFERROR(INDEX('Projekt-Budget-Übersicht'!$E:$E,MATCH(A11,'Projekt-Budget-Übersicht'!$A:$A,0)),"")
A12: 5793.03 StadtFB-Eschholzstr118-Freiburg-Rettungszentrum-Halle-E | B12: (aN) Pos. 1 Brandschutztechnische Beratung | C12: G | D12: 20 | E12: 1.75 | F12: 0.5 | G12: 8.75 | I12: =IF(H12=0,"",F12-H12) | K12: 0 | L12: =IF($B$2="-","",IF($B$2="Pauschale",IFERROR(INDEX('Projekt-Budget-Übersicht'!$H:$H,MATCH(A12,'Projekt-Budget-Übersicht'!$A:$A,0)),""),IF($B$2="SV",IFERROR(INDEX('Projekt-Budget-Übersicht'!$H:$H,MATCH(A12,'Projekt-Budget-Übersicht'!$A:$A,0)),""),IF($B$2="CAD",IFERROR(INDEX('Projekt-Budget-Übersicht'!$I:$I,MATCH(A12,'Projekt-Budget-Übersicht'!$A:$A,0)),""),IF($B$2="ADM",IFERROR(INDEX('Projekt-Budget-Übersicht'!$J:$J,MATCH(A12,'Projekt-Budget-Übersicht'!$A:$A,0)),""),""))))) | M12: =IF($B$2="-","",L12*(F12+I12+K12)) | N12: =IFERROR(INDEX('Projekt-Budget-Übersicht'!$E:$E,MATCH(A12,'Projekt-Budget-Übersicht'!$A:$A,0)),"")
A13: 5984.01 QE-WEA-Windpark-Lusshardt-Überarbeitung-BSK | B13: ADM | C13: G | D13: 1 | E13: 1.25 | F13: 0.5 | G13: 125 | I13: =IF(H13=0,"",F13-H13) | K13: 0 | L13: =IF($B$2="-","",IF($B$2="Pauschale",IFERROR(INDEX('Projekt-Budget-Übersicht'!$H:$H,MATCH(A13,'Projekt-Budget-Übersicht'!$A:$A,0)),""),IF($B$2="SV",IFERROR(INDEX('Projekt-Budget-Übersicht'!$H:$H,MATCH(A13,'Projekt-Budget-Übersicht'!$A:$A,0)),""),IF($B$2="CAD",IFERROR(INDEX('Projekt-Budget-Übersicht'!$I:$I,MATCH(A13,'Projekt-Budget-Übersicht'!$A:$A,0)),""),IF($B$2="ADM",IFERROR(INDEX('Projekt-Budget-Übersicht'!$J:$J,MATCH(A13,'Projekt-Budget-Übersicht'!$A:$A,0)),""),""))))) | M13: =IF($B$2="-","",L13*(F13+I13+K13)) | N13: =IFERROR(INDEX('Projekt-Budget-Übersicht'!$E:$E,MATCH(A13,'Projekt-Budget-Übersicht'!$A:$A,0)),"")
A14: 6527.01 IO-Anp-BSK-Mühlenfeldstr1-Holzminden-Symotion | B14: SV | C14: G | D14: 6 | E14: 33.75 | F14: 0.25 | G14: 562.5 | I14: =IF(H14=0,"",F14-H14) | K14: =IF('E. Bieler'!J20="A. Kokott",'E. Bieler'!I20,0)+IF('J. Dorchies'!J9="A. Kokott",'J. Dorchies'!I9,0)+IF('J. Dorn'!J23="A. Kokott",'J. Dorn'!I23,0)+IF('P. Bergner'!J7="A. Kokott",'P. Bergner'!I7,0)+IF('R. Böttiger'!J13="A. Kokott",'R. Böttiger'!I13,0) | L14: =IF($B$2="-","",IF($B$2="Pauschale",IFERROR(INDEX('Projekt-Budget-Übersicht'!$H:$H,MATCH(A14,'Projekt-Budget-Übersicht'!$A:$A,0)),""),IF($B$2="SV",IFERROR(INDEX('Projekt-Budget-Übersicht'!$H:$H,MATCH(A14,'Projekt-Budget-Übersicht'!$A:$A,0)),""),IF($B$2="CAD",IFERROR(INDEX('Projekt-Budget-Übersicht'!$I:$I,MATCH(A14,'Projekt-Budget-Übersicht'!$A:$A,0)),""),IF($B$2="ADM",IFERROR(INDEX('Projekt-Budget-Übersicht'!$J:$J,MATCH(A14,'Projekt-Budget-Übersicht'!$A:$A,0)),""),""))))) | M14: =IF($B$2="-","",L14*(F14+I14+K14)) | N14: =IFERROR(INDEX('Projekt-Budget-Übersicht'!$E:$E,MATCH(A14,'Projekt-Budget-Übersicht'!$A:$A,0)),"")
A15: 6769.01 Juwi-Anp-BSK-Selser-Berg | B15: (p) Anp. BSK | C15: G | D15: 2 | E15: 3.5 | F15: 0.5 | G15: 175 | I15: =IF(H15=0,"",F15-H15) | K15: =IF('H. Bektas'!J6="A. Kokott",'H. Bektas'!I6,0) | L15: =IF($B$2="-","",IF($B$2="Pauschale",IFERROR(INDEX('Projekt-Budget-Übersicht'!$H:$H,MATCH(A15,'Projekt-Budget-Übersicht'!$A:$A,0)),""),IF($B$2="SV",IFERROR(INDEX('Projekt-Budget-Übersicht'!$H:$H,MATCH(A15,'Projekt-Budget-Übersicht'!$A:$A,0)),""),IF($B$2="CAD",IFERROR(INDEX('Projekt-Budget-Übersicht'!$I:$I,MATCH(A15,'Projekt-Budget-Übersicht'!$A:$A,0)),""),IF($B$2="ADM",IFERROR(INDEX('Projekt-Budget-Übersicht'!$J:$J,MATCH(A15,'Projekt-Budget-Übersicht'!$A:$A,0)),""),""))))) | M15: =IF($B$2="-","",L15*(F15+I15+K15)) | N15: =IFERROR(INDEX('Projekt-Budget-Übersicht'!$E:$E,MATCH(A15,'Projekt-Budget-Übersicht'!$A:$A,0)),"")
A16: 6961.01 Neptune-Rheinhafen-Speyer-allgemeineBeratungsleistungen | B16: (aN) BTB (SV) | C16: G | D16: 68 | E16: 47.25 | F16: 0.5 | G16: 69.49 | I16: =IF(H16=0,"",F16-H16) | K16: =IF('H. Bektas'!J7="A. Kokott",'H. Bektas'!I7,0) | L16: =IF($B$2="-","",IF($B$2="Pauschale",IFERROR(INDEX('Projekt-Budget-Übersicht'!$H:$H,MATCH(A16,'Projekt-Budget-Übersicht'!$A:$A,0)),""),IF($B$2="SV",IFERROR(INDEX('Projekt-Budget-Übersicht'!$H:$H,MATCH(A16,'Projekt-Budget-Übersicht'!$A:$A,0)),""),IF($B$2="CAD",IFERROR(INDEX('Projekt-Budget-Übersicht'!$I:$I,MATCH(A16,'Projekt-Budget-Übersicht'!$A:$A,0)),""),IF($B$2="ADM",IFERROR(INDEX('Projekt-Budget-Übersicht'!$J:$J,MATCH(A16,'Projekt-Budget-Übersicht'!$A:$A,0)),""),""))))) | M16: =IF($B$2="-","",L16*(F16+I16+K16)) | N16: =IFERROR(INDEX('Projekt-Budget-Übersicht'!$E:$E,MATCH(A16,'Projekt-Budget-Übersicht'!$A:$A,0)),"")
A17: 7015.02 HeyLagerGmbH-BAB-Garagenpark-Alzenau | B17: ADM | C17: G | D17: 1 | E17: 1.25 | F17: 0.5 | G17: 125 | I17: =IF(H17=0,"",F17-H17) | K17: 0 | L17: =IF($B$2="-","",IF($B$2="Pauschale",IFERROR(INDEX('Projekt-Budget-Übersicht'!$H:$H,MATCH(A17,'Projekt-Budget-Übersicht'!$A:$A,0)),""),IF($B$2="SV",IFERROR(INDEX('Projekt-Budget-Übersicht'!$H:$H,MATCH(A17,'Projekt-Budget-Übersicht'!$A:$A,0)),""),IF($B$2="CAD",IFERROR(INDEX('Projekt-Budget-Übersicht'!$I:$I,MATCH(A17,'Projekt-Budget-Übersicht'!$A:$A,0)),""),IF($B$2="ADM",IFERROR(INDEX('Projekt-Budget-Übersicht'!$J:$J,MATCH(A17,'Projekt-Budget-Übersicht'!$A:$A,0)),""),""))))) | M17: =IF($B$2="-","",L17*(F17+I17+K17)) | N17: =IFERROR(INDEX('Projekt-Budget-Übersicht'!$E:$E,MATCH(A17,'Projekt-Budget-Übersicht'!$A:$A,0)),"")
A18: 7090.01 Baupionier-BSK-Garagenpark-Eckersmühlen | B18: ADM | C18: G | D18: 1 | E18: 1.75 | F18: 0.25 | G18: 175 | I18: =IF(H18=0,"",F18-H18) | K18: 0 | L18: =IF($B$2="-","",IF($B$2="Pauschale",IFERROR(INDEX('Projekt-Budget-Übersicht'!$H:$H,MATCH(A18,'Projekt-Budget-Übersicht'!$A:$A,0)),""),IF($B$2="SV",IFERROR(INDEX('Projekt-Budget-Übersicht'!$H:$H,MATCH(A18,'Projekt-Budget-Übersicht'!$A:$A,0)),""),IF($B$2="CAD",IFERROR(INDEX('Projekt-Budget-Übersicht'!$I:$I,MATCH(A18,'Projekt-Budget-Übersicht'!$A:$A,0)),""),IF($B$2="ADM",IFERROR(INDEX('Projekt-Budget-Übersicht'!$J:$J,MATCH(A18,'Projekt-Budget-Übersicht'!$A:$A,0)),""),""))))) | M18: =IF($B$2="-","",L18*(F18+I18+K18)) | N18: =IFERROR(INDEX('Projekt-Budget-Übersicht'!$E:$E,MATCH(A18,'Projekt-Budget-Übersicht'!$A:$A,0)),"")
B19: SV | C19: G | D19: 12 | E19: 15.5 | F19: 0.5 | G19: 129.17 | I19: =IF(H19=0,"",F19-H19) | K19: 0 | L19: =IF($B$2="-","",IF($B$2="Pauschale",IFERROR(INDEX('Projekt-Budget-Übersicht'!$H:$H,MATCH(A19,'Projekt-Budget-Übersicht'!$A:$A,0)),""),IF($B$2="SV",IFERROR(INDEX('Projekt-Budget-Übersicht'!$H:$H,MATCH(A19,'Projekt-Budget-Übersicht'!$A:$A,0)),""),IF($B$2="CAD",IFERROR(INDEX('Projekt-Budget-Übersicht'!$I:$I,MATCH(A19,'Projekt-Budget-Übersicht'!$A:$A,0)),""),IF($B$2="ADM",IFERROR(INDEX('Projekt-Budget-Übersicht'!$J:$J,MATCH(A19,'Projekt-Budget-Übersicht'!$A:$A,0)),""),""))))) | M19: =IF($B$2="-","",L19*(F19+I19+K19)) | N19: =IFERROR(INDEX('Projekt-Budget-Übersicht'!$E:$E,MATCH(A19,'Projekt-Budget-Übersicht'!$A:$A,0)),"")
A20: 7247.01 Hoepfner-BST-Zentrale-Karlsruhe | B20: 0100-Anlage Projekt, Angebot, Versand, Auftrag | C20: G | D20: 1 | E20: 2 | F20: 1 | G20: 200 | I20: =IF(H20=0,"",F20-H20) | K20: 0 | L20: =IF($B$2="-","",IF($B$2="Pauschale",IFERROR(INDEX('Projekt-Budget-Übersicht'!$H:$H,MATCH(A20,'Projekt-Budget-Übersicht'!$A:$A,0)),""),IF($B$2="SV",IFERROR(INDEX('Projekt-Budget-Übersicht'!$H:$H,MATCH(A20,'Projekt-Budget-Übersicht'!$A:$A,0)),""),IF($B$2="CAD",IFERROR(INDEX('Projekt-Budget-Übersicht'!$I:$I,MATCH(A20,'Projekt-Budget-Übersicht'!$A:$A,0)),""),IF($B$2="ADM",IFERROR(INDEX('Projekt-Budget-Übersicht'!$J:$J,MATCH(A20,'Projekt-Budget-Übersicht'!$A:$A,0)),""),""))))) | M20: =IF($B$2="-","",L20*(F20+I20+K20)) | N20: =IFERROR(INDEX('Projekt-Budget-Übersicht'!$E:$E,MATCH(A20,'Projekt-Budget-Übersicht'!$A:$A,0)),"")
A21: 7293 VEW-BSK-WEA-Hopperkopf | B21: ADM | C21: G | D21: 1 | E21: 1.75 | F21: 0.5 | G21: 175 | I21: =IF(H21=0,"",F21-H21) | K21: 0 | L21: =IF($B$2="-","",IF($B$2="Pauschale",IFERROR(INDEX('Projekt-Budget-Übersicht'!$H:$H,MATCH(A21,'Projekt-Budget-Übersicht'!$A:$A,0)),""),IF($B$2="SV",IFERROR(INDEX('Projekt-Budget-Übersicht'!$H:$H,MATCH(A21,'Projekt-Budget-Übersicht'!$A:$A,0)),""),IF($B$2="CAD",IFERROR(INDEX('Projekt-Budget-Übersicht'!$I:$I,MATCH(A21,'Projekt-Budget-Übersicht'!$A:$A,0)),""),IF($B$2="ADM",IFERROR(INDEX('Projekt-Budget-Übersicht'!$J:$J,MATCH(A21,'Projekt-Budget-Übersicht'!$A:$A,0)),""),""))))) | M21: =IF($B$2="-","",L21*(F21+I21+K21)) | N21: =IFERROR(INDEX('Projekt-Budget-Übersicht'!$E:$E,MATCH(A21,'Projekt-Budget-Übersicht'!$A:$A,0)),"")
A22: 7422 Energieprojekte-DK-BSK-WEA-Aschbach-Ilmenau | B22: ADM | C22: G | D22: 1 | E22: 1.25 | F22: 0.5 | G22: 125 | I22: =IF(H22=0,"",F22-H22) | K22: 0 | L22: =IF($B$2="-","",IF($B$2="Pauschale",IFERROR(INDEX('Projekt-Budget-Übersicht'!$H:$H,MATCH(A22,'Projekt-Budget-Übersicht'!$A:$A,0)),""),IF($B$2="SV",IFERROR(INDEX('Projekt-Budget-Übersicht'!$H:$H,MATCH(A22,'Projekt-Budget-Übersicht'!$A:$A,0)),""),IF($B$2="CAD",IFERROR(INDEX('Projekt-Budget-Übersicht'!$I:$I,MATCH(A22,'Projekt-Budget-Übersicht'!$A:$A,0)),""),IF($B$2="ADM",IFERROR(INDEX('Projekt-Budget-Übersicht'!$J:$J,MATCH(A22,'Projekt-Budget-Übersicht'!$A:$A,0)),""),""))))) | M22: =IF($B$2="-","",L22*(F22+I22+K22)) | N22: =IFERROR(INDEX('Projekt-Budget-Übersicht'!$E:$E,MATCH(A22,'Projekt-Budget-Übersicht'!$A:$A,0)),"")
A23: 7435 wiwi-BSK-WEA-Spiesheim-Wörrstadt-Ost | B23: ADM | C23: G | D23: 1 | E23: 2 | F23: 0.5 | G23: 200 | I23: =IF(H23=0,"",F23-H23) | K23: 0 | L23: =IF($B$2="-","",IF($B$2="Pauschale",IFERROR(INDEX('Projekt-Budget-Übersicht'!$H:$H,MATCH(A23,'Projekt-Budget-Übersicht'!$A:$A,0)),""),IF($B$2="SV",IFERROR(INDEX('Projekt-Budget-Übersicht'!$H:$H,MATCH(A23,'Projekt-Budget-Übersicht'!$A:$A,0)),""),IF($B$2="CAD",IFERROR(INDEX('Projekt-Budget-Übersicht'!$I:$I,MATCH(A23,'Projekt-Budget-Übersicht'!$A:$A,0)),""),IF($B$2="ADM",IFERROR(INDEX('Projekt-Budget-Übersicht'!$J:$J,MATCH(A23,'Projekt-Budget-Übersicht'!$A:$A,0)),""),""))))) | M23: =IF($B$2="-","",L23*(F23+I23+K23)) | N23: =IFERROR(INDEX('Projekt-Budget-Übersicht'!$E:$E,MATCH(A23,'Projekt-Budget-Übersicht'!$A:$A,0)),"")
A24: 7437 MVV-BSK-UW3-Käfertal-Mannheim | B24: Anlage Projekt, Angebot, Versand, Auftrag | C24: G | D24: 1 | E24: 2 | F24: 0.5 | G24: 200 | I24: =IF(H24=0,"",F24-H24) | K24: 0 | L24: =IF($B$2="-","",IF($B$2="Pauschale",IFERROR(INDEX('Projekt-Budget-Übersicht'!$H:$H,MATCH(A24,'Projekt-Budget-Übersicht'!$A:$A,0)),""),IF($B$2="SV",IFERROR(INDEX('Projekt-Budget-Übersicht'!$H:$H,MATCH(A24,'Projekt-Budget-Übersicht'!$A:$A,0)),""),IF($B$2="CAD",IFERROR(INDEX('Projekt-Budget-Übersicht'!$I:$I,MATCH(A24,'Projekt-Budget-Übersicht'!$A:$A,0)),""),IF($B$2="ADM",IFERROR(INDEX('Projekt-Budget-Übersicht'!$J:$J,MATCH(A24,'Projekt-Budget-Übersicht'!$A:$A,0)),""),""))))) | M24: =IF($B$2="-","",L24*(F24+I24+K24)) | N24: =IFERROR(INDEX('Projekt-Budget-Übersicht'!$E:$E,MATCH(A24,'Projekt-Budget-Übersicht'!$A:$A,0)),"")
A25: 7441 Baupionier-Garagenpark-Öhringen-BSK | B25: ADM | C25: G | D25: 1 | E25: 2.25 | F25: 1 | G25: 225 | I25: =IF(H25=0,"",F25-H25) | K25: 0 | L25: =IF($B$2="-","",IF($B$2="Pauschale",IFERROR(INDEX('Projekt-Budget-Übersicht'!$H:$H,MATCH(A25,'Projekt-Budget-Übersicht'!$A:$A,0)),""),IF($B$2="SV",IFERROR(INDEX('Projekt-Budget-Übersicht'!$H:$H,MATCH(A25,'Projekt-Budget-Übersicht'!$A:$A,0)),""),IF($B$2="CAD",IFERROR(INDEX('Projekt-Budget-Übersicht'!$I:$I,MATCH(A25,'Projekt-Budget-Übersicht'!$A:$A,0)),""),IF($B$2="ADM",IFERROR(INDEX('Projekt-Budget-Übersicht'!$J:$J,MATCH(A25,'Projekt-Budget-Übersicht'!$A:$A,0)),""),""))))) | M25: =IF($B$2="-","",L25*(F25+I25+K25)) | N25: =IFERROR(INDEX('Projekt-Budget-Übersicht'!$E:$E,MATCH(A25,'Projekt-Budget-Übersicht'!$A:$A,0)),"")
A26: 7444 Energieprojekte-DK-BSK-WEA-Schußbachwald | B26: ADM | C26: G | D26: 1 | E26: 1.25 | F26: 0.5 | G26: 125 | I26: =IF(H26=0,"",F26-H26) | K26: 0 | L26: =IF($B$2="-","",IF($B$2="Pauschale",IFERROR(INDEX('Projekt-Budget-Übersicht'!$H:$H,MATCH(A26,'Projekt-Budget-Übersicht'!$A:$A,0)),""),IF($B$2="SV",IFERROR(INDEX('Projekt-Budget-Übersicht'!$H:$H,MATCH(A26,'Projekt-Budget-Übersicht'!$A:$A,0)),""),IF($B$2="CAD",IFERROR(INDEX('Projekt-Budget-Übersicht'!$I:$I,MATCH(A26,'Projekt-Budget-Übersicht'!$A:$A,0)),""),IF($B$2="ADM",IFERROR(INDEX('Projekt-Budget-Übersicht'!$J:$J,MATCH(A26,'Projekt-Budget-Übersicht'!$A:$A,0)),""),""))))) | M26: =IF($B$2="-","",L26*(F26+I26+K26)) | N26: =IFERROR(INDEX('Projekt-Budget-Übersicht'!$E:$E,MATCH(A26,'Projekt-Budget-Übersicht'!$A:$A,0)),"")
A27: 7445 Energieprojekte-DK-BSK-WEA-Thüngersheim | B27: ADM | C27: G | D27: 1 | E27: 1.25 | F27: 0.5 | G27: 125 | I27: =IF(H27=0,"",F27-H27) | K27: 0 | L27: =IF($B$2="-","",IF($B$2="Pauschale",IFERROR(INDEX('Projekt-Budget-Übersicht'!$H:$H,MATCH(A27,'Projekt-Budget-Übersicht'!$A:$A,0)),""),IF($B$2="SV",IFERROR(INDEX('Projekt-Budget-Übersicht'!$H:$H,MATCH(A27,'Projekt-Budget-Übersicht'!$A:$A,0)),""),IF($B$2="CAD",IFERROR(INDEX('Projekt-Budget-Übersicht'!$I:$I,MATCH(A27,'Projekt-Budget-Übersicht'!$A:$A,0)),""),IF($B$2="ADM",IFERROR(INDEX('Projekt-Budget-Übersicht'!$J:$J,MATCH(A27,'Projekt-Budget-Übersicht'!$A:$A,0)),""),""))))) | M27: =IF($B$2="-","",L27*(F27+I27+K27)) | N27: =IFERROR(INDEX('Projekt-Budget-Übersicht'!$E:$E,MATCH(A27,'Projekt-Budget-Übersicht'!$A:$A,0)),"")
A28: 7448 Seniorenresidenz-Sonnenwinkel-BSH-Im-Füllengarten14-16-Saarbrücken | B28: ADM | C28: G | D28: 5 | E28: 1.25 | F28: 0.5 | G28: 25 | I28: =IF(H28=0,"",F28-H28) | K28: 0 | L28: =IF($B$2="-","",IF($B$2="Pauschale",IFERROR(INDEX('Projekt-Budget-Übersicht'!$H:$H,MATCH(A28,'Projekt-Budget-Übersicht'!$A:$A,0)),""),IF($B$2="SV",IFERROR(INDEX('Projekt-Budget-Übersicht'!$H:$H,MATCH(A28,'Projekt-Budget-Übersicht'!$A:$A,0)),""),IF($B$2="CAD",IFERROR(INDEX('Projekt-Budget-Übersicht'!$I:$I,MATCH(A28,'Projekt-Budget-Übersicht'!$A:$A,0)),""),IF($B$2="ADM",IFERROR(INDEX('Projekt-Budget-Übersicht'!$J:$J,MATCH(A28,'Projekt-Budget-Übersicht'!$A:$A,0)),""),""))))) | M28: =IF($B$2="-","",L28*(F28+I28+K28)) | N28: =IFERROR(INDEX('Projekt-Budget-Übersicht'!$E:$E,MATCH(A28,'Projekt-Budget-Übersicht'!$A:$A,0)),"")
A29: 7459 Baupionier-BTB-Prüfung-Details-Garagenparks | B29: 0100-Anlage Projekt, Angebot, Versand, Auftrag | C29: G | D29: 1 | E29: 1.25 | F29: 0.5 | G29: 125 | I29: =IF(H29=0,"",F29-H29) | K29: 0 | L29: =IF($B$2="-","",IF($B$2="Pauschale",IFERROR(INDEX('Projekt-Budget-Übersicht'!$H:$H,MATCH(A29,'Projekt-Budget-Übersicht'!$A:$A,0)),""),IF($B$2="SV",IFERROR(INDEX('Projekt-Budget-Übersicht'!$H:$H,MATCH(A29,'Projekt-Budget-Übersicht'!$A:$A,0)),""),IF($B$2="CAD",IFERROR(INDEX('Projekt-Budget-Übersicht'!$I:$I,MATCH(A29,'Projekt-Budget-Übersicht'!$A:$A,0)),""),IF($B$2="ADM",IFERROR(INDEX('Projekt-Budget-Übersicht'!$J:$J,MATCH(A29,'Projekt-Budget-Übersicht'!$A:$A,0)),""),""))))) | M29: =IF($B$2="-","",L29*(F29+I29+K29)) | N29: =IFERROR(INDEX('Projekt-Budget-Übersicht'!$E:$E,MATCH(A29,'Projekt-Budget-Übersicht'!$A:$A,0)),"")
B30: 3100-Erarbeiten des Brandschutzkonzept/Nachweis/Stellungnahme | C30: G | D30: 14 | E30: 15.5 | F30: 0.5 | G30: 110.71 | I30: =IF(H30=0,"",F30-H30) | K30: =IF('E. Bieler'!J38="A. Kokott",'E. Bieler'!I38,0)+IF('M. Bandlofsky'!J17="A. Kokott",'M. Bandlofsky'!I17,0) | L30: =IF($B$2="-","",IF($B$2="Pauschale",IFERROR(INDEX('Projekt-Budget-Übersicht'!$H:$H,MATCH(A30,'Projekt-Budget-Übersicht'!$A:$A,0)),""),IF($B$2="SV",IFERROR(INDEX('Projekt-Budget-Übersicht'!$H:$H,MATCH(A30,'Projekt-Budget-Übersicht'!$A:$A,0)),""),IF($B$2="CAD",IFERROR(INDEX('Projekt-Budget-Übersicht'!$I:$I,MATCH(A30,'Projekt-Budget-Übersicht'!$A:$A,0)),""),IF($B$2="ADM",IFERROR(INDEX('Projekt-Budget-Übersicht'!$J:$J,MATCH(A30,'Projekt-Budget-Übersicht'!$A:$A,0)),""),""))))) | M30: =IF($B$2="-","",L30*(F30+I30+K30)) | N30: =IFERROR(INDEX('Projekt-Budget-Übersicht'!$E:$E,MATCH(A30,'Projekt-Budget-Übersicht'!$A:$A,0)),"")
B31: Summe | F31: 77.5
B32: Bonusberechtigte Stunden | F32: =G32+H32 | G32: 52 | H32: =SUM(H8,H9,H10,H11,H12,H13,H14,H15,H16,H17,H18,H19,H20,H21,H22,H23,H24,H25,H26,H27,H28,H29,H30)
B33: Bonusberechtigte Stunden Sonderprojekt | F33: =G33+H33 | G33: 16 | H33: =SUM(H6,H7)
B34: Zugeordnete Stunden von anderen MA | F34: =SUM(K6:K30)
B35: Gesamt Bonus Stunden | F35: =F32+F33+F34
A37: --- August 2025 ---
A38: Projekt | B38: Meilenstein | C38: Typ | D38: Soll (h) | E38: Ist (h) | F38: August 2025 (h) | G38: % | H38: Bonus-Anpassung (h) | I38: Differenz (h) | J38: Zuordnen an | K38: Von anderen (h) | L38: Stundensatz (€/h) | M38: Umsatz (€) | N38: Budget Gesamt (€) | O38: Budget Ist (€) | P38: Budget Erwirtschaftet (€)
A39: 0000 Sonderprojekt für Bonus | B39: Angebote-Ausschreibungen-Kalkulationen (max. 8h/Monat pro MA) | C39: M | D39: 8 | E39: 8 | F39: 8 | G39: 100 | I39: =IF(H39=0,"",F39-H39) | K39: =IF('J. Dorn'!J45="A. Kokott",'J. Dorn'!I45,0)+IF('O. Haag BS-CAD'!J51="A. Kokott",'O. Haag BS-CAD'!I51,0)+IF('P. Bergner'!J21="A. Kokott",'P. Bergner'!I21,0)+IF('R. Böttiger'!J31="A. Kokott",'R. Böttiger'!I31,0)+IF('T. Trautmann'!J28="A. Kokott",'T. Trautmann'!I28,0)+IF('U. Sutter ADM'!J28="A. Kokott",'U. Sutter ADM'!I28,0) | L39: =IF($B$2="-","",IF($B$2="Pauschale",IFERROR(INDEX('Projekt-Budget-Übersicht'!$H:$H,MATCH(A39,'Projekt-Budget-Übersicht'!$A:$A,0)),""),IF($B$2="SV",IFERROR(INDEX('Projekt-Budget-Übersicht'!$H:$H,MATCH(A39,'Projekt-Budget-Übersicht'!$A:$A,0)),""),IF($B$2="CAD",IFERROR(INDEX('Projekt-Budget-Übersicht'!$I:$I,MATCH(A39,'Projekt-Budget-Übersicht'!$A:$A,0)),""),IF($B$2="ADM",IFERROR(INDEX('Projekt-Budget-Übersicht'!$J:$J,MATCH(A39,'Projekt-Budget-Übersicht'!$A:$A,0)),""),""))))) | M39: =IF($B$2="-","",L39*(F39+I39+K39)) | N39: =IFERROR(INDEX('Projekt-Budget-Übersicht'!$E:$E,MATCH(A39,'Projekt-Budget-Übersicht'!$A:$A,0)),"")
B40: Einarbeitung neuer Mitarbeiter (max. 8h/Monat pro MA) | C40: M | D40: 8 | E40: 3 | F40: 3 | G40: 37.5 | I40: =IF(H40=0,"",F40-H40) | K40: =IF('M. Bandlofsky'!J26="A. Kokott",'M. Bandlofsky'!I26,0)+IF('O. Haag BS-CAD'!J52="A. Kokott",'O. Haag BS-CAD'!I52,0)+IF('P. Bergner'!J22="A. Kokott",'P. Bergner'!I22,0)+IF('R. Wagen CAD'!J31="A. Kokott",'R. Wagen CAD'!I31,0)+IF('T. Trautmann'!J29="A. Kokott",'T. Trautmann'!I29,0)+IF('U. Sutter ADM'!J29="A. Kokott",'U. Sutter ADM'!I29,0) | L40: =IF($B$2="-","",IF($B$2="Pauschale",IFERROR(INDEX('Projekt-Budget-Übersicht'!$H:$H,MATCH(A40,'Projekt-Budget-Übersicht'!$A:$A,0)),""),IF($B$2="SV",IFERROR(INDEX('Projekt-Budget-Übersicht'!$H:$H,MATCH(A40,'Projekt-Budget-Übersicht'!$A:$A,0)),""),IF($B$2="CAD",IFERROR(INDEX('Projekt-Budget-Übersicht'!$I:$I,MATCH(A40,'Projekt-Budget-Übersicht'!$A:$A,0)),""),IF($B$2="ADM",IFERROR(INDEX('Projekt-Budget-Übersicht'!$J:$J,MATCH(A40,'Projekt-Budget-Übersicht'!$A:$A,0)),""),""))))) | M40: =IF($B$2="-","",L40*(F40+I40+K40)) | N40: =IFERROR(INDEX('Projekt-Budget-Übersicht'!$E:$E,MATCH(A40,'Projekt-Budget-Übersicht'!$A:$A,0)),"")
A41: 2032.061 aam2core-FRP-Halbergstraße1-LU | B41: ADM | C41: G | D41: 1 | E41: 1.25 | F41: 0.5 | G41: 125 | I41: =IF(H41=0,"",F41-H41) | K41: 0 | L41: =IF($B$2="-","",IF($B$2="Pauschale",IFERROR(INDEX('Projekt-Budget-Übersicht'!$H:$H,MATCH(A41,'Projekt-Budget-Übersicht'!$A:$A,0)),""),IF($B$2="SV",IFERROR(INDEX('Projekt-Budget-Übersicht'!$H:$H,MATCH(A41,'Projekt-Budget-Übersicht'!$A:$A,0)),""),IF($B$2="CAD",IFERROR(INDEX('Projekt-Budget-Übersicht'!$I:$I,MATCH(A41,'Projekt-Budget-Übersicht'!$A:$A,0)),""),IF($B$2="ADM",IFERROR(INDEX('Projekt-Budget-Übersicht'!$J:$J,MATCH(A41,'Projekt-Budget-Übersicht'!$A:$A,0)),""),""))))) | M41: =IF($B$2="-","",L41*(F41+I41+K41)) | N41: =IFERROR(INDEX('Projekt-Budget-Übersicht'!$E:$E,MATCH(A41,'Projekt-Budget-Übersicht'!$A:$A,0)),"")
A42: 3258.30 Öztürk-FRP-DQ-Pilates-Studio-Marktstr1-3-Stuttgart | B42: ADM | C42: G | D42: 1 | E42: 1.25 | F42: 0.5 | G42: 125 | I42: =IF(H42=0,"",F42-H42) | K42: 0 | L42: =IF($B$2="-","",IF($B$2="Pauschale",IFERROR(INDEX('Projekt-Budget-Übersicht'!$H:$H,MATCH(A42,'Projekt-Budget-Übersicht'!$A:$A,0)),""),IF($B$2="SV",IFERROR(INDEX('Projekt-Budget-Übersicht'!$H:$H,MATCH(A42,'Projekt-Budget-Übersicht'!$A:$A,0)),""),IF($B$2="CAD",IFERROR(INDEX('Projekt-Budget-Übersicht'!$I:$I,MATCH(A42,'Projekt-Budget-Übersicht'!$A:$A,0)),""),IF($B$2="ADM",IFERROR(INDEX('Projekt-Budget-Übersicht'!$J:$J,MATCH(A42,'Projekt-Budget-Übersicht'!$A:$A,0)),""),""))))) | M42: =IF($B$2="-","",L42*(F42+I42+K42)) | N42: =IFERROR(INDEX('Projekt-Budget-Übersicht'!$E:$E,MATCH(A42,'Projekt-Budget-Übersicht'!$A:$A,0)),"")
A43: 3943.06 TFD-BSK-EuropePlaza-Innere-Wiener-Straße17-München | B43: 3100-Erarbeiten des Brandschutzkonzept/Nachweis/Stellungnahme | C43: G | D43: 0 | E43: 0 | F43: 0.25 | G43: 0 | I43: =IF(H43=0,"",F43-H43) | K43: 0 | L43: =IF($B$2="-","",IF($B$2="Pauschale",IFERROR(INDEX('Projekt-Budget-Übersicht'!$H:$H,MATCH(A43,'Projekt-Budget-Übersicht'!$A:$A,0)),""),IF($B$2="SV",IFERROR(INDEX('Projekt-Budget-Übersicht'!$H:$H,MATCH(A43,'Projekt-Budget-Übersicht'!$A:$A,0)),""),IF($B$2="CAD",IFERROR(INDEX('Projekt-Budget-Übersicht'!$I:$I,MATCH(A43,'Projekt-Budget-Übersicht'!$A:$A,0)),""),IF($B$2="ADM",IFERROR(INDEX('Projekt-Budget-Übersicht'!$J:$J,MATCH(A43,'Projekt-Budget-Übersicht'!$A:$A,0)),""),""))))) | M43: =IF($B$2="-","",L43*(F43+I43+K43)) | N43: =IFERROR(INDEX('Projekt-Budget-Übersicht'!$E:$E,MATCH(A43,'Projekt-Budget-Übersicht'!$A:$A,0)),"")
A44: 4249.12 Apleona-BSK-Geb10+11-Am-Keltenwald-Ehningen | B44: ADM | C44: G | D44: 1 | E44: 3 | F44: 0.5 | G44: 300 | I44: =IF(H44=0,"",F44-H44) | K44: 0 | L44: =IF($B$2="-","",IF($B$2="Pauschale",IFERROR(INDEX('Projekt-Budget-Übersicht'!$H:$H,MATCH(A44,'Projekt-Budget-Übersicht'!$A:$A,0)),""),IF($B$2="SV",IFERROR(INDEX('Projekt-Budget-Übersicht'!$H:$H,MATCH(A44,'Projekt-Budget-Übersicht'!$A:$A,0)),""),IF($B$2="CAD",IFERROR(INDEX('Projekt-Budget-Übersicht'!$I:$I,MATCH(A44,'Projekt-Budget-Übersicht'!$A:$A,0)),""),IF($B$2="ADM",IFERROR(INDEX('Projekt-Budget-Übersicht'!$J:$J,MATCH(A44,'Projekt-Budget-Übersicht'!$A:$A,0)),""),""))))) | M44: =IF($B$2="-","",L44*(F44+I44+K44)) | N44: =IFERROR(INDEX('Projekt-Budget-Übersicht'!$E:$E,MATCH(A44,'Projekt-Budget-Übersicht'!$A:$A,0)),"")
A45: 4436.043 FWP-NA003-KKH-Bergstraße-Viernheimer-Straße-2-Heppenheim-Bauphase+NB-BauteilG | B45: 9200-Erstellen od. Prüfen Feuerwehrpläne…. | C45: G | D45: 230 | E45: 31.75 | F45: 0.25 | G45: 13.8 | I45: =IF(H45=0,"",F45-H45) | K45: =IF('M. Warner'!J8="A. Kokott",'M. Warner'!I8,0)+IF('S. Schüler'!J62="A. Kokott",'S. Schüler'!I62,0) | L45: =IF($B$2="-","",IF($B$2="Pauschale",IFERROR(INDEX('Projekt-Budget-Übersicht'!$H:$H,MATCH(A45,'Projekt-Budget-Übersicht'!$A:$A,0)),""),IF($B$2="SV",IFERROR(INDEX('Projekt-Budget-Übersicht'!$H:$H,MATCH(A45,'Projekt-Budget-Übersicht'!$A:$A,0)),""),IF($B$2="CAD",IFERROR(INDEX('Projekt-Budget-Übersicht'!$I:$I,MATCH(A45,'Projekt-Budget-Übersicht'!$A:$A,0)),""),IF($B$2="ADM",IFERROR(INDEX('Projekt-Budget-Übersicht'!$J:$J,MATCH(A45,'Projekt-Budget-Übersicht'!$A:$A,0)),""),""))))) | M45: =IF($B$2="-","",L45*(F45+I45+K45)) | N45: =IFERROR(INDEX('Projekt-Budget-Übersicht'!$E:$E,MATCH(A45,'Projekt-Budget-Übersicht'!$A:$A,0)),"")
A46: 5395.04 Burkhardt-Witteler-BSK-Gesundheitszentrum-Industriestr17-Ladenburg | B46: ADM | C46: G | D46: 1 | E46: 1.75 | F46: 1 | G46: 175 | I46: =IF(H46=0,"",F46-H46) | K46: 0 | L46: =IF($B$2="-","",IF($B$2="Pauschale",IFERROR(INDEX('Projekt-Budget-Übersicht'!$H:$H,MATCH(A46,'Projekt-Budget-Übersicht'!$A:$A,0)),""),IF($B$2="SV",IFERROR(INDEX('Projekt-Budget-Übersicht'!$H:$H,MATCH(A46,'Projekt-Budget-Übersicht'!$A:$A,0)),""),IF($B$2="CAD",IFERROR(INDEX('Projekt-Budget-Übersicht'!$I:$I,MATCH(A46,'Projekt-Budget-Übersicht'!$A:$A,0)),""),IF($B$2="ADM",IFERROR(INDEX('Projekt-Budget-Übersicht'!$J:$J,MATCH(A46,'Projekt-Budget-Übersicht'!$A:$A,0)),""),""))))) | M46: =IF($B$2="-","",L46*(F46+I46+K46)) | N46: =IFERROR(INDEX('Projekt-Budget-Übersicht'!$E:$E,MATCH(A46,'Projekt-Budget-Übersicht'!$A:$A,0)),"")
A47: 5607.05 BAB-NB-J4-Zentralinstitut-für-seelische-Gesundheit-Mannheim | B47: (p) NAT03-Bestandsaufnahme (Ist-Aufnahme) | C47: G | D47: 32 | E47: 51.75 | F47: 0.5 | G47: 161.72 | I47: =IF(H47=0,"",F47-H47) | K47: =IF('C. Trapp SV'!J39="A. Kokott",'C. Trapp SV'!I39,0)+IF('S. Roßkopf'!J7="A. Kokott",'S. Roßkopf'!I7,0) | L47: =IF($B$2="-","",IF($B$2="Pauschale",IFERROR(INDEX('Projekt-Budget-Übersicht'!$H:$H,MATCH(A47,'Projekt-Budget-Übersicht'!$A:$A,0)),""),IF($B$2="SV",IFERROR(INDEX('Projekt-Budget-Übersicht'!$H:$H,MATCH(A47,'Projekt-Budget-Übersicht'!$A:$A,0)),""),IF($B$2="CAD",IFERROR(INDEX('Projekt-Budget-Übersicht'!$I:$I,MATCH(A47,'Projekt-Budget-Übersicht'!$A:$A,0)),""),IF($B$2="ADM",IFERROR(INDEX('Projekt-Budget-Übersicht'!$J:$J,MATCH(A47,'Projekt-Budget-Übersicht'!$A:$A,0)),""),""))))) | M47: =IF($B$2="-","",L47*(F47+I47+K47)) | N47: =IFERROR(INDEX('Projekt-Budget-Übersicht'!$E:$E,MATCH(A47,'Projekt-Budget-Übersicht'!$A:$A,0)),"")
B48: 9101-Fortschreibung Brandschutzkonzept…. | C48: G | D48: 14.25 | E48: 53.25 | F48: 0.5 | G48: 373.68 | I48: =IF(H48=0,"",F48-H48) | K48: =IF('S. Schüler'!J64="A. Kokott",'S. Schüler'!I64,0) | L48: =IF($B$2="-","",IF($B$2="Pauschale",IFERROR(INDEX('Projekt-Budget-Übersicht'!$H:$H,MATCH(A48,'Projekt-Budget-Übersicht'!$A:$A,0)),""),IF($B$2="SV",IFERROR(INDEX('Projekt-Budget-Übersicht'!$H:$H,MATCH(A48,'Projekt-Budget-Übersicht'!$A:$A,0)),""),IF($B$2="CAD",IFERROR(INDEX('Projekt-Budget-Übersicht'!$I:$I,MATCH(A48,'Projekt-Budget-Übersicht'!$A:$A,0)),""),IF($B$2="ADM",IFERROR(INDEX('Projekt-Budget-Übersicht'!$J:$J,MATCH(A48,'Projekt-Budget-Übersicht'!$A:$A,0)),""),""))))) | M48: =IF($B$2="-","",L48*(F48+I48+K48)) | N48: =IFERROR(INDEX('Projekt-Budget-Übersicht'!$E:$E,MATCH(A48,'Projekt-Budget-Übersicht'!$A:$A,0)),"")
A49: 5664.19 (5667.04) KOB-BAB-Umbau-Sprinkleranlage-Lauterstr50-Wolfstein | B49: 3100-Erarbeiten des Brandschutzkonzept/Nachweis/Stellungnahme (SV) | C49: G | D49: 16 | E49: 18 | F49: 0.25 | G49: 112.5 | I49: =IF(H49=0,"",F49-H49) | K49: =IF('J. Dorn'!J51="A. Kokott",'J. Dorn'!I51,0)+IF('T. Trautmann'!J41="A. Kokott",'T. Trautmann'!I41,0) | L49: =IF($B$2="-","",IF($B$2="Pauschale",IFERROR(INDEX('Projekt-Budget-Übersicht'!$H:$H,MATCH(A49,'Projekt-Budget-Übersicht'!$A:$A,0)),""),IF($B$2="SV",IFERROR(INDEX('Projekt-Budget-Übersicht'!$H:$H,MATCH(A49,'Projekt-Budget-Übersicht'!$A:$A,0)),""),IF($B$2="CAD",IFERROR(INDEX('Projekt-Budget-Übersicht'!$I:$I,MATCH(A49,'Projekt-Budget-Übersicht'!$A:$A,0)),""),IF($B$2="ADM",IFERROR(INDEX('Projekt-Budget-Übersicht'!$J:$J,MATCH(A49,'Projekt-Budget-Übersicht'!$A:$A,0)),""),""))))) | M49: =IF($B$2="-","",L49*(F49+I49+K49)) | N49: =IFERROR(INDEX('Projekt-Budget-Übersicht'!$E:$E,MATCH(A49,'Projekt-Budget-Übersicht'!$A:$A,0)),"")
A50: 6313.02 BSK+BAB-Otto-Volger-Straße-Sulzbach-Limespark | B50: 4103-Erarbeiten Brandschutzkonzeptpläne…. | C50: G | D50: 100 | E50: 101.5 | F50: 0.75 | G50: 101.5 | I50: =IF(H50=0,"",F50-H50) | K50: 0 | L50: =IF($B$2="-","",IF($B$2="Pauschale",IFERROR(INDEX('Projekt-Budget-Übersicht'!$H:$H,MATCH(A50,'Projekt-Budget-Übersicht'!$A:$A,0)),""),IF($B$2="SV",IFERROR(INDEX('Projekt-Budget-Übersicht'!$H:$H,MATCH(A50,'Projekt-Budget-Übersicht'!$A:$A,0)),""),IF($B$2="CAD",IFERROR(INDEX('Projekt-Budget-Übersicht'!$I:$I,MATCH(A50,'Projekt-Budget-Übersicht'!$A:$A,0)),""),IF($B$2="ADM",IFERROR(INDEX('Projekt-Budget-Übersicht'!$J:$J,MATCH(A50,'Projekt-Budget-Übersicht'!$A:$A,0)),""),""))))) | M50: =IF($B$2="-","",L50*(F50+I50+K50)) | N50: =IFERROR(INDEX('Projekt-Budget-Übersicht'!$E:$E,MATCH(A50,'Projekt-Budget-Übersicht'!$A:$A,0)),"")
A51: 6649.03 formica-Anp-BSK-Otto-Hahn-Str-Hilden-Laer | B51: SV | C51: G | D51: 0 | E51: -1 | F51: 0.5 | G51: 0 | I51: =IF(H51=0,"",F51-H51) | K51: =IF('J. Dorn'!J64="A. Kokott",'J. Dorn'!I64,0)+IF('T. Trautmann'!J50="A. Kokott",'T. Trautmann'!I50,0) | L51: =IF($B$2="-","",IF($B$2="Pauschale",IFERROR(INDEX('Projekt-Budget-Übersicht'!$H:$H,MATCH(A51,'Projekt-Budget-Übersicht'!$A:$A,0)),""),IF($B$2="SV",IFERROR(INDEX('Projekt-Budget-Übersicht'!$H:$H,MATCH(A51,'Projekt-Budget-Übersicht'!$A:$A,0)),""),IF($B$2="CAD",IFERROR(INDEX('Projekt-Budget-Übersicht'!$I:$I,MATCH(A51,'Projekt-Budget-Übersicht'!$A:$A,0)),""),IF($B$2="ADM",IFERROR(INDEX('Projekt-Budget-Übersicht'!$J:$J,MATCH(A51,'Projekt-Budget-Übersicht'!$A:$A,0)),""),""))))) | M51: =IF($B$2="-","",L51*(F51+I51+K51)) | N51: =IFERROR(INDEX('Projekt-Budget-Übersicht'!$E:$E,MATCH(A51,'Projekt-Budget-Übersicht'!$A:$A,0)),"")
A52: 6712.011 Züblin-Strabag-NA02-LP5-BTB-Waldstr6-10-Weiterstadt | B52: 5000-Ausführungsplanung | C52: G | D52: 25 | E52: 3.25 | F52: 0.5 | G52: 13 | I52: =IF(H52=0,"",F52-H52) | K52: =IF('P. Bergner'!J32="A. Kokott",'P. Bergner'!I32,0) | L52: =IF($B$2="-","",IF($B$2="Pauschale",IFERROR(INDEX('Projekt-Budget-Übersicht'!$H:$H,MATCH(A52,'Projekt-Budget-Übersicht'!$A:$A,0)),""),IF($B$2="SV",IFERROR(INDEX('Projekt-Budget-Übersicht'!$H:$H,MATCH(A52,'Projekt-Budget-Übersicht'!$A:$A,0)),""),IF($B$2="CAD",IFERROR(INDEX('Projekt-Budget-Übersicht'!$I:$I,MATCH(A52,'Projekt-Budget-Übersicht'!$A:$A,0)),""),IF($B$2="ADM",IFERROR(INDEX('Projekt-Budget-Übersicht'!$J:$J,MATCH(A52,'Projekt-Budget-Übersicht'!$A:$A,0)),""),""))))) | M52: =IF($B$2="-","",L52*(F52+I52+K52)) | N52: =IFERROR(INDEX('Projekt-Budget-Übersicht'!$E:$E,MATCH(A52,'Projekt-Budget-Übersicht'!$A:$A,0)),"")
A53: 7000.01 RES-NAT-BSK-WEA-Oberrot | B53: ADM | C53: G | D53: 1 | E53: 1.25 | F53: 0.5 | G53: 125 | I53: =IF(H53=0,"",F53-H53) | K53: 0 | L53: =IF($B$2="-","",IF($B$2="Pauschale",IFERROR(INDEX('Projekt-Budget-Übersicht'!$H:$H,MATCH(A53,'Projekt-Budget-Übersicht'!$A:$A,0)),""),IF($B$2="SV",IFERROR(INDEX('Projekt-Budget-Übersicht'!$H:$H,MATCH(A53,'Projekt-Budget-Übersicht'!$A:$A,0)),""),IF($B$2="CAD",IFERROR(INDEX('Projekt-Budget-Übersicht'!$I:$I,MATCH(A53,'Projekt-Budget-Übersicht'!$A:$A,0)),""),IF($B$2="ADM",IFERROR(INDEX('Projekt-Budget-Übersicht'!$J:$J,MATCH(A53,'Projekt-Budget-Übersicht'!$A:$A,0)),""),""))))) | M53: =IF($B$2="-","",L53*(F53+I53+K53)) | N53: =IFERROR(INDEX('Projekt-Budget-Übersicht'!$E:$E,MATCH(A53,'Projekt-Budget-Übersicht'!$A:$A,0)),"")
A54: 7272 SW-Tübingen-BSK-WEA-Ostelsheim | B54: ADM | C54: G | D54: 0 | E54: 0 | F54: 0.5 | G54: 0 | I54: =IF(H54=0,"",F54-H54) | K54: 0 | L54: =IF($B$2="-","",IF($B$2="Pauschale",IFERROR(INDEX('Projekt-Budget-Übersicht'!$H:$H,MATCH(A54,'Projekt-Budget-Übersicht'!$A:$A,0)),""),IF($B$2="SV",IFERROR(INDEX('Projekt-Budget-Übersicht'!$H:$H,MATCH(A54,'Projekt-Budget-Übersicht'!$A:$A,0)),""),IF($B$2="CAD",IFERROR(INDEX('Projekt-Budget-Übersicht'!$I:$I,MATCH(A54,'Projekt-Budget-Übersicht'!$A:$A,0)),""),IF($B$2="ADM",IFERROR(INDEX('Projekt-Budget-Übersicht'!$J:$J,MATCH(A54,'Projekt-Budget-Übersicht'!$A:$A,0)),""),""))))) | M54: =IF($B$2="-","",L54*(F54+I54+K54)) | N54: =IFERROR(INDEX('Projekt-Budget-Übersicht'!$E:$E,MATCH(A54,'Projekt-Budget-Übersicht'!$A:$A,0)),"")
A55: 7355.01 Pfizer-BSK-Umnutzung-Mooswaldallee-1-Freiburg-Geb-K | B55: ADM | C55: G | D55: 1 | E55: 1.5 | F55: 0.5 | G55: 150 | I55: =IF(H55=0,"",F55-H55) | K55: 0 | L55: =IF($B$2="-","",IF($B$2="Pauschale",IFERROR(INDEX('Projekt-Budget-Übersicht'!$H:$H,MATCH(A55,'Projekt-Budget-Übersicht'!$A:$A,0)),""),IF($B$2="SV",IFERROR(INDEX('Projekt-Budget-Übersicht'!$H:$H,MATCH(A55,'Projekt-Budget-Übersicht'!$A:$A,0)),""),IF($B$2="CAD",IFERROR(INDEX('Projekt-Budget-Übersicht'!$I:$I,MATCH(A55,'Projekt-Budget-Übersicht'!$A:$A,0)),""),IF($B$2="ADM",IFERROR(INDEX('Projekt-Budget-Übersicht'!$J:$J,MATCH(A55,'Projekt-Budget-Übersicht'!$A:$A,0)),""),""))))) | M55: =IF($B$2="-","",L55*(F55+I55+K55)) | N55: =IFERROR(INDEX('Projekt-Budget-Übersicht'!$E:$E,MATCH(A55,'Projekt-Budget-Übersicht'!$A:$A,0)),"")
A56: 7361 Energieprojekte-DK-BSK-WP-Thalfingen+Repowering-Anlage-Seligweiler-Bayern | B56: ADM | C56: G | D56: 1 | E56: 0.5 | F56: 0.5 | G56: 50 | I56: =IF(H56=0,"",F56-H56) | K56: 0 | L56: =IF($B$2="-","",IF($B$2="Pauschale",IFERROR(INDEX('Projekt-Budget-Übersicht'!$H:$H,MATCH(A56,'Projekt-Budget-Übersicht'!$A:$A,0)),""),IF($B$2="SV",IFERROR(INDEX('Projekt-Budget-Übersicht'!$H:$H,MATCH(A56,'Projekt-Budget-Übersicht'!$A:$A,0)),""),IF($B$2="CAD",IFERROR(INDEX('Projekt-Budget-Übersicht'!$I:$I,MATCH(A56,'Projekt-Budget-Übersicht'!$A:$A,0)),""),IF($B$2="ADM",IFERROR(INDEX('Projekt-Budget-Übersicht'!$J:$J,MATCH(A56,'Projekt-Budget-Übersicht'!$A:$A,0)),""),""))))) | M56: =IF($B$2="-","",L56*(F56+I56+K56)) | N56: =IFERROR(INDEX('Projekt-Budget-Übersicht'!$E:$E,MATCH(A56,'Projekt-Budget-Übersicht'!$A:$A,0)),"")
A57: 7364 SHE-BSK-WP-Göttingen-Baden-Württemberg | B57: ADM | C57: G | D57: 1 | E57: 1.25 | F57: 0.5 | G57: 125 | I57: =IF(H57=0,"",F57-H57) | K57: 0 | L57: =IF($B$2="-","",IF($B$2="Pauschale",IFERROR(INDEX('Projekt-Budget-Übersicht'!$H:$H,MATCH(A57,'Projekt-Budget-Übersicht'!$A:$A,0)),""),IF($B$2="SV",IFERROR(INDEX('Projekt-Budget-Übersicht'!$H:$H,MATCH(A57,'Projekt-Budget-Übersicht'!$A:$A,0)),""),IF($B$2="CAD",IFERROR(INDEX('Projekt-Budget-Übersicht'!$I:$I,MATCH(A57,'Projekt-Budget-Übersicht'!$A:$A,0)),""),IF($B$2="ADM",IFERROR(INDEX('Projekt-Budget-Übersicht'!$J:$J,MATCH(A57,'Projekt-Budget-Übersicht'!$A:$A,0)),""),""))))) | M57: =IF($B$2="-","",L57*(F57+I57+K57)) | N57: =IFERROR(INDEX('Projekt-Budget-Übersicht'!$E:$E,MATCH(A57,'Projekt-Budget-Übersicht'!$A:$A,0)),"")
A58: 7365.01 UI-BST-StGeorgener-Str-2-Freiburg-Breisgaucenter | B58: 3100-Erarbeiten des Brandschutzkonzept/Nachweis/Stellungnahme | C58: G | D58: 20 | E58: 19.25 | F58: 0.5 | G58: 96.25 | I58: =IF(H58=0,"",F58-H58) | K58: =IF('R. Böttiger'!J40="A. Kokott",'R. Böttiger'!I40,0) | L58: =IF($B$2="-","",IF($B$2="Pauschale",IFERROR(INDEX('Projekt-Budget-Übersicht'!$H:$H,MATCH(A58,'Projekt-Budget-Übersicht'!$A:$A,0)),""),IF($B$2="SV",IFERROR(INDEX('Projekt-Budget-Übersicht'!$H:$H,MATCH(A58,'Projekt-Budget-Übersicht'!$A:$A,0)),""),IF($B$2="CAD",IFERROR(INDEX('Projekt-Budget-Übersicht'!$I:$I,MATCH(A58,'Projekt-Budget-Übersicht'!$A:$A,0)),""),IF($B$2="ADM",IFERROR(INDEX('Projekt-Budget-Übersicht'!$J:$J,MATCH(A58,'Projekt-Budget-Übersicht'!$A:$A,0)),""),""))))) | M58: =IF($B$2="-","",L58*(F58+I58+K58)) | N58: =IFERROR(INDEX('Projekt-Budget-Übersicht'!$E:$E,MATCH(A58,'Projekt-Budget-Übersicht'!$A:$A,0)),"")
A59: 7370.02 LAER-formica-BSK-Garagenpark-Willi-Melchers-Straße-Lünen-NB-Hallenreihen | B59: 3100-Erarbeiten des Brandschutzkonzept/Nachweis/Stellungnahme | C59: G | D59: 20 | E59: 21 | F59: 0.5 | G59: 105 | I59: =IF(H59=0,"",F59-H59) | K59: =IF('J. Dorn'!J72="A. Kokott",'J. Dorn'!I72,0) | L59: =IF($B$2="-","",IF($B$2="Pauschale",IFERROR(INDEX('Projekt-Budget-Übersicht'!$H:$H,MATCH(A59,'Projekt-Budget-Übersicht'!$A:$A,0)),""),IF($B$2="SV",IFERROR(INDEX('Projekt-Budget-Übersicht'!$H:$H,MATCH(A59,'Projekt-Budget-Übersicht'!$A:$A,0)),""),IF($B$2="CAD",IFERROR(INDEX('Projekt-Budget-Übersicht'!$I:$I,MATCH(A59,'Projekt-Budget-Übersicht'!$A:$A,0)),""),IF($B$2="ADM",IFERROR(INDEX('Projekt-Budget-Übersicht'!$J:$J,MATCH(A59,'Projekt-Budget-Übersicht'!$A:$A,0)),""),""))))) | M59: =IF($B$2="-","",L59*(F59+I59+K59)) | N59: =IFERROR(INDEX('Projekt-Budget-Übersicht'!$E:$E,MATCH(A59,'Projekt-Budget-Übersicht'!$A:$A,0)),"")
A60: 7380.02 Qualitas-BSK-WEA-Geroldshausen-Uengershausen | B60: ADM | C60: G | D60: 60 | E60: 1 | F60: 1 | G60: 1.67 | I60: =IF(H60=0,"",F60-H60) | K60: 0 | L60: =IF($B$2="-","",IF($B$2="Pauschale",IFERROR(INDEX('Projekt-Budget-Übersicht'!$H:$H,MATCH(A60,'Projekt-Budget-Übersicht'!$A:$A,0)),""),IF($B$2="SV",IFERROR(INDEX('Projekt-Budget-Übersicht'!$H:$H,MATCH(A60,'Projekt-Budget-Übersicht'!$A:$A,0)),""),IF($B$2="CAD",IFERROR(INDEX('Projekt-Budget-Übersicht'!$I:$I,MATCH(A60,'Projekt-Budget-Übersicht'!$A:$A,0)),""),IF($B$2="ADM",IFERROR(INDEX('Projekt-Budget-Übersicht'!$J:$J,MATCH(A60,'Projekt-Budget-Übersicht'!$A:$A,0)),""),""))))) | M60: =IF($B$2="-","",L60*(F60+I60+K60)) | N60: =IFERROR(INDEX('Projekt-Budget-Übersicht'!$E:$E,MATCH(A60,'Projekt-Budget-Übersicht'!$A:$A,0)),"")
A61: 7400 JUWI-WP-div-MST | B61: (p) Pos. 1 Anp. BSK (Best. 4500008752 25-03-20) | C61: G | D61: 10 | E61: 11.5 | F61: 0.5 | G61: 115 | I61: =IF(H61=0,"",F61-H61) | K61: 0 | L61: =IF($B$2="-","",IF($B$2="Pauschale",IFERROR(INDEX('Projekt-Budget-Übersicht'!$H:$H,MATCH(A61,'Projekt-Budget-Übersicht'!$A:$A,0)),""),IF($B$2="SV",IFERROR(INDEX('Projekt-Budget-Übersicht'!$H:$H,MATCH(A61,'Projekt-Budget-Übersicht'!$A:$A,0)),""),IF($B$2="CAD",IFERROR(INDEX('Projekt-Budget-Übersicht'!$I:$I,MATCH(A61,'Projekt-Budget-Übersicht'!$A:$A,0)),""),IF($B$2="ADM",IFERROR(INDEX('Projekt-Budget-Übersicht'!$J:$J,MATCH(A61,'Projekt-Budget-Übersicht'!$A:$A,0)),""),""))))) | M61: =IF($B$2="-","",L61*(F61+I61+K61)) | N61: =IFERROR(INDEX('Projekt-Budget-Übersicht'!$E:$E,MATCH(A61,'Projekt-Budget-Übersicht'!$A:$A,0)),"")
B62: (p) Pos. 1 Anp. BSK gem. RV (Best. 4500010513 25.06.27) | C62: G | D62: 10 | E62: 10 | F62: 0.5 | G62: 100 | I62: =IF(H62=0,"",F62-H62) | K62: 0 | L62: =IF($B$2="-","",IF($B$2="Pauschale",IFERROR(INDEX('Projekt-Budget-Übersicht'!$H:$H,MATCH(A62,'Projekt-Budget-Übersicht'!$A:$A,0)),""),IF($B$2="SV",IFERROR(INDEX('Projekt-Budget-Übersicht'!$H:$H,MATCH(A62,'Projekt-Budget-Übersicht'!$A:$A,0)),""),IF($B$2="CAD",IFERROR(INDEX('Projekt-Budget-Übersicht'!$I:$I,MATCH(A62,'Projekt-Budget-Übersicht'!$A:$A,0)),""),IF($B$2="ADM",IFERROR(INDEX('Projekt-Budget-Übersicht'!$J:$J,MATCH(A62,'Projekt-Budget-Übersicht'!$A:$A,0)),""),""))))) | M62: =IF($B$2="-","",L62*(F62+I62+K62)) | N62: =IFERROR(INDEX('Projekt-Budget-Übersicht'!$E:$E,MATCH(A62,'Projekt-Budget-Übersicht'!$A:$A,0)),"")
A63: 7405 VWPA-BSK-WEA-Hollfeld-Daniel-Koglin | B63: ADM | C63: G | D63: 1 | E63: 1.25 | F63: 0.5 | G63: 125 | I63: =IF(H63=0,"",F63-H63) | K63: 0 | L63: =IF($B$2="-","",IF($B$2="Pauschale",IFERROR(INDEX('Projekt-Budget-Übersicht'!$H:$H,MATCH(A63,'Projekt-Budget-Übersicht'!$A:$A,0)),""),IF($B$2="SV",IFERROR(INDEX('Projekt-Budget-Übersicht'!$H:$H,MATCH(A63,'Projekt-Budget-Übersicht'!$A:$A,0)),""),IF($B$2="CAD",IFERROR(INDEX('Projekt-Budget-Übersicht'!$I:$I,MATCH(A63,'Projekt-Budget-Übersicht'!$A:$A,0)),""),IF($B$2="ADM",IFERROR(INDEX('Projekt-Budget-Übersicht'!$J:$J,MATCH(A63,'Projekt-Budget-Übersicht'!$A:$A,0)),""),""))))) | M63: =IF($B$2="-","",L63*(F63+I63+K63)) | N63: =IFERROR(INDEX('Projekt-Budget-Übersicht'!$E:$E,MATCH(A63,'Projekt-Budget-Übersicht'!$A:$A,0)),"")
A64: 7419.03 Zech-BSO-Sporthalle-Pestalozzistr10-Eppelheim | B64: ADM | C64: G | D64: 1 | E64: 1.25 | F64: 0.5 | G64: 125 | I64: =IF(H64=0,"",F64-H64) | K64: 0 | L64: =IF($B$2="-","",IF($B$2="Pauschale",IFERROR(INDEX('Projekt-Budget-Übersicht'!$H:$H,MATCH(A64,'Projekt-Budget-Übersicht'!$A:$A,0)),""),IF($B$2="SV",IFERROR(INDEX('Projekt-Budget-Übersicht'!$H:$H,MATCH(A64,'Projekt-Budget-Übersicht'!$A:$A,0)),""),IF($B$2="CAD",IFERROR(INDEX('Projekt-Budget-Übersicht'!$I:$I,MATCH(A64,'Projekt-Budget-Übersicht'!$A:$A,0)),""),IF($B$2="ADM",IFERROR(INDEX('Projekt-Budget-Übersicht'!$J:$J,MATCH(A64,'Projekt-Budget-Übersicht'!$A:$A,0)),""),""))))) | M64: =IF($B$2="-","",L64*(F64+I64+K64)) | N64: =IFERROR(INDEX('Projekt-Budget-Übersicht'!$E:$E,MATCH(A64,'Projekt-Budget-Übersicht'!$A:$A,0)),"")
A65: 7422 Energieprojekte-DK-BSK-WEA-Aschbach-Ilmenau | B65: ADM | C65: G | D65: 1 | E65: 2.25 | F65: 1 | G65: 225 | I65: =IF(H65=0,"",F65-H65) | K65: 0 | L65: =IF($B$2="-","",IF($B$2="Pauschale",IFERROR(INDEX('Projekt-Budget-Übersicht'!$H:$H,MATCH(A65,'Projekt-Budget-Übersicht'!$A:$A,0)),""),IF($B$2="SV",IFERROR(INDEX('Projekt-Budget-Übersicht'!$H:$H,MATCH(A65,'Projekt-Budget-Übersicht'!$A:$A,0)),""),IF($B$2="CAD",IFERROR(INDEX('Projekt-Budget-Übersicht'!$I:$I,MATCH(A65,'Projekt-Budget-Übersicht'!$A:$A,0)),""),IF($B$2="ADM",IFERROR(INDEX('Projekt-Budget-Übersicht'!$J:$J,MATCH(A65,'Projekt-Budget-Übersicht'!$A:$A,0)),""),""))))) | M65: =IF($B$2="-","",L65*(F65+I65+K65)) | N65: =IFERROR(INDEX('Projekt-Budget-Übersicht'!$E:$E,MATCH(A65,'Projekt-Budget-Übersicht'!$A:$A,0)),"")
A66: 7435 wiwi-BSK-WEA-Spiesheim-Wörrstadt-Ost | B66: ADM | C66: G | D66: 1 | E66: 2.5 | F66: 0.5 | G66: 250 | I66: =IF(H66=0,"",F66-H66) | K66: 0 | L66: =IF($B$2="-","",IF($B$2="Pauschale",IFERROR(INDEX('Projekt-Budget-Übersicht'!$H:$H,MATCH(A66,'Projekt-Budget-Übersicht'!$A:$A,0)),""),IF($B$2="SV",IFERROR(INDEX('Projekt-Budget-Übersicht'!$H:$H,MATCH(A66,'Projekt-Budget-Übersicht'!$A:$A,0)),""),IF($B$2="CAD",IFERROR(INDEX('Projekt-Budget-Übersicht'!$I:$I,MATCH(A66,'Projekt-Budget-Übersicht'!$A:$A,0)),""),IF($B$2="ADM",IFERROR(INDEX('Projekt-Budget-Übersicht'!$J:$J,MATCH(A66,'Projekt-Budget-Übersicht'!$A:$A,0)),""),""))))) | M66: =IF($B$2="-","",L66*(F66+I66+K66)) | N66: =IFERROR(INDEX('Projekt-Budget-Übersicht'!$E:$E,MATCH(A66,'Projekt-Budget-Übersicht'!$A:$A,0)),"")
A67: 7437 MVV-BSK-UW3-Käfertal-Mannheim | B67: Erarbeiten des Brandschutzkonzept/Nachweis/Stellungnahme | C67: G | D67: 31 | E67: 38.75 | F67: 0.5 | G67: 125 | I67: =IF(H67=0,"",F67-H67) | K67: =IF('M. Bandlofsky'!J36="A. Kokott",'M. Bandlofsky'!I36,0) | L67: =IF($B$2="-","",IF($B$2="Pauschale",IFERROR(INDEX('Projekt-Budget-Übersicht'!$H:$H,MATCH(A67,'Projekt-Budget-Übersicht'!$A:$A,0)),""),IF($B$2="SV",IFERROR(INDEX('Projekt-Budget-Übersicht'!$H:$H,MATCH(A67,'Projekt-Budget-Übersicht'!$A:$A,0)),""),IF($B$2="CAD",IFERROR(INDEX('Projekt-Budget-Übersicht'!$I:$I,MATCH(A67,'Projekt-Budget-Übersicht'!$A:$A,0)),""),IF($B$2="ADM",IFERROR(INDEX('Projekt-Budget-Übersicht'!$J:$J,MATCH(A67,'Projekt-Budget-Übersicht'!$A:$A,0)),""),""))))) | M67: =IF($B$2="-","",L67*(F67+I67+K67)) | N67: =IFERROR(INDEX('Projekt-Budget-Übersicht'!$E:$E,MATCH(A67,'Projekt-Budget-Übersicht'!$A:$A,0)),"")
A68: 7444 Energieprojekte-DK-BSK-WEA-Schußbachwald | B68: ADM | C68: G | D68: 1 | E68: 1.75 | F68: 0.5 | G68: 175 | I68: =IF(H68=0,"",F68-H68) | K68: 0 | L68: =IF($B$2="-","",IF($B$2="Pauschale",IFERROR(INDEX('Projekt-Budget-Übersicht'!$H:$H,MATCH(A68,'Projekt-Budget-Übersicht'!$A:$A,0)),""),IF($B$2="SV",IFERROR(INDEX('Projekt-Budget-Übersicht'!$H:$H,MATCH(A68,'Projekt-Budget-Übersicht'!$A:$A,0)),""),IF($B$2="CAD",IFERROR(INDEX('Projekt-Budget-Übersicht'!$I:$I,MATCH(A68,'Projekt-Budget-Übersicht'!$A:$A,0)),""),IF($B$2="ADM",IFERROR(INDEX('Projekt-Budget-Übersicht'!$J:$J,MATCH(A68,'Projekt-Budget-Übersicht'!$A:$A,0)),""),""))))) | M68: =IF($B$2="-","",L68*(F68+I68+K68)) | N68: =IFERROR(INDEX('Projekt-Budget-Übersicht'!$E:$E,MATCH(A68,'Projekt-Budget-Übersicht'!$A:$A,0)),"")
A69: 7445 Energieprojekte-DK-BSK-WEA-Thüngersheim | B69: ADM | C69: G | D69: 1 | E69: 1.75 | F69: 0.5 | G69: 175 | I69: =IF(H69=0,"",F69-H69) | K69: 0 | L69: =IF($B$2="-","",IF($B$2="Pauschale",IFERROR(INDEX('Projekt-Budget-Übersicht'!$H:$H,MATCH(A69,'Projekt-Budget-Übersicht'!$A:$A,0)),""),IF($B$2="SV",IFERROR(INDEX('Projekt-Budget-Übersicht'!$H:$H,MATCH(A69,'Projekt-Budget-Übersicht'!$A:$A,0)),""),IF($B$2="CAD",IFERROR(INDEX('Projekt-Budget-Übersicht'!$I:$I,MATCH(A69,'Projekt-Budget-Übersicht'!$A:$A,0)),""),IF($B$2="ADM",IFERROR(INDEX('Projekt-Budget-Übersicht'!$J:$J,MATCH(A69,'Projekt-Budget-Übersicht'!$A:$A,0)),""),""))))) | M69: =IF($B$2="-","",L69*(F69+I69+K69)) | N69: =IFERROR(INDEX('Projekt-Budget-Übersicht'!$E:$E,MATCH(A69,'Projekt-Budget-Übersicht'!$A:$A,0)),"")
A70: 7477 WindBauer-BSK-WEA-Waldhausen | B70: ADM | C70: G | D70: 1 | E70: 1.75 | F70: 0.5 | G70: 175 | I70: =IF(H70=0,"",F70-H70) | K70: 0 | L70: =IF($B$2="-","",IF($B$2="Pauschale",IFERROR(INDEX('Projekt-Budget-Übersicht'!$H:$H,MATCH(A70,'Projekt-Budget-Übersicht'!$A:$A,0)),""),IF($B$2="SV",IFERROR(INDEX('Projekt-Budget-Übersicht'!$H:$H,MATCH(A70,'Projekt-Budget-Übersicht'!$A:$A,0)),""),IF($B$2="CAD",IFERROR(INDEX('Projekt-Budget-Übersicht'!$I:$I,MATCH(A70,'Projekt-Budget-Übersicht'!$A:$A,0)),""),IF($B$2="ADM",IFERROR(INDEX('Projekt-Budget-Übersicht'!$J:$J,MATCH(A70,'Projekt-Budget-Übersicht'!$A:$A,0)),""),""))))) | M70: =IF($B$2="-","",L70*(F70+I70+K70)) | N70: =IFERROR(INDEX('Projekt-Budget-Übersicht'!$E:$E,MATCH(A70,'Projekt-Budget-Übersicht'!$A:$A,0)),"")
A71: 7478 WindBauer-BSK-WEA-Hofstett | B71: ADM | C71: G | D71: 1 | E71: 1.75 | F71: 0.5 | G71: 175 | I71: =IF(H71=0,"",F71-H71) | K71: 0 | L71: =IF($B$2="-","",IF($B$2="Pauschale",IFERROR(INDEX('Projekt-Budget-Übersicht'!$H:$H,MATCH(A71,'Projekt-Budget-Übersicht'!$A:$A,0)),""),IF($B$2="SV",IFERROR(INDEX('Projekt-Budget-Übersicht'!$H:$H,MATCH(A71,'Projekt-Budget-Übersicht'!$A:$A,0)),""),IF($B$2="CAD",IFERROR(INDEX('Projekt-Budget-Übersicht'!$I:$I,MATCH(A71,'Projekt-Budget-Übersicht'!$A:$A,0)),""),IF($B$2="ADM",IFERROR(INDEX('Projekt-Budget-Übersicht'!$J:$J,MATCH(A71,'Projekt-Budget-Übersicht'!$A:$A,0)),""),""))))) | M71: =IF($B$2="-","",L71*(F71+I71+K71)) | N71: =IFERROR(INDEX('Projekt-Budget-Übersicht'!$E:$E,MATCH(A71,'Projekt-Budget-Übersicht'!$A:$A,0)),"")
A72: 7482 Telehouse-BSK-TDE-Campus-Kleyerstraße-FFM-übergeordnetes-BSK | B72: ADM (nicht kalkuliert) | C72: G | D72: 3 | E72: 2 | F72: 0.5 | G72: 66.67 | I72: =IF(H72=0,"",F72-H72) | K72: 0 | L72: =IF($B$2="-","",IF($B$2="Pauschale",IFERROR(INDEX('Projekt-Budget-Übersicht'!$H:$H,MATCH(A72,'Projekt-Budget-Übersicht'!$A:$A,0)),""),IF($B$2="SV",IFERROR(INDEX('Projekt-Budget-Übersicht'!$H:$H,MATCH(A72,'Projekt-Budget-Übersicht'!$A:$A,0)),""),IF($B$2="CAD",IFERROR(INDEX('Projekt-Budget-Übersicht'!$I:$I,MATCH(A72,'Projekt-Budget-Übersicht'!$A:$A,0)),""),IF($B$2="ADM",IFERROR(INDEX('Projekt-Budget-Übersicht'!$J:$J,MATCH(A72,'Projekt-Budget-Übersicht'!$A:$A,0)),""),""))))) | M72: =IF($B$2="-","",L72*(F72+I72+K72)) | N72: =IFERROR(INDEX('Projekt-Budget-Übersicht'!$E:$E,MATCH(A72,'Projekt-Budget-Übersicht'!$A:$A,0)),"")
A73: 7485 Hijran-Sohrab-BSK-Europaplatz10-BKR | B73: ADM | C73: G | D73: 1 | E73: 1 | F73: 0.25 | G73: 100 | I73: =IF(H73=0,"",F73-H73) | K73: 0 | L73: =IF($B$2="-","",IF($B$2="Pauschale",IFERROR(INDEX('Projekt-Budget-Übersicht'!$H:$H,MATCH(A73,'Projekt-Budget-Übersicht'!$A:$A,0)),""),IF($B$2="SV",IFERROR(INDEX('Projekt-Budget-Übersicht'!$H:$H,MATCH(A73,'Projekt-Budget-Übersicht'!$A:$A,0)),""),IF($B$2="CAD",IFERROR(INDEX('Projekt-Budget-Übersicht'!$I:$I,MATCH(A73,'Projekt-Budget-Übersicht'!$A:$A,0)),""),IF($B$2="ADM",IFERROR(INDEX('Projekt-Budget-Übersicht'!$J:$J,MATCH(A73,'Projekt-Budget-Übersicht'!$A:$A,0)),""),""))))) | M73: =IF($B$2="-","",L73*(F73+I73+K73)) | N73: =IFERROR(INDEX('Projekt-Budget-Übersicht'!$E:$E,MATCH(A73,'Projekt-Budget-Übersicht'!$A:$A,0)),"")
A74: 7486 wiwi-BSK-WEA-Mainz-Hechtsheim | B74: ADM | C74: G | D74: 1 | E74: 1.75 | F74: 0.5 | G74: 175 | I74: =IF(H74=0,"",F74-H74) | K74: 0 | L74: =IF($B$2="-","",IF($B$2="Pauschale",IFERROR(INDEX('Projekt-Budget-Übersicht'!$H:$H,MATCH(A74,'Projekt-Budget-Übersicht'!$A:$A,0)),""),IF($B$2="SV",IFERROR(INDEX('Projekt-Budget-Übersicht'!$H:$H,MATCH(A74,'Projekt-Budget-Übersicht'!$A:$A,0)),""),IF($B$2="CAD",IFERROR(INDEX('Projekt-Budget-Übersicht'!$I:$I,MATCH(A74,'Projekt-Budget-Übersicht'!$A:$A,0)),""),IF($B$2="ADM",IFERROR(INDEX('Projekt-Budget-Übersicht'!$J:$J,MATCH(A74,'Projekt-Budget-Übersicht'!$A:$A,0)),""),""))))) | M74: =IF($B$2="-","",L74*(F74+I74+K74)) | N74: =IFERROR(INDEX('Projekt-Budget-Übersicht'!$E:$E,MATCH(A74,'Projekt-Budget-Übersicht'!$A:$A,0)),"")
A75: 7497 Fichter-BTB-Dachsanierung-Kettlerstraße44-Ludwigshafen | B75: (aN) Pos. 1 Brandschutztechnische Beratung während der Planungsphase (SV) | C75: G | D75: 6 | E75: 1.25 | F75: 0.5 | G75: 20.83 | I75: =IF(H75=0,"",F75-H75) | K75: 0 | L75: =IF($B$2="-","",IF($B$2="Pauschale",IFERROR(INDEX('Projekt-Budget-Übersicht'!$H:$H,MATCH(A75,'Projekt-Budget-Übersicht'!$A:$A,0)),""),IF($B$2="SV",IFERROR(INDEX('Projekt-Budget-Übersicht'!$H:$H,MATCH(A75,'Projekt-Budget-Übersicht'!$A:$A,0)),""),IF($B$2="CAD",IFERROR(INDEX('Projekt-Budget-Übersicht'!$I:$I,MATCH(A75,'Projekt-Budget-Übersicht'!$A:$A,0)),""),IF($B$2="ADM",IFERROR(INDEX('Projekt-Budget-Übersicht'!$J:$J,MATCH(A75,'Projekt-Budget-Übersicht'!$A:$A,0)),""),""))))) | M75: =IF($B$2="-","",L75*(F75+I75+K75)) | N75: =IFERROR(INDEX('Projekt-Budget-Übersicht'!$E:$E,MATCH(A75,'Projekt-Budget-Übersicht'!$A:$A,0)),"")
A76: 7600 Altus-Dummy-für-Unterprojekte | B76: ADM | C76: G | D76: 0 | E76: 0.5 | F76: 0.5 | G76: 0 | I76: =IF(H76=0,"",F76-H76) | K76: 0 | L76: =IF($B$2="-","",IF($B$2="Pauschale",IFERROR(INDEX('Projekt-Budget-Übersicht'!$H:$H,MATCH(A76,'Projekt-Budget-Übersicht'!$A:$A,0)),""),IF($B$2="SV",IFERROR(INDEX('Projekt-Budget-Übersicht'!$H:$H,MATCH(A76,'Projekt-Budget-Übersicht'!$A:$A,0)),""),IF($B$2="CAD",IFERROR(INDEX('Projekt-Budget-Übersicht'!$I:$I,MATCH(A76,'Projekt-Budget-Übersicht'!$A:$A,0)),""),IF($B$2="ADM",IFERROR(INDEX('Projekt-Budget-Übersicht'!$J:$J,MATCH(A76,'Projekt-Budget-Übersicht'!$A:$A,0)),""),""))))) | M76: =IF($B$2="-","",L76*(F76+I76+K76)) | N76: =IFERROR(INDEX('Projekt-Budget-Übersicht'!$E:$E,MATCH(A76,'Projekt-Budget-Übersicht'!$A:$A,0)),"")
B77: Summe | F77: 29.75
B78: Bonusberechtigte Stunden | F78: =G78+H78 | G78: 6.25 | H78: =SUM(H41,H42,H43,H44,H45,H46,H47,H48,H49,H50,H51,H52,H53,H54,H55,H56,H57,H58,H59,H60,H61,H62,H63,H64,H65,H66,H67,H68,H69,H70,H71,H72,H73,H74,H75,H76)
B79: Bonusberechtigte Stunden Sonderprojekt | F79: =G79+H79 | G79: 11 | H79: =SUM(H39,H40)
B80: Zugeordnete Stunden von anderen MA | F80: =SUM(K39:K76)
B81: Gesamt Bonus Stunden | F81: =F78+F79+F80
A83: --- September 2025 ---
A84: Projekt | B84: Meilenstein | C84: Typ | D84: Soll (h) | E84: Ist (h) | F84: September 2025 (h) | G84: % | H84: Bonus-Anpassung (h) | I84: Differenz (h) | J84: Zuordnen an | K84: Von anderen (h) | L84: Stundensatz (€/h) | M84: Umsatz (€) | N84: Budget Gesamt (€) | O84: Budget Ist (€) | P84: Budget Erwirtschaftet (€)
A85: 0000 Sonderprojekt für Bonus | B85: Angebote-Ausschreibungen-Kalkulationen (max. 8h/Monat pro MA) | C85: M | D85: 8 | E85: 7 | F85: 7 | G85: 87.5 | I85: =IF(H85=0,"",F85-H85) | K85: =IF('C. Trapp SV'!J56="A. Kokott",'C. Trapp SV'!I56,0)+IF('D. Brucker'!J33="A. Kokott",'D. Brucker'!I33,0)+IF('J. Dorn'!J83="A. Kokott",'J. Dorn'!I83,0)+IF('O. Haag BS-CAD'!J92="A. Kokott",'O. Haag BS-CAD'!I92,0)+IF('S. Schüler'!J93="A. Kokott",'S. Schüler'!I93,0)+IF('U. Sutter ADM'!J51="A. Kokott",'U. Sutter ADM'!I51,0) | L85: =IF($B$2="-","",IF($B$2="Pauschale",IFERROR(INDEX('Projekt-Budget-Übersicht'!$H:$H,MATCH(A85,'Projekt-Budget-Übersicht'!$A:$A,0)),""),IF($B$2="SV",IFERROR(INDEX('Projekt-Budget-Übersicht'!$H:$H,MATCH(A85,'Projekt-Budget-Übersicht'!$A:$A,0)),""),IF($B$2="CAD",IFERROR(INDEX('Projekt-Budget-Übersicht'!$I:$I,MATCH(A85,'Projekt-Budget-Übersicht'!$A:$A,0)),""),IF($B$2="ADM",IFERROR(INDEX('Projekt-Budget-Übersicht'!$J:$J,MATCH(A85,'Projekt-Budget-Übersicht'!$A:$A,0)),""),""))))) | M85: =IF($B$2="-","",L85*(F85+I85+K85)) | N85: =IFERROR(INDEX('Projekt-Budget-Übersicht'!$E:$E,MATCH(A85,'Projekt-Budget-Übersicht'!$A:$A,0)),"")
B86: Einarbeitung neuer Mitarbeiter (max. 8h/Monat pro MA) | C86: M | D86: 8 | E86: 2 | F86: 2 | G86: 25 | I86: =IF(H86=0,"",F86-H86) | K86: =IF('C. Trapp SV'!J57="A. Kokott",'C. Trapp SV'!I57,0)+IF('J. Dorn'!J84="A. Kokott",'J. Dorn'!I84,0)+IF('M. Bandlofsky'!J45="A. Kokott",'M. Bandlofsky'!I45,0)+IF('O. Haag BS-CAD'!J93="A. Kokott",'O. Haag BS-CAD'!I93,0)+IF('R. Wagen CAD'!J57="A. Kokott",'R. Wagen CAD'!I57,0)+IF('T. Trautmann'!J72="A. Kokott",'T. Trautmann'!I72,0)+IF('U. Sutter ADM'!J52="A. Kokott",'U. Sutter ADM'!I52,0) | L86: =IF($B$2="-","",IF($B$2="Pauschale",IFERROR(INDEX('Projekt-Budget-Übersicht'!$H:$H,MATCH(A86,'Projekt-Budget-Übersicht'!$A:$A,0)),""),IF($B$2="SV",IFERROR(INDEX('Projekt-Budget-Übersicht'!$H:$H,MATCH(A86,'Projekt-Budget-Übersicht'!$A:$A,0)),""),IF($B$2="CAD",IFERROR(INDEX('Projekt-Budget-Übersicht'!$I:$I,MATCH(A86,'Projekt-Budget-Übersicht'!$A:$A,0)),""),IF($B$2="ADM",IFERROR(INDEX('Projekt-Budget-Übersicht'!$J:$J,MATCH(A86,'Projekt-Budget-Übersicht'!$A:$A,0)),""),""))))) | M86: =IF($B$2="-","",L86*(F86+I86+K86)) | N86: =IFERROR(INDEX('Projekt-Budget-Übersicht'!$E:$E,MATCH(A86,'Projekt-Budget-Übersicht'!$A:$A,0)),"")
A87: 0815.10 MPI-Fortschr-BSK-Z-HIRN-Umbau-Tierhaus-Max-von-Laue-Str4-FFM | B87: SV | C87: G | D87: 20 | E87: 19.5 | F87: 0.25 | G87: 97.5 | I87: =IF(H87=0,"",F87-H87) | K87: =IF('M. Bandlofsky'!J47="A. Kokott",'M. Bandlofsky'!I47,0) | L87: =IF($B$2="-","",IF($B$2="Pauschale",IFERROR(INDEX('Projekt-Budget-Übersicht'!$H:$H,MATCH(A87,'Projekt-Budget-Übersicht'!$A:$A,0)),""),IF($B$2="SV",IFERROR(INDEX('Projekt-Budget-Übersicht'!$H:$H,MATCH(A87,'Projekt-Budget-Übersicht'!$A:$A,0)),""),IF($B$2="CAD",IFERROR(INDEX('Projekt-Budget-Übersicht'!$I:$I,MATCH(A87,'Projekt-Budget-Übersicht'!$A:$A,0)),""),IF($B$2="ADM",IFERROR(INDEX('Projekt-Budget-Übersicht'!$J:$J,MATCH(A87,'Projekt-Budget-Übersicht'!$A:$A,0)),""),""))))) | M87: =IF($B$2="-","",L87*(F87+I87+K87)) | N87: =IFERROR(INDEX('Projekt-Budget-Übersicht'!$E:$E,MATCH(A87,'Projekt-Budget-Übersicht'!$A:$A,0)),"")
A88: 1015.02 VuBBaWü-BTB-Kurfürstenanlage15-HD-Justizzentrum | B88: ADM | C88: G | D88: 1 | E88: 2 | F88: 0.5 | G88: 200 | I88: =IF(H88=0,"",F88-H88) | K88: 0 | L88: =IF($B$2="-","",IF($B$2="Pauschale",IFERROR(INDEX('Projekt-Budget-Übersicht'!$H:$H,MATCH(A88,'Projekt-Budget-Übersicht'!$A:$A,0)),""),IF($B$2="SV",IFERROR(INDEX('Projekt-Budget-Übersicht'!$H:$H,MATCH(A88,'Projekt-Budget-Übersicht'!$A:$A,0)),""),IF($B$2="CAD",IFERROR(INDEX('Projekt-Budget-Übersicht'!$I:$I,MATCH(A88,'Projekt-Budget-Übersicht'!$A:$A,0)),""),IF($B$2="ADM",IFERROR(INDEX('Projekt-Budget-Übersicht'!$J:$J,MATCH(A88,'Projekt-Budget-Übersicht'!$A:$A,0)),""),""))))) | M88: =IF($B$2="-","",L88*(F88+I88+K88)) | N88: =IFERROR(INDEX('Projekt-Budget-Übersicht'!$E:$E,MATCH(A88,'Projekt-Budget-Übersicht'!$A:$A,0)),"")
A89: 4436.04 BTB Krankenhaus-Bergstraße-Viernheimer-Straße-2-Heppenheim | B89: 8103-Prüfen Plausibilität der Sachverständigennachweise auf Schnittstellen…. | C89: G | D89: 13 | E89: 0.25 | F89: 0.25 | G89: 1.92 | I89: =IF(H89=0,"",F89-H89) | K89: 0 | L89: =IF($B$2="-","",IF($B$2="Pauschale",IFERROR(INDEX('Projekt-Budget-Übersicht'!$H:$H,MATCH(A89,'Projekt-Budget-Übersicht'!$A:$A,0)),""),IF($B$2="SV",IFERROR(INDEX('Projekt-Budget-Übersicht'!$H:$H,MATCH(A89,'Projekt-Budget-Übersicht'!$A:$A,0)),""),IF($B$2="CAD",IFERROR(INDEX('Projekt-Budget-Übersicht'!$I:$I,MATCH(A89,'Projekt-Budget-Übersicht'!$A:$A,0)),""),IF($B$2="ADM",IFERROR(INDEX('Projekt-Budget-Übersicht'!$J:$J,MATCH(A89,'Projekt-Budget-Übersicht'!$A:$A,0)),""),""))))) | M89: =IF($B$2="-","",L89*(F89+I89+K89)) | N89: =IFERROR(INDEX('Projekt-Budget-Übersicht'!$E:$E,MATCH(A89,'Projekt-Budget-Übersicht'!$A:$A,0)),"")
A90: 4436.043 FWP-NA003-KKH-Bergstraße-Viernheimer-Straße-2-Heppenheim-Bauphase+NB-BauteilG | B90: 9200-Erstellen od. Prüfen Feuerwehrpläne…. | C90: G | D90: 230 | E90: 140.25 | F90: 0.5 | G90: 60.98 | I90: =IF(H90=0,"",F90-H90) | K90: =IF('M. Warner'!J24="A. Kokott",'M. Warner'!I24,0)+IF('S. Schüler'!J97="A. Kokott",'S. Schüler'!I97,0) | L90: =IF($B$2="-","",IF($B$2="Pauschale",IFERROR(INDEX('Projekt-Budget-Übersicht'!$H:$H,MATCH(A90,'Projekt-Budget-Übersicht'!$A:$A,0)),""),IF($B$2="SV",IFERROR(INDEX('Projekt-Budget-Übersicht'!$H:$H,MATCH(A90,'Projekt-Budget-Übersicht'!$A:$A,0)),""),IF($B$2="CAD",IFERROR(INDEX('Projekt-Budget-Übersicht'!$I:$I,MATCH(A90,'Projekt-Budget-Übersicht'!$A:$A,0)),""),IF($B$2="ADM",IFERROR(INDEX('Projekt-Budget-Übersicht'!$J:$J,MATCH(A90,'Projekt-Budget-Übersicht'!$A:$A,0)),""),""))))) | M90: =IF($B$2="-","",L90*(F90+I90+K90)) | N90: =IFERROR(INDEX('Projekt-Budget-Übersicht'!$E:$E,MATCH(A90,'Projekt-Budget-Übersicht'!$A:$A,0)),"")
A91: 5291.01 RNV-BTB-NB-ABZ-Betriebshof-Ludwigshafen | B91: SV | C91: G | D91: 0 | E91: 0 | F91: 0.5 | G91: 0 | I91: =IF(H91=0,"",F91-H91) | K91: =IF('M. Bandlofsky'!J50="A. Kokott",'M. Bandlofsky'!I50,0) | L91: =IF($B$2="-","",IF($B$2="Pauschale",IFERROR(INDEX('Projekt-Budget-Übersicht'!$H:$H,MATCH(A91,'Projekt-Budget-Übersicht'!$A:$A,0)),""),IF($B$2="SV",IFERROR(INDEX('Projekt-Budget-Übersicht'!$H:$H,MATCH(A91,'Projekt-Budget-Übersicht'!$A:$A,0)),""),IF($B$2="CAD",IFERROR(INDEX('Projekt-Budget-Übersicht'!$I:$I,MATCH(A91,'Projekt-Budget-Übersicht'!$A:$A,0)),""),IF($B$2="ADM",IFERROR(INDEX('Projekt-Budget-Übersicht'!$J:$J,MATCH(A91,'Projekt-Budget-Übersicht'!$A:$A,0)),""),""))))) | M91: =IF($B$2="-","",L91*(F91+I91+K91)) | N91: =IFERROR(INDEX('Projekt-Budget-Übersicht'!$E:$E,MATCH(A91,'Projekt-Budget-Übersicht'!$A:$A,0)),"")
A92: 5640.13 E&S-Fortschr2-BSK-Eppelheimerstr8-Heidelberg | B92: ADM | C92: G | D92: 1 | E92: 2 | F92: 1 | G92: 200 | I92: =IF(H92=0,"",F92-H92) | K92: 0 | L92: =IF($B$2="-","",IF($B$2="Pauschale",IFERROR(INDEX('Projekt-Budget-Übersicht'!$H:$H,MATCH(A92,'Projekt-Budget-Übersicht'!$A:$A,0)),""),IF($B$2="SV",IFERROR(INDEX('Projekt-Budget-Übersicht'!$H:$H,MATCH(A92,'Projekt-Budget-Übersicht'!$A:$A,0)),""),IF($B$2="CAD",IFERROR(INDEX('Projekt-Budget-Übersicht'!$I:$I,MATCH(A92,'Projekt-Budget-Übersicht'!$A:$A,0)),""),IF($B$2="ADM",IFERROR(INDEX('Projekt-Budget-Übersicht'!$J:$J,MATCH(A92,'Projekt-Budget-Übersicht'!$A:$A,0)),""),""))))) | M92: =IF($B$2="-","",L92*(F92+I92+K92)) | N92: =IFERROR(INDEX('Projekt-Budget-Übersicht'!$E:$E,MATCH(A92,'Projekt-Budget-Übersicht'!$A:$A,0)),"")
A93: 5664.20 KOB-BAB-Trinkwassertrennung-Lauterstraße-50-Wolfstein | B93: (aN) Pos. 1 Brandschutztechnische Beratung (SV 30h) 3.000€ | C93: G | D93: 30 | E93: 12.75 | F93: 0.25 | G93: 42.5 | I93: =IF(H93=0,"",F93-H93) | K93: 0 | L93: =IF($B$2="-","",IF($B$2="Pauschale",IFERROR(INDEX('Projekt-Budget-Übersicht'!$H:$H,MATCH(A93,'Projekt-Budget-Übersicht'!$A:$A,0)),""),IF($B$2="SV",IFERROR(INDEX('Projekt-Budget-Übersicht'!$H:$H,MATCH(A93,'Projekt-Budget-Übersicht'!$A:$A,0)),""),IF($B$2="CAD",IFERROR(INDEX('Projekt-Budget-Übersicht'!$I:$I,MATCH(A93,'Projekt-Budget-Übersicht'!$A:$A,0)),""),IF($B$2="ADM",IFERROR(INDEX('Projekt-Budget-Übersicht'!$J:$J,MATCH(A93,'Projekt-Budget-Übersicht'!$A:$A,0)),""),""))))) | M93: =IF($B$2="-","",L93*(F93+I93+K93)) | N93: =IFERROR(INDEX('Projekt-Budget-Übersicht'!$E:$E,MATCH(A93,'Projekt-Budget-Übersicht'!$A:$A,0)),"")
A94: 5834.07 Fuchs-Digit-Bestandspläne-Werner-HeisenbergStr1-KL | B94: ADM (nicht kalkuliert) | C94: G | D94: 1 | E94: 1.5 | F94: 0.5 | G94: 150 | I94: =IF(H94=0,"",F94-H94) | K94: 0 | L94: =IF($B$2="-","",IF($B$2="Pauschale",IFERROR(INDEX('Projekt-Budget-Übersicht'!$H:$H,MATCH(A94,'Projekt-Budget-Übersicht'!$A:$A,0)),""),IF($B$2="SV",IFERROR(INDEX('Projekt-Budget-Übersicht'!$H:$H,MATCH(A94,'Projekt-Budget-Übersicht'!$A:$A,0)),""),IF($B$2="CAD",IFERROR(INDEX('Projekt-Budget-Übersicht'!$I:$I,MATCH(A94,'Projekt-Budget-Übersicht'!$A:$A,0)),""),IF($B$2="ADM",IFERROR(INDEX('Projekt-Budget-Übersicht'!$J:$J,MATCH(A94,'Projekt-Budget-Übersicht'!$A:$A,0)),""),""))))) | M94: =IF($B$2="-","",L94*(F94+I94+K94)) | N94: =IFERROR(INDEX('Projekt-Budget-Übersicht'!$E:$E,MATCH(A94,'Projekt-Budget-Übersicht'!$A:$A,0)),"")
A95: 5875.061 John-Deere-Werk-Halle-N-HomburgerStr117-125-Zweibrücken | B95: ADM | C95: G | D95: 1.5 | E95: 0.75 | F95: 0.5 | G95: 50 | I95: =IF(H95=0,"",F95-H95) | K95: 0 | L95: =IF($B$2="-","",IF($B$2="Pauschale",IFERROR(INDEX('Projekt-Budget-Übersicht'!$H:$H,MATCH(A95,'Projekt-Budget-Übersicht'!$A:$A,0)),""),IF($B$2="SV",IFERROR(INDEX('Projekt-Budget-Übersicht'!$H:$H,MATCH(A95,'Projekt-Budget-Übersicht'!$A:$A,0)),""),IF($B$2="CAD",IFERROR(INDEX('Projekt-Budget-Übersicht'!$I:$I,MATCH(A95,'Projekt-Budget-Übersicht'!$A:$A,0)),""),IF($B$2="ADM",IFERROR(INDEX('Projekt-Budget-Übersicht'!$J:$J,MATCH(A95,'Projekt-Budget-Übersicht'!$A:$A,0)),""),""))))) | M95: =IF($B$2="-","",L95*(F95+I95+K95)) | N95: =IFERROR(INDEX('Projekt-Budget-Übersicht'!$E:$E,MATCH(A95,'Projekt-Budget-Übersicht'!$A:$A,0)),"")
A96: 6045.03 wpd-BSK-Windpark-Dreihausen-Nordeck | B96: ADM | C96: G | D96: 1 | E96: 1.25 | F96: 0.5 | G96: 125 | I96: =IF(H96=0,"",F96-H96) | K96: 0 | L96: =IF($B$2="-","",IF($B$2="Pauschale",IFERROR(INDEX('Projekt-Budget-Übersicht'!$H:$H,MATCH(A96,'Projekt-Budget-Übersicht'!$A:$A,0)),""),IF($B$2="SV",IFERROR(INDEX('Projekt-Budget-Übersicht'!$H:$H,MATCH(A96,'Projekt-Budget-Übersicht'!$A:$A,0)),""),IF($B$2="CAD",IFERROR(INDEX('Projekt-Budget-Übersicht'!$I:$I,MATCH(A96,'Projekt-Budget-Übersicht'!$A:$A,0)),""),IF($B$2="ADM",IFERROR(INDEX('Projekt-Budget-Übersicht'!$J:$J,MATCH(A96,'Projekt-Budget-Übersicht'!$A:$A,0)),""),""))))) | M96: =IF($B$2="-","",L96*(F96+I96+K96)) | N96: =IFERROR(INDEX('Projekt-Budget-Übersicht'!$E:$E,MATCH(A96,'Projekt-Budget-Übersicht'!$A:$A,0)),"")
A97: 6344 Brodenheckstraße-Bitburg-Amtsgericht | B97: 4000-Genehmigungsplanung | C97: G | D97: 37 | E97: 27.75 | F97: 0.75 | G97: 75 | I97: =IF(H97=0,"",F97-H97) | K97: =IF('J. Dorn'!J90="A. Kokott",'J. Dorn'!I90,0)+IF('M. Bandlofsky'!J61="A. Kokott",'M. Bandlofsky'!I61,0)+IF('O. Haag BS-CAD'!J106="A. Kokott",'O. Haag BS-CAD'!I106,0)+IF('T. Trautmann'!J88="A. Kokott",'T. Trautmann'!I88,0) | L97: =IF($B$2="-","",IF($B$2="Pauschale",IFERROR(INDEX('Projekt-Budget-Übersicht'!$H:$H,MATCH(A97,'Projekt-Budget-Übersicht'!$A:$A,0)),""),IF($B$2="SV",IFERROR(INDEX('Projekt-Budget-Übersicht'!$H:$H,MATCH(A97,'Projekt-Budget-Übersicht'!$A:$A,0)),""),IF($B$2="CAD",IFERROR(INDEX('Projekt-Budget-Übersicht'!$I:$I,MATCH(A97,'Projekt-Budget-Übersicht'!$A:$A,0)),""),IF($B$2="ADM",IFERROR(INDEX('Projekt-Budget-Übersicht'!$J:$J,MATCH(A97,'Projekt-Budget-Übersicht'!$A:$A,0)),""),""))))) | M97: =IF($B$2="-","",L97*(F97+I97+K97)) | N97: =IFERROR(INDEX('Projekt-Budget-Übersicht'!$E:$E,MATCH(A97,'Projekt-Budget-Übersicht'!$A:$A,0)),"")
A98: 6377.04 IAV-BSK-Im-Kammertal10-Heimsheim | B98: ADM | C98: G | D98: 2 | E98: 2.25 | F98: 1 | G98: 112.5 | I98: =IF(H98=0,"",F98-H98) | K98: 0 | L98: =IF($B$2="-","",IF($B$2="Pauschale",IFERROR(INDEX('Projekt-Budget-Übersicht'!$H:$H,MATCH(A98,'Projekt-Budget-Übersicht'!$A:$A,0)),""),IF($B$2="SV",IFERROR(INDEX('Projekt-Budget-Übersicht'!$H:$H,MATCH(A98,'Projekt-Budget-Übersicht'!$A:$A,0)),""),IF($B$2="CAD",IFERROR(INDEX('Projekt-Budget-Übersicht'!$I:$I,MATCH(A98,'Projekt-Budget-Übersicht'!$A:$A,0)),""),IF($B$2="ADM",IFERROR(INDEX('Projekt-Budget-Übersicht'!$J:$J,MATCH(A98,'Projekt-Budget-Übersicht'!$A:$A,0)),""),""))))) | M98: =IF($B$2="-","",L98*(F98+I98+K98)) | N98: =IFERROR(INDEX('Projekt-Budget-Übersicht'!$E:$E,MATCH(A98,'Projekt-Budget-Übersicht'!$A:$A,0)),"")
A99: 6421.071 Weerts-NAT-BSK-DtAircraft-Leipzig | B99: ADM | C99: G | D99: 1 | E99: 1.75 | F99: 0.5 | G99: 175 | I99: =IF(H99=0,"",F99-H99) | K99: 0 | L99: =IF($B$2="-","",IF($B$2="Pauschale",IFERROR(INDEX('Projekt-Budget-Übersicht'!$H:$H,MATCH(A99,'Projekt-Budget-Übersicht'!$A:$A,0)),""),IF($B$2="SV",IFERROR(INDEX('Projekt-Budget-Übersicht'!$H:$H,MATCH(A99,'Projekt-Budget-Übersicht'!$A:$A,0)),""),IF($B$2="CAD",IFERROR(INDEX('Projekt-Budget-Übersicht'!$I:$I,MATCH(A99,'Projekt-Budget-Übersicht'!$A:$A,0)),""),IF($B$2="ADM",IFERROR(INDEX('Projekt-Budget-Übersicht'!$J:$J,MATCH(A99,'Projekt-Budget-Übersicht'!$A:$A,0)),""),""))))) | M99: =IF($B$2="-","",L99*(F99+I99+K99)) | N99: =IFERROR(INDEX('Projekt-Budget-Übersicht'!$E:$E,MATCH(A99,'Projekt-Budget-Übersicht'!$A:$A,0)),"")
A100: 6497 SunYardOffice-Heidelberg | B100: 4000-Genehmigungsplanung | C100: G | D100: 0 | E100: 0 | F100: 0.5 | G100: 0 | I100: =IF(H100=0,"",F100-H100) | K100: =IF('J. Dorn'!J91="A. Kokott",'J. Dorn'!I91,0)+IF('T. Trautmann'!J91="A. Kokott",'T. Trautmann'!I91,0) | L100: =IF($B$2="-","",IF($B$2="Pauschale",IFERROR(INDEX('Projekt-Budget-Übersicht'!$H:$H,MATCH(A100,'Projekt-Budget-Übersicht'!$A:$A,0)),""),IF($B$2="SV",IFERROR(INDEX('Projekt-Budget-Übersicht'!$H:$H,MATCH(A100,'Projekt-Budget-Übersicht'!$A:$A,0)),""),IF($B$2="CAD",IFERROR(INDEX('Projekt-Budget-Übersicht'!$I:$I,MATCH(A100,'Projekt-Budget-Übersicht'!$A:$A,0)),""),IF($B$2="ADM",IFERROR(INDEX('Projekt-Budget-Übersicht'!$J:$J,MATCH(A100,'Projekt-Budget-Übersicht'!$A:$A,0)),""),""))))) | M100: =IF($B$2="-","",L100*(F100+I100+K100)) | N100: =IFERROR(INDEX('Projekt-Budget-Übersicht'!$E:$E,MATCH(A100,'Projekt-Budget-Übersicht'!$A:$A,0)),"")
A101: 6527.01 IO-Anp-BSK-Mühlenfeldstr1-Holzminden-Symotion | B101: SV | C101: G | D101: 6 | E101: 48 | F101: 0.75 | G101: 800 | I101: =IF(H101=0,"",F101-H101) | K101: =IF('J. Dorn'!J92="A. Kokott",'J. Dorn'!I92,0)+IF('O. Haag BS-CAD'!J109="A. Kokott",'O. Haag BS-CAD'!I109,0) | L101: =IF($B$2="-","",IF($B$2="Pauschale",IFERROR(INDEX('Projekt-Budget-Übersicht'!$H:$H,MATCH(A101,'Projekt-Budget-Übersicht'!$A:$A,0)),""),IF($B$2="SV",IFERROR(INDEX('Projekt-Budget-Übersicht'!$H:$H,MATCH(A101,'Projekt-Budget-Übersicht'!$A:$A,0)),""),IF($B$2="CAD",IFERROR(INDEX('Projekt-Budget-Übersicht'!$I:$I,MATCH(A101,'Projekt-Budget-Übersicht'!$A:$A,0)),""),IF($B$2="ADM",IFERROR(INDEX('Projekt-Budget-Übersicht'!$J:$J,MATCH(A101,'Projekt-Budget-Übersicht'!$A:$A,0)),""),""))))) | M101: =IF($B$2="-","",L101*(F101+I101+K101)) | N101: =IFERROR(INDEX('Projekt-Budget-Übersicht'!$E:$E,MATCH(A101,'Projekt-Budget-Übersicht'!$A:$A,0)),"")
A102: 6649.03 formica-Anp-BSK-Otto-Hahn-Str-Hilden-Laer | B102: ADM | C102: G | D102: 0 | E102: 0 | F102: 1 | G102: 0 | I102: =IF(H102=0,"",F102-H102) | K102: 0 | L102: =IF($B$2="-","",IF($B$2="Pauschale",IFERROR(INDEX('Projekt-Budget-Übersicht'!$H:$H,MATCH(A102,'Projekt-Budget-Übersicht'!$A:$A,0)),""),IF($B$2="SV",IFERROR(INDEX('Projekt-Budget-Übersicht'!$H:$H,MATCH(A102,'Projekt-Budget-Übersicht'!$A:$A,0)),""),IF($B$2="CAD",IFERROR(INDEX('Projekt-Budget-Übersicht'!$I:$I,MATCH(A102,'Projekt-Budget-Übersicht'!$A:$A,0)),""),IF($B$2="ADM",IFERROR(INDEX('Projekt-Budget-Übersicht'!$J:$J,MATCH(A102,'Projekt-Budget-Übersicht'!$A:$A,0)),""),""))))) | M102: =IF($B$2="-","",L102*(F102+I102+K102)) | N102: =IFERROR(INDEX('Projekt-Budget-Übersicht'!$E:$E,MATCH(A102,'Projekt-Budget-Übersicht'!$A:$A,0)),"")
A103: 6693.02 Holnis-FRP-Quartier-D-Römerkreis-Heidelberg | B103: 0100-Anlage Projekt, Angebot, Versand, Auftrag | C103: G | D103: 1 | E103: 1.5 | F103: 0.5 | G103: 150 | I103: =IF(H103=0,"",F103-H103) | K103: 0 | L103: =IF($B$2="-","",IF($B$2="Pauschale",IFERROR(INDEX('Projekt-Budget-Übersicht'!$H:$H,MATCH(A103,'Projekt-Budget-Übersicht'!$A:$A,0)),""),IF($B$2="SV",IFERROR(INDEX('Projekt-Budget-Übersicht'!$H:$H,MATCH(A103,'Projekt-Budget-Übersicht'!$A:$A,0)),""),IF($B$2="CAD",IFERROR(INDEX('Projekt-Budget-Übersicht'!$I:$I,MATCH(A103,'Projekt-Budget-Übersicht'!$A:$A,0)),""),IF($B$2="ADM",IFERROR(INDEX('Projekt-Budget-Übersicht'!$J:$J,MATCH(A103,'Projekt-Budget-Übersicht'!$A:$A,0)),""),""))))) | M103: =IF($B$2="-","",L103*(F103+I103+K103)) | N103: =IFERROR(INDEX('Projekt-Budget-Übersicht'!$E:$E,MATCH(A103,'Projekt-Budget-Übersicht'!$A:$A,0)),"")
...

Sheet C. Trapp SV
A1: C. Trapp SV - Quartalsreport 2025Q3
A2: Position: | B2: SV
A4: --- Juli 2025 ---
A5: Projekt | B5: Meilenstein | C5: Typ | D5: Soll (h) | E5: Ist (h) | F5: Juli 2025 (h) | G5: % | H5: Bonus-Anpassung (h) | I5: Differenz (h) | J5: Zuordnen an | K5: Von anderen (h) | L5: Stundensatz (€/h) | M5: Umsatz (€) | N5: Budget Gesamt (€) | O5: Budget Ist (€) | P5: Budget Erwirtschaftet (€)
A6: 0000 Sonderprojekt für Bonus | B6: Einarbeitung neuer Mitarbeiter (max. 8h/Monat pro MA) | C6: M | D6: 8 | E6: 1 | F6: 1 | G6: 12.5 | I6: =IF(H6=0,"",F6-H6) | K6: =IF('A. Kokott'!J7="C. Trapp SV",'A. Kokott'!I7,0)+IF('D. Brucker'!J7="C. Trapp SV",'D. Brucker'!I7,0)+IF('E. Bieler'!J7="C. Trapp SV",'E. Bieler'!I7,0)+IF('J. Dorchies'!J7="C. Trapp SV",'J. Dorchies'!I7,0)+IF('J. Dorn'!J6="C. Trapp SV",'J. Dorn'!I6,0)+IF('M. Bandlofsky'!J6="C. Trapp SV",'M. Bandlofsky'!I6,0)+IF('T. Trautmann'!J7="C. Trapp SV",'T. Trautmann'!I7,0)+IF('U. Sutter ADM'!J7="C. Trapp SV",'U. Sutter ADM'!I7,0) | L6: =IF($B$2="-","",IF($B$2="Pauschale",IFERROR(INDEX('Projekt-Budget-Übersicht'!$H:$H,MATCH(A6,'Projekt-Budget-Übersicht'!$A:$A,0)),""),IF($B$2="SV",IFERROR(INDEX('Projekt-Budget-Übersicht'!$H:$H,MATCH(A6,'Projekt-Budget-Übersicht'!$A:$A,0)),""),IF($B$2="CAD",IFERROR(INDEX('Projekt-Budget-Übersicht'!$I:$I,MATCH(A6,'Projekt-Budget-Übersicht'!$A:$A,0)),""),IF($B$2="ADM",IFERROR(INDEX('Projekt-Budget-Übersicht'!$J:$J,MATCH(A6,'Projekt-Budget-Übersicht'!$A:$A,0)),""),""))))) | M6: =IF($B$2="-","",L6*(F6+I6+K6)) | N6: =IFERROR(INDEX('Projekt-Budget-Übersicht'!$E:$E,MATCH(A6,'Projekt-Budget-Übersicht'!$A:$A,0)),"")
A7: 4126.041 Telluride-LP8-Bauzeitverlängerung-BA2-Klinikum-am-Gesundbrunnen-Heilbronn | B7: (aN) Pos. 2 weiterführende BAB über die Verlängerung der Bauzeit von 28 Monaten hinaus | C7: G | D7: 40 | E7: 468.75 | F7: 8 | G7: 1171.88 | I7: =IF(H7=0,"",F7-H7) | K7: =IF('U. Sutter ADM'!J9="C. Trapp SV",'U. Sutter ADM'!I9,0) | L7: =IF($B$2="-","",IF($B$2="Pauschale",IFERROR(INDEX('Projekt-Budget-Übersicht'!$H:$H,MATCH(A7,'Projekt-Budget-Übersicht'!$A:$A,0)),""),IF($B$2="SV",IFERROR(INDEX('Projekt-Budget-Übersicht'!$H:$H,MATCH(A7,'Projekt-Budget-Übersicht'!$A:$A,0)),""),IF($B$2="CAD",IFERROR(INDEX('Projekt-Budget-Übersicht'!$I:$I,MATCH(A7,'Projekt-Budget-Übersicht'!$A:$A,0)),""),IF($B$2="ADM",IFERROR(INDEX('Projekt-Budget-Übersicht'!$J:$J,MATCH(A7,'Projekt-Budget-Übersicht'!$A:$A,0)),""),""))))) | M7: =IF($B$2="-","",L7*(F7+I7+K7)) | N7: =IFERROR(INDEX('Projekt-Budget-Übersicht'!$E:$E,MATCH(A7,'Projekt-Budget-Übersicht'!$A:$A,0)),"")
A8: 4436.04 BTB Krankenhaus-Bergstraße-Viernheimer-Straße-2-Heppenheim | B8: 4105-Zusammenstellung Unterlagen für Einreichung bei BA…. | C8: G | D8: 6 | E8: 16.75 | F8: 4 | G8: 279.17 | I8: =IF(H8=0,"",F8-H8) | K8: =IF('U. Sutter ADM'!J10="C. Trapp SV",'U. Sutter ADM'!I10,0) | L8: =IF($B$2="-","",IF($B$2="Pauschale",IFERROR(INDEX('Projekt-Budget-Übersicht'!$H:$H,MATCH(A8,'Projekt-Budget-Übersicht'!$A:$A,0)),""),IF($B$2="SV",IFERROR(INDEX('Projekt-Budget-Übersicht'!$H:$H,MATCH(A8,'Projekt-Budget-Übersicht'!$A:$A,0)),""),IF($B$2="CAD",IFERROR(INDEX('Projekt-Budget-Übersicht'!$I:$I,MATCH(A8,'Projekt-Budget-Übersicht'!$A:$A,0)),""),IF($B$2="ADM",IFERROR(INDEX('Projekt-Budget-Übersicht'!$J:$J,MATCH(A8,'Projekt-Budget-Übersicht'!$A:$A,0)),""),""))))) | M8: =IF($B$2="-","",L8*(F8+I8+K8)) | N8: =IFERROR(INDEX('Projekt-Budget-Übersicht'!$E:$E,MATCH(A8,'Projekt-Budget-Übersicht'!$A:$A,0)),"")
B9: 5100-Beraten Planer ausführungsreife Lösungen…. | C9: G | D9: 52 | E9: 146.75 | F9: 8.75 | G9: 282.21 | I9: =IF(H9=0,"",F9-H9) | K9: =IF('S. Schüler'!J13="C. Trapp SV",'S. Schüler'!I13,0) | L9: =IF($B$2="-","",IF($B$2="Pauschale",IFERROR(INDEX('Projekt-Budget-Übersicht'!$H:$H,MATCH(A9,'Projekt-Budget-Übersicht'!$A:$A,0)),""),IF($B$2="SV",IFERROR(INDEX('Projekt-Budget-Übersicht'!$H:$H,MATCH(A9,'Projekt-Budget-Übersicht'!$A:$A,0)),""),IF($B$2="CAD",IFERROR(INDEX('Projekt-Budget-Übersicht'!$I:$I,MATCH(A9,'Projekt-Budget-Übersicht'!$A:$A,0)),""),IF($B$2="ADM",IFERROR(INDEX('Projekt-Budget-Übersicht'!$J:$J,MATCH(A9,'Projekt-Budget-Übersicht'!$A:$A,0)),""),""))))) | M9: =IF($B$2="-","",L9*(F9+I9+K9)) | N9: =IFERROR(INDEX('Projekt-Budget-Übersicht'!$E:$E,MATCH(A9,'Projekt-Budget-Übersicht'!$A:$A,0)),"")
B10: 5101-Mitwirken Koordination Fachplanung…. | C10: G | D10: 21 | E10: 30.25 | F10: 1.5 | G10: 144.05 | I10: =IF(H10=0,"",F10-H10) | K10: 0 | L10: =IF($B$2="-","",IF($B$2="Pauschale",IFERROR(INDEX('Projekt-Budget-Übersicht'!$H:$H,MATCH(A10,'Projekt-Budget-Übersicht'!$A:$A,0)),""),IF($B$2="SV",IFERROR(INDEX('Projekt-Budget-Übersicht'!$H:$H,MATCH(A10,'Projekt-Budget-Übersicht'!$A:$A,0)),""),IF($B$2="CAD",IFERROR(INDEX('Projekt-Budget-Übersicht'!$I:$I,MATCH(A10,'Projekt-Budget-Übersicht'!$A:$A,0)),""),IF($B$2="ADM",IFERROR(INDEX('Projekt-Budget-Übersicht'!$J:$J,MATCH(A10,'Projekt-Budget-Übersicht'!$A:$A,0)),""),""))))) | M10: =IF($B$2="-","",L10*(F10+I10+K10)) | N10: =IFERROR(INDEX('Projekt-Budget-Übersicht'!$E:$E,MATCH(A10,'Projekt-Budget-Übersicht'!$A:$A,0)),"")
B11: 5106-Prüfen auf zusätzl. genehmigungspfl. Sachverhalte.... | C11: G | D11: 5 | E11: 23.5 | F11: 16.5 | G11: 470 | I11: =IF(H11=0,"",F11-H11) | K11: 0 | L11: =IF($B$2="-","",IF($B$2="Pauschale",IFERROR(INDEX('Projekt-Budget-Übersicht'!$H:$H,MATCH(A11,'Projekt-Budget-Übersicht'!$A:$A,0)),""),IF($B$2="SV",IFERROR(INDEX('Projekt-Budget-Übersicht'!$H:$H,MATCH(A11,'Projekt-Budget-Übersicht'!$A:$A,0)),""),IF($B$2="CAD",IFERROR(INDEX('Projekt-Budget-Übersicht'!$I:$I,MATCH(A11,'Projekt-Budget-Übersicht'!$A:$A,0)),""),IF($B$2="ADM",IFERROR(INDEX('Projekt-Budget-Übersicht'!$J:$J,MATCH(A11,'Projekt-Budget-Übersicht'!$A:$A,0)),""),""))))) | M11: =IF($B$2="-","",L11*(F11+I11+K11)) | N11: =IFERROR(INDEX('Projekt-Budget-Übersicht'!$E:$E,MATCH(A11,'Projekt-Budget-Übersicht'!$A:$A,0)),"")
B12: 5205-Mitwirken Erstellen Brandmelde- und Alarmierungskonzept.... | C12: G | D12: 19 | E12: 1.5 | F12: 1.5 | G12: 7.89 | I12: =IF(H12=0,"",F12-H12) | K12: 0 | L12: =IF($B$2="-","",IF($B$2="Pauschale",IFERROR(INDEX('Projekt-Budget-Übersicht'!$H:$H,MATCH(A12,'Projekt-Budget-Übersicht'!$A:$A,0)),""),IF($B$2="SV",IFERROR(INDEX('Projekt-Budget-Übersicht'!$H:$H,MATCH(A12,'Projekt-Budget-Übersicht'!$A:$A,0)),""),IF($B$2="CAD",IFERROR(INDEX('Projekt-Budget-Übersicht'!$I:$I,MATCH(A12,'Projekt-Budget-Übersicht'!$A:$A,0)),""),IF($B$2="ADM",IFERROR(INDEX('Projekt-Budget-Übersicht'!$J:$J,MATCH(A12,'Projekt-Budget-Übersicht'!$A:$A,0)),""),""))))) | M12: =IF($B$2="-","",L12*(F12+I12+K12)) | N12: =IFERROR(INDEX('Projekt-Budget-Übersicht'!$E:$E,MATCH(A12,'Projekt-Budget-Übersicht'!$A:$A,0)),"")
A13: 5328 Flugfeldklinikum-Böblingen | B13: 5101-Mitwirken Koordination Fachplanung…. | C13: G | D13: 16 | E13: 68.75 | F13: 2.25 | G13: 429.69 | I13: =IF(H13=0,"",F13-H13) | K13: =IF('M. Bandlofsky'!J11="C. Trapp SV",'M. Bandlofsky'!I11,0) | L13: =IF($B$2="-","",IF($B$2="Pauschale",IFERROR(INDEX('Projekt-Budget-Übersicht'!$H:$H,MATCH(A13,'Projekt-Budget-Übersicht'!$A:$A,0)),""),IF($B$2="SV",IFERROR(INDEX('Projekt-Budget-Übersicht'!$H:$H,MATCH(A13,'Projekt-Budget-Übersicht'!$A:$A,0)),""),IF($B$2="CAD",IFERROR(INDEX('Projekt-Budget-Übersicht'!$I:$I,MATCH(A13,'Projekt-Budget-Übersicht'!$A:$A,0)),""),IF($B$2="ADM",IFERROR(INDEX('Projekt-Budget-Übersicht'!$J:$J,MATCH(A13,'Projekt-Budget-Übersicht'!$A:$A,0)),""),""))))) | M13: =IF($B$2="-","",L13*(F13+I13+K13)) | N13: =IFERROR(INDEX('Projekt-Budget-Übersicht'!$E:$E,MATCH(A13,'Projekt-Budget-Übersicht'!$A:$A,0)),"")
B14: 8100-Prüfen der Ausführung auf prinzipielle Übereinstimmung (Stufe 1).... | C14: G | D14: 610 | E14: 45.25 | F14: 32.75 | G14: 7.42 | I14: =IF(H14=0,"",F14-H14) | K14: 0 | L14: =IF($B$2="-","",IF($B$2="Pauschale",IFERROR(INDEX('Projekt-Budget-Übersicht'!$H:$H,MATCH(A14,'Projekt-Budget-Übersicht'!$A:$A,0)),""),IF($B$2="SV",IFERROR(INDEX('Projekt-Budget-Übersicht'!$H:$H,MATCH(A14,'Projekt-Budget-Übersicht'!$A:$A,0)),""),IF($B$2="CAD",IFERROR(INDEX('Projekt-Budget-Übersicht'!$I:$I,MATCH(A14,'Projekt-Budget-Übersicht'!$A:$A,0)),""),IF($B$2="ADM",IFERROR(INDEX('Projekt-Budget-Übersicht'!$J:$J,MATCH(A14,'Projekt-Budget-Übersicht'!$A:$A,0)),""),""))))) | M14: =IF($B$2="-","",L14*(F14+I14+K14)) | N14: =IFERROR(INDEX('Projekt-Budget-Übersicht'!$E:$E,MATCH(A14,'Projekt-Budget-Übersicht'!$A:$A,0)),"")
B15: 8101-Kontrolle Verwendbarkeitsnachweise/Bescheinigungen…. | C15: G | D15: 160 | E15: 22 | F15: 2 | G15: 13.75 | I15: =IF(H15=0,"",F15-H15) | K15: 0 | L15: =IF($B$2="-","",IF($B$2="Pauschale",IFERROR(INDEX('Projekt-Budget-Übersicht'!$H:$H,MATCH(A15,'Projekt-Budget-Übersicht'!$A:$A,0)),""),IF($B$2="SV",IFERROR(INDEX('Projekt-Budget-Übersicht'!$H:$H,MATCH(A15,'Projekt-Budget-Übersicht'!$A:$A,0)),""),IF($B$2="CAD",IFERROR(INDEX('Projekt-Budget-Übersicht'!$I:$I,MATCH(A15,'Projekt-Budget-Übersicht'!$A:$A,0)),""),IF($B$2="ADM",IFERROR(INDEX('Projekt-Budget-Übersicht'!$J:$J,MATCH(A15,'Projekt-Budget-Übersicht'!$A:$A,0)),""),""))))) | M15: =IF($B$2="-","",L15*(F15+I15+K15)) | N15: =IFERROR(INDEX('Projekt-Budget-Übersicht'!$E:$E,MATCH(A15,'Projekt-Budget-Übersicht'!$A:$A,0)),"")
B16: 8200-Prüfen der Ausführung - system. stichprobenart. Kontrolle (Stufe 2)…. | C16: G | D16: 562 | E16: 199 | F16: 31 | G16: 35.41 | I16: =IF(H16=0,"",F16-H16) | K16: 0 | L16: =IF($B$2="-","",IF($B$2="Pauschale",IFERROR(INDEX('Projekt-Budget-Übersicht'!$H:$H,MATCH(A16,'Projekt-Budget-Übersicht'!$A:$A,0)),""),IF($B$2="SV",IFERROR(INDEX('Projekt-Budget-Übersicht'!$H:$H,MATCH(A16,'Projekt-Budget-Übersicht'!$A:$A,0)),""),IF($B$2="CAD",IFERROR(INDEX('Projekt-Budget-Übersicht'!$I:$I,MATCH(A16,'Projekt-Budget-Übersicht'!$A:$A,0)),""),IF($B$2="ADM",IFERROR(INDEX('Projekt-Budget-Übersicht'!$J:$J,MATCH(A16,'Projekt-Budget-Übersicht'!$A:$A,0)),""),""))))) | M16: =IF($B$2="-","",L16*(F16+I16+K16)) | N16: =IFERROR(INDEX('Projekt-Budget-Übersicht'!$E:$E,MATCH(A16,'Projekt-Budget-Übersicht'!$A:$A,0)),"")
A17: 5607.05 BAB-NB-J4-Zentralinstitut-für-seelische-Gesundheit-Mannheim | B17: (aN) 8200-Prüfen der Ausführung - system. stichprobenart. Kontrolle (Stufe 2)…. | C17: G | D17: 240 | E17: 168.5 | F17: 18 | G17: 70.21 | I17: =IF(H17=0,"",F17-H17) | K17: =IF('U. Sutter ADM'!J15="C. Trapp SV",'U. Sutter ADM'!I15,0) | L17: =IF($B$2="-","",IF($B$2="Pauschale",IFERROR(INDEX('Projekt-Budget-Übersicht'!$H:$H,MATCH(A17,'Projekt-Budget-Übersicht'!$A:$A,0)),""),IF($B$2="SV",IFERROR(INDEX('Projekt-Budget-Übersicht'!$H:$H,MATCH(A17,'Projekt-Budget-Übersicht'!$A:$A,0)),""),IF($B$2="CAD",IFERROR(INDEX('Projekt-Budget-Übersicht'!$I:$I,MATCH(A17,'Projekt-Budget-Übersicht'!$A:$A,0)),""),IF($B$2="ADM",IFERROR(INDEX('Projekt-Budget-Übersicht'!$J:$J,MATCH(A17,'Projekt-Budget-Übersicht'!$A:$A,0)),""),""))))) | M17: =IF($B$2="-","",L17*(F17+I17+K17)) | N17: =IFERROR(INDEX('Projekt-Budget-Übersicht'!$E:$E,MATCH(A17,'Projekt-Budget-Übersicht'!$A:$A,0)),"")
B18: 5100-Beraten Planer ausführungsreife Lösungen…. | C18: G | D18: 25.25 | E18: 96 | F18: 1 | G18: 380.2 | I18: =IF(H18=0,"",F18-H18) | K18: 0 | L18: =IF($B$2="-","",IF($B$2="Pauschale",IFERROR(INDEX('Projekt-Budget-Übersicht'!$H:$H,MATCH(A18,'Projekt-Budget-Übersicht'!$A:$A,0)),""),IF($B$2="SV",IFERROR(INDEX('Projekt-Budget-Übersicht'!$H:$H,MATCH(A18,'Projekt-Budget-Übersicht'!$A:$A,0)),""),IF($B$2="CAD",IFERROR(INDEX('Projekt-Budget-Übersicht'!$I:$I,MATCH(A18,'Projekt-Budget-Übersicht'!$A:$A,0)),""),IF($B$2="ADM",IFERROR(INDEX('Projekt-Budget-Übersicht'!$J:$J,MATCH(A18,'Projekt-Budget-Übersicht'!$A:$A,0)),""),""))))) | M18: =IF($B$2="-","",L18*(F18+I18+K18)) | N18: =IFERROR(INDEX('Projekt-Budget-Übersicht'!$E:$E,MATCH(A18,'Projekt-Budget-Übersicht'!$A:$A,0)),"")
A19: 6564.01 ROB-MCR-Weilerbach-Züblin-TP1 | B19: 8000-Objektüberwachung | C19: G | D19: 3640 | E19: 175.5 | F19: 8.5 | G19: 4.82 | I19: =IF(H19=0,"",F19-H19) | K19: =IF('P. Bergner'!J8="C. Trapp SV",'P. Bergner'!I8,0) | L19: =IF($B$2="-","",IF($B$2="Pauschale",IFERROR(INDEX('Projekt-Budget-Übersicht'!$H:$H,MATCH(A19,'Projekt-Budget-Übersicht'!$A:$A,0)),""),IF($B$2="SV",IFERROR(INDEX('Projekt-Budget-Übersicht'!$H:$H,MATCH(A19,'Projekt-Budget-Übersicht'!$A:$A,0)),""),IF($B$2="CAD",IFERROR(INDEX('Projekt-Budget-Übersicht'!$I:$I,MATCH(A19,'Projekt-Budget-Übersicht'!$A:$A,0)),""),IF($B$2="ADM",IFERROR(INDEX('Projekt-Budget-Übersicht'!$J:$J,MATCH(A19,'Projekt-Budget-Übersicht'!$A:$A,0)),""),""))))) | M19: =IF($B$2="-","",L19*(F19+I19+K19)) | N19: =IFERROR(INDEX('Projekt-Budget-Übersicht'!$E:$E,MATCH(A19,'Projekt-Budget-Übersicht'!$A:$A,0)),"")
A20: 6643 BTB-FRP-FWP-Ersatzneubau-Krankenhaus-Hohenlohe-Öhringen-Vamed | B20: 5106-Prüfen auf zusätzl. genehmigungspfl. Sachverhalte.... | C20: G | D20: 16 | E20: 28.25 | F20: 3 | G20: 176.56 | I20: =IF(H20=0,"",F20-H20) | K20: 0 | L20: =IF($B$2="-","",IF($B$2="Pauschale",IFERROR(INDEX('Projekt-Budget-Übersicht'!$H:$H,MATCH(A20,'Projekt-Budget-Übersicht'!$A:$A,0)),""),IF($B$2="SV",IFERROR(INDEX('Projekt-Budget-Übersicht'!$H:$H,MATCH(A20,'Projekt-Budget-Übersicht'!$A:$A,0)),""),IF($B$2="CAD",IFERROR(INDEX('Projekt-Budget-Übersicht'!$I:$I,MATCH(A20,'Projekt-Budget-Übersicht'!$A:$A,0)),""),IF($B$2="ADM",IFERROR(INDEX('Projekt-Budget-Übersicht'!$J:$J,MATCH(A20,'Projekt-Budget-Übersicht'!$A:$A,0)),""),""))))) | M20: =IF($B$2="-","",L20*(F20+I20+K20)) | N20: =IFERROR(INDEX('Projekt-Budget-Übersicht'!$E:$E,MATCH(A20,'Projekt-Budget-Übersicht'!$A:$A,0)),"")
A21: 6704 BSK-BTB+FWP-FuR-ZsG-Lörrach | B21: 8101-Kontrolle Verwendbarkeitsnachweise/Bescheinigungen…. | C21: G | D21: 20 | E21: 33.75 | F21: 15.75 | G21: 168.75 | I21: =IF(H21=0,"",F21-H21) | K21: =IF('U. Sutter ADM'!J18="C. Trapp SV",'U. Sutter ADM'!I18,0) | L21: =IF($B$2="-","",IF($B$2="Pauschale",IFERROR(INDEX('Projekt-Budget-Übersicht'!$H:$H,MATCH(A21,'Projekt-Budget-Übersicht'!$A:$A,0)),""),IF($B$2="SV",IFERROR(INDEX('Projekt-Budget-Übersicht'!$H:$H,MATCH(A21,'Projekt-Budget-Übersicht'!$A:$A,0)),""),IF($B$2="CAD",IFERROR(INDEX('Projekt-Budget-Übersicht'!$I:$I,MATCH(A21,'Projekt-Budget-Übersicht'!$A:$A,0)),""),IF($B$2="ADM",IFERROR(INDEX('Projekt-Budget-Übersicht'!$J:$J,MATCH(A21,'Projekt-Budget-Übersicht'!$A:$A,0)),""),""))))) | M21: =IF($B$2="-","",L21*(F21+I21+K21)) | N21: =IFERROR(INDEX('Projekt-Budget-Übersicht'!$E:$E,MATCH(A21,'Projekt-Budget-Übersicht'!$A:$A,0)),"")
B22: 8104-Statusbericht Bewertung auf Möglichkeiten zur Inbetriebnahme…. | C22: G | D22: 40 | E22: 5 | F22: 2 | G22: 12.5 | I22: =IF(H22=0,"",F22-H22) | K22: 0 | L22: =IF($B$2="-","",IF($B$2="Pauschale",IFERROR(INDEX('Projekt-Budget-Übersicht'!$H:$H,MATCH(A22,'Projekt-Budget-Übersicht'!$A:$A,0)),""),IF($B$2="SV",IFERROR(INDEX('Projekt-Budget-Übersicht'!$H:$H,MATCH(A22,'Projekt-Budget-Übersicht'!$A:$A,0)),""),IF($B$2="CAD",IFERROR(INDEX('Projekt-Budget-Übersicht'!$I:$I,MATCH(A22,'Projekt-Budget-Übersicht'!$A:$A,0)),""),IF($B$2="ADM",IFERROR(INDEX('Projekt-Budget-Übersicht'!$J:$J,MATCH(A22,'Projekt-Budget-Übersicht'!$A:$A,0)),""),""))))) | M22: =IF($B$2="-","",L22*(F22+I22+K22)) | N22: =IFERROR(INDEX('Projekt-Budget-Übersicht'!$E:$E,MATCH(A22,'Projekt-Budget-Übersicht'!$A:$A,0)),"")
A23: 7313.01 BTS-Sachsenwaldhochhaus-Hamburger-Straße-49-Reinbek-OG-3-19+TK | B23: 1200-Bestandserfassung vor Ort.... | C23: G | D23: 18 | E23: 27 | F23: 20.5 | G23: 150 | I23: =IF(H23=0,"",F23-H23) | K23: 0 | L23: =IF($B$2="-","",IF($B$2="Pauschale",IFERROR(INDEX('Projekt-Budget-Übersicht'!$H:$H,MATCH(A23,'Projekt-Budget-Übersicht'!$A:$A,0)),""),IF($B$2="SV",IFERROR(INDEX('Projekt-Budget-Übersicht'!$H:$H,MATCH(A23,'Projekt-Budget-Übersicht'!$A:$A,0)),""),IF($B$2="CAD",IFERROR(INDEX('Projekt-Budget-Übersicht'!$I:$I,MATCH(A23,'Projekt-Budget-Übersicht'!$A:$A,0)),""),IF($B$2="ADM",IFERROR(INDEX('Projekt-Budget-Übersicht'!$J:$J,MATCH(A23,'Projekt-Budget-Übersicht'!$A:$A,0)),""),""))))) | M23: =IF($B$2="-","",L23*(F23+I23+K23)) | N23: =IFERROR(INDEX('Projekt-Budget-Übersicht'!$E:$E,MATCH(A23,'Projekt-Budget-Übersicht'!$A:$A,0)),"")
B24: Summe | F24: 178
B25: Bonusberechtigte Stunden | F25: =G25+H25 | G25: 95.75 | H25: =SUM(H7,H8,H9,H10,H11,H12,H13,H14,H15,H16,H17,H18,H19,H20,H21,H22,H23)
B26: Bonusberechtigte Stunden Sonderprojekt | F26: =G26+H26 | G26: 1 | H26: =SUM(H6)
B27: Zugeordnete Stunden von anderen MA | F27: =SUM(K6:K23)
B28: Gesamt Bonus Stunden | F28: =F25+F26+F27
A30: --- August 2025 ---
A31: Projekt | B31: Meilenstein | C31: Typ | D31: Soll (h) | E31: Ist (h) | F31: August 2025 (h) | G31: % | H31: Bonus-Anpassung (h) | I31: Differenz (h) | J31: Zuordnen an | K31: Von anderen (h) | L31: Stundensatz (€/h) | M31: Umsatz (€) | N31: Budget Gesamt (€) | O31: Budget Ist (€) | P31: Budget Erwirtschaftet (€)
A32: 0000 Sonderprojekt für Bonus | B32: Erstellung Vorlagen (übergreifend) (max. 8h/Monat pro MA) | C32: M | D32: 8 | E32: 3.5 | F32: 3.5 | G32: 43.75 | I32: =IF(H32=0,"",F32-H32) | K32: =IF('J. Dorn'!J46="C. Trapp SV",'J. Dorn'!I46,0)+IF('T. Trautmann'!J30="C. Trapp SV",'T. Trautmann'!I30,0) | L32: =IF($B$2="-","",IF($B$2="Pauschale",IFERROR(INDEX('Projekt-Budget-Übersicht'!$H:$H,MATCH(A32,'Projekt-Budget-Übersicht'!$A:$A,0)),""),IF($B$2="SV",IFERROR(INDEX('Projekt-Budget-Übersicht'!$H:$H,MATCH(A32,'Projekt-Budget-Übersicht'!$A:$A,0)),""),IF($B$2="CAD",IFERROR(INDEX('Projekt-Budget-Übersicht'!$I:$I,MATCH(A32,'Projekt-Budget-Übersicht'!$A:$A,0)),""),IF($B$2="ADM",IFERROR(INDEX('Projekt-Budget-Übersicht'!$J:$J,MATCH(A32,'Projekt-Budget-Übersicht'!$A:$A,0)),""),""))))) | M32: =IF($B$2="-","",L32*(F32+I32+K32)) | N32: =IFERROR(INDEX('Projekt-Budget-Übersicht'!$E:$E,MATCH(A32,'Projekt-Budget-Übersicht'!$A:$A,0)),"")
A33: 4126.041 Telluride-LP8-Bauzeitverlängerung-BA2-Klinikum-am-Gesundbrunnen-Heilbronn | B33: (aN) Pos. 2 weiterführende BAB über die Verlängerung der Bauzeit von 28 Monaten hinaus | C33: G | D33: 40 | E33: 472.75 | F33: 4 | G33: 1181.88 | I33: =IF(H33=0,"",F33-H33) | K33: 0 | L33: =IF($B$2="-","",IF($B$2="Pauschale",IFERROR(INDEX('Projekt-Budget-Übersicht'!$H:$H,MATCH(A33,'Projekt-Budget-Übersicht'!$A:$A,0)),""),IF($B$2="SV",IFERROR(INDEX('Projekt-Budget-Übersicht'!$H:$H,MATCH(A33,'Projekt-Budget-Übersicht'!$A:$A,0)),""),IF($B$2="CAD",IFERROR(INDEX('Projekt-Budget-Übersicht'!$I:$I,MATCH(A33,'Projekt-Budget-Übersicht'!$A:$A,0)),""),IF($B$2="ADM",IFERROR(INDEX('Projekt-Budget-Übersicht'!$J:$J,MATCH(A33,'Projekt-Budget-Übersicht'!$A:$A,0)),""),""))))) | M33: =IF($B$2="-","",L33*(F33+I33+K33)) | N33: =IFERROR(INDEX('Projekt-Budget-Übersicht'!$E:$E,MATCH(A33,'Projekt-Budget-Übersicht'!$A:$A,0)),"")
A34: 4436.04 BTB Krankenhaus-Bergstraße-Viernheimer-Straße-2-Heppenheim | B34: 5106-Prüfen auf zusätzl. genehmigungspfl. Sachverhalte.... | C34: G | D34: 5 | E34: 25 | F34: 1.5 | G34: 500 | I34: =IF(H34=0,"",F34-H34) | K34: 0 | L34: =IF($B$2="-","",IF($B$2="Pauschale",IFERROR(INDEX('Projekt-Budget-Übersicht'!$H:$H,MATCH(A34,'Projekt-Budget-Übersicht'!$A:$A,0)),""),IF($B$2="SV",IFERROR(INDEX('Projekt-Budget-Übersicht'!$H:$H,MATCH(A34,'Projekt-Budget-Übersicht'!$A:$A,0)),""),IF($B$2="CAD",IFERROR(INDEX('Projekt-Budget-Übersicht'!$I:$I,MATCH(A34,'Projekt-Budget-Übersicht'!$A:$A,0)),""),IF($B$2="ADM",IFERROR(INDEX('Projekt-Budget-Übersicht'!$J:$J,MATCH(A34,'Projekt-Budget-Übersicht'!$A:$A,0)),""),""))))) | M34: =IF($B$2="-","",L34*(F34+I34+K34)) | N34: =IFERROR(INDEX('Projekt-Budget-Übersicht'!$E:$E,MATCH(A34,'Projekt-Budget-Übersicht'!$A:$A,0)),"")
A35: 5328 Flugfeldklinikum-Böblingen | B35: 5100-Beraten Planer ausführungsreife Lösungen…. | C35: G | D35: 307.5 | E35: 390.25 | F35: 1.5 | G35: 126.91 | I35: =IF(H35=0,"",F35-H35) | K35: =IF('E. Bieler'!J50="C. Trapp SV",'E. Bieler'!I50,0)+IF('M. Bandlofsky'!J31="C. Trapp SV",'M. Bandlofsky'!I31,0) | L35: =IF($B$2="-","",IF($B$2="Pauschale",IFERROR(INDEX('Projekt-Budget-Übersicht'!$H:$H,MATCH(A35,'Projekt-Budget-Übersicht'!$A:$A,0)),""),IF($B$2="SV",IFERROR(INDEX('Projekt-Budget-Übersicht'!$H:$H,MATCH(A35,'Projekt-Budget-Übersicht'!$A:$A,0)),""),IF($B$2="CAD",IFERROR(INDEX('Projekt-Budget-Übersicht'!$I:$I,MATCH(A35,'Projekt-Budget-Übersicht'!$A:$A,0)),""),IF($B$2="ADM",IFERROR(INDEX('Projekt-Budget-Übersicht'!$J:$J,MATCH(A35,'Projekt-Budget-Übersicht'!$A:$A,0)),""),""))))) | M35: =IF($B$2="-","",L35*(F35+I35+K35)) | N35: =IFERROR(INDEX('Projekt-Budget-Übersicht'!$E:$E,MATCH(A35,'Projekt-Budget-Übersicht'!$A:$A,0)),"")
B36: 8100-Prüfen der Ausführung auf prinzipielle Übereinstimmung (Stufe 1).... | C36: G | D36: 610 | E36: 65.5 | F36: 14.5 | G36: 10.74 | I36: =IF(H36=0,"",F36-H36) | K36: =IF('E. Bieler'!J51="C. Trapp SV",'E. Bieler'!I51,0) | L36: =IF($B$2="-","",IF($B$2="Pauschale",IFERROR(INDEX('Projekt-Budget-Übersicht'!$H:$H,MATCH(A36,'Projekt-Budget-Übersicht'!$A:$A,0)),""),IF($B$2="SV",IFERROR(INDEX('Projekt-Budget-Übersicht'!$H:$H,MATCH(A36,'Projekt-Budget-Übersicht'!$A:$A,0)),""),IF($B$2="CAD",IFERROR(INDEX('Projekt-Budget-Übersicht'!$I:$I,MATCH(A36,'Projekt-Budget-Übersicht'!$A:$A,0)),""),IF($B$2="ADM",IFERROR(INDEX('Projekt-Budget-Übersicht'!$J:$J,MATCH(A36,'Projekt-Budget-Übersicht'!$A:$A,0)),""),""))))) | M36: =IF($B$2="-","",L36*(F36+I36+K36)) | N36: =IFERROR(INDEX('Projekt-Budget-Übersicht'!$E:$E,MATCH(A36,'Projekt-Budget-Übersicht'!$A:$A,0)),"")
B37: 8101-Kontrolle Verwendbarkeitsnachweise/Bescheinigungen…. | C37: G | D37: 160 | E37: 29 | F37: 7 | G37: 18.12 | I37: =IF(H37=0,"",F37-H37) | K37: 0 | L37: =IF($B$2="-","",IF($B$2="Pauschale",IFERROR(INDEX('Projekt-Budget-Übersicht'!$H:$H,MATCH(A37,'Projekt-Budget-Übersicht'!$A:$A,0)),""),IF($B$2="SV",IFERROR(INDEX('Projekt-Budget-Übersicht'!$H:$H,MATCH(A37,'Projekt-Budget-Übersicht'!$A:$A,0)),""),IF($B$2="CAD",IFERROR(INDEX('Projekt-Budget-Übersicht'!$I:$I,MATCH(A37,'Projekt-Budget-Übersicht'!$A:$A,0)),""),IF($B$2="ADM",IFERROR(INDEX('Projekt-Budget-Übersicht'!$J:$J,MATCH(A37,'Projekt-Budget-Übersicht'!$A:$A,0)),""),""))))) | M37: =IF($B$2="-","",L37*(F37+I37+K37)) | N37: =IFERROR(INDEX('Projekt-Budget-Übersicht'!$E:$E,MATCH(A37,'Projekt-Budget-Übersicht'!$A:$A,0)),"")
B38: 8200-Prüfen der Ausführung - system. stichprobenart. Kontrolle (Stufe 2)…. | C38: G | D38: 562 | E38: 244.5 | F38: 27 | G38: 43.51 | I38: =IF(H38=0,"",F38-H38) | K38: =IF('S. Roßkopf'!J6="C. Trapp SV",'S. Roßkopf'!I6,0) | L38: =IF($B$2="-","",IF($B$2="Pauschale",IFERROR(INDEX('Projekt-Budget-Übersicht'!$H:$H,MATCH(A38,'Projekt-Budget-Übersicht'!$A:$A,0)),""),IF($B$2="SV",IFERROR(INDEX('Projekt-Budget-Übersicht'!$H:$H,MATCH(A38,'Projekt-Budget-Übersicht'!$A:$A,0)),""),IF($B$2="CAD",IFERROR(INDEX('Projekt-Budget-Übersicht'!$I:$I,MATCH(A38,'Projekt-Budget-Übersicht'!$A:$A,0)),""),IF($B$2="ADM",IFERROR(INDEX('Projekt-Budget-Übersicht'!$J:$J,MATCH(A38,'Projekt-Budget-Übersicht'!$A:$A,0)),""),""))))) | M38: =IF($B$2="-","",L38*(F38+I38+K38)) | N38: =IFERROR(INDEX('Projekt-Budget-Übersicht'!$E:$E,MATCH(A38,'Projekt-Budget-Übersicht'!$A:$A,0)),"")
A39: 5607.05 BAB-NB-J4-Zentralinstitut-für-seelische-Gesundheit-Mannheim | B39: (p) NAT03-Bestandsaufnahme (Ist-Aufnahme) | C39: G | D39: 32 | E39: 51.75 | F39: 34 | G39: 161.72 | I39: =IF(H39=0,"",F39-H39) | K39: =IF('A. Kokott'!J47="C. Trapp SV",'A. Kokott'!I47,0)+IF('S. Roßkopf'!J7="C. Trapp SV",'S. Roßkopf'!I7,0) | L39: =IF($B$2="-","",IF($B$2="Pauschale",IFERROR(INDEX('Projekt-Budget-Übersicht'!$H:$H,MATCH(A39,'Projekt-Budget-Übersicht'!$A:$A,0)),""),IF($B$2="SV",IFERROR(INDEX('Projekt-Budget-Übersicht'!$H:$H,MATCH(A39,'Projekt-Budget-Übersicht'!$A:$A,0)),""),IF($B$2="CAD",IFERROR(INDEX('Projekt-Budget-Übersicht'!$I:$I,MATCH(A39,'Projekt-Budget-Übersicht'!$A:$A,0)),""),IF($B$2="ADM",IFERROR(INDEX('Projekt-Budget-Übersicht'!$J:$J,MATCH(A39,'Projekt-Budget-Übersicht'!$A:$A,0)),""),""))))) | M39: =IF($B$2="-","",L39*(F39+I39+K39)) | N39: =IFERROR(INDEX('Projekt-Budget-Übersicht'!$E:$E,MATCH(A39,'Projekt-Budget-Übersicht'!$A:$A,0)),"")
B40: 5100-Beraten Planer ausführungsreife Lösungen…. | C40: G | D40: 25.25 | E40: 104 | F40: 8 | G40: 411.88 | I40: =IF(H40=0,"",F40-H40) | K40: 0 | L40: =IF($B$2="-","",IF($B$2="Pauschale",IFERROR(INDEX('Projekt-Budget-Übersicht'!$H:$H,MATCH(A40,'Projekt-Budget-Übersicht'!$A:$A,0)),""),IF($B$2="SV",IFERROR(INDEX('Projekt-Budget-Übersicht'!$H:$H,MATCH(A40,'Projekt-Budget-Übersicht'!$A:$A,0)),""),IF($B$2="CAD",IFERROR(INDEX('Projekt-Budget-Übersicht'!$I:$I,MATCH(A40,'Projekt-Budget-Übersicht'!$A:$A,0)),""),IF($B$2="ADM",IFERROR(INDEX('Projekt-Budget-Übersicht'!$J:$J,MATCH(A40,'Projekt-Budget-Übersicht'!$A:$A,0)),""),""))))) | M40: =IF($B$2="-","",L40*(F40+I40+K40)) | N40: =IFERROR(INDEX('Projekt-Budget-Übersicht'!$E:$E,MATCH(A40,'Projekt-Budget-Übersicht'!$A:$A,0)),"")
B41: 9000-Mitwirken Abstimmung Behörden | C41: G | D41: 1.25 | E41: 3.5 | F41: 1.25 | G41: 280 | I41: =IF(H41=0,"",F41-H41) | K41: 0 | L41: =IF($B$2="-","",IF($B$2="Pauschale",IFERROR(INDEX('Projekt-Budget-Übersicht'!$H:$H,MATCH(A41,'Projekt-Budget-Übersicht'!$A:$A,0)),""),IF($B$2="SV",IFERROR(INDEX('Projekt-Budget-Übersicht'!$H:$H,MATCH(A41,'Projekt-Budget-Übersicht'!$A:$A,0)),""),IF($B$2="CAD",IFERROR(INDEX('Projekt-Budget-Übersicht'!$I:$I,MATCH(A41,'Projekt-Budget-Übersicht'!$A:$A,0)),""),IF($B$2="ADM",IFERROR(INDEX('Projekt-Budget-Übersicht'!$J:$J,MATCH(A41,'Projekt-Budget-Übersicht'!$A:$A,0)),""),""))))) | M41: =IF($B$2="-","",L41*(F41+I41+K41)) | N41: =IFERROR(INDEX('Projekt-Budget-Übersicht'!$E:$E,MATCH(A41,'Projekt-Budget-Übersicht'!$A:$A,0)),"")
A42: 6564.01 ROB-MCR-Weilerbach-Züblin-TP1 | B42: 8000-Objektüberwachung | C42: G | D42: 3640 | E42: 200 | F42: 17.5 | G42: 5.49 | I42: =IF(H42=0,"",F42-H42) | K42: =IF('S. Roßkopf'!J8="C. Trapp SV",'S. Roßkopf'!I8,0) | L42: =IF($B$2="-","",IF($B$2="Pauschale",IFERROR(INDEX('Projekt-Budget-Übersicht'!$H:$H,MATCH(A42,'Projekt-Budget-Übersicht'!$A:$A,0)),""),IF($B$2="SV",IFERROR(INDEX('Projekt-Budget-Übersicht'!$H:$H,MATCH(A42,'Projekt-Budget-Übersicht'!$A:$A,0)),""),IF($B$2="CAD",IFERROR(INDEX('Projekt-Budget-Übersicht'!$I:$I,MATCH(A42,'Projekt-Budget-Übersicht'!$A:$A,0)),""),IF($B$2="ADM",IFERROR(INDEX('Projekt-Budget-Übersicht'!$J:$J,MATCH(A42,'Projekt-Budget-Übersicht'!$A:$A,0)),""),""))))) | M42: =IF($B$2="-","",L42*(F42+I42+K42)) | N42: =IFERROR(INDEX('Projekt-Budget-Übersicht'!$E:$E,MATCH(A42,'Projekt-Budget-Übersicht'!$A:$A,0)),"")
A43: 6643 BTB-FRP-FWP-Ersatzneubau-Krankenhaus-Hohenlohe-Öhringen-Vamed | B43: 5100-Beraten Planer ausführungsreife Lösungen…. | C43: G | D43: 144 | E43: 106.5 | F43: 1 | G43: 73.96 | I43: =IF(H43=0,"",F43-H43) | K43: =IF('E. Bieler'!J52="C. Trapp SV",'E. Bieler'!I52,0) | L43: =IF($B$2="-","",IF($B$2="Pauschale",IFERROR(INDEX('Projekt-Budget-Übersicht'!$H:$H,MATCH(A43,'Projekt-Budget-Übersicht'!$A:$A,0)),""),IF($B$2="SV",IFERROR(INDEX('Projekt-Budget-Übersicht'!$H:$H,MATCH(A43,'Projekt-Budget-Übersicht'!$A:$A,0)),""),IF($B$2="CAD",IFERROR(INDEX('Projekt-Budget-Übersicht'!$I:$I,MATCH(A43,'Projekt-Budget-Übersicht'!$A:$A,0)),""),IF($B$2="ADM",IFERROR(INDEX('Projekt-Budget-Übersicht'!$J:$J,MATCH(A43,'Projekt-Budget-Übersicht'!$A:$A,0)),""),""))))) | M43: =IF($B$2="-","",L43*(F43+I43+K43)) | N43: =IFERROR(INDEX('Projekt-Budget-Übersicht'!$E:$E,MATCH(A43,'Projekt-Budget-Übersicht'!$A:$A,0)),"")
B44: 5106-Prüfen auf zusätzl. genehmigungspfl. Sachverhalte.... | C44: G | D44: 16 | E44: 33.25 | F44: 5 | G44: 207.81 | I44: =IF(H44=0,"",F44-H44) | K44: 0 | L44: =IF($B$2="-","",IF($B$2="Pauschale",IFERROR(INDEX('Projekt-Budget-Übersicht'!$H:$H,MATCH(A44,'Projekt-Budget-Übersicht'!$A:$A,0)),""),IF($B$2="SV",IFERROR(INDEX('Projekt-Budget-Übersicht'!$H:$H,MATCH(A44,'Projekt-Budget-Übersicht'!$A:$A,0)),""),IF($B$2="CAD",IFERROR(INDEX('Projekt-Budget-Übersicht'!$I:$I,MATCH(A44,'Projekt-Budget-Übersicht'!$A:$A,0)),""),IF($B$2="ADM",IFERROR(INDEX('Projekt-Budget-Übersicht'!$J:$J,MATCH(A44,'Projekt-Budget-Übersicht'!$A:$A,0)),""),""))))) | M44: =IF($B$2="-","",L44*(F44+I44+K44)) | N44: =IFERROR(INDEX('Projekt-Budget-Übersicht'!$E:$E,MATCH(A44,'Projekt-Budget-Übersicht'!$A:$A,0)),"")
B45: 8101-Kontrolle Verwendbarkeitsnachweise/Bescheinigungen…. | C45: G | D45: 80 | E45: 19.75 | F45: 8.75 | G45: 24.69 | I45: =IF(H45=0,"",F45-H45) | K45: =IF('U. Sutter ADM'!J39="C. Trapp SV",'U. Sutter ADM'!I39,0) | L45: =IF($B$2="-","",IF($B$2="Pauschale",IFERROR(INDEX('Projekt-Budget-Übersicht'!$H:$H,MATCH(A45,'Projekt-Budget-Übersicht'!$A:$A,0)),""),IF($B$2="SV",IFERROR(INDEX('Projekt-Budget-Übersicht'!$H:$H,MATCH(A45,'Projekt-Budget-Übersicht'!$A:$A,0)),""),IF($B$2="CAD",IFERROR(INDEX('Projekt-Budget-Übersicht'!$I:$I,MATCH(A45,'Projekt-Budget-Übersicht'!$A:$A,0)),""),IF($B$2="ADM",IFERROR(INDEX('Projekt-Budget-Übersicht'!$J:$J,MATCH(A45,'Projekt-Budget-Übersicht'!$A:$A,0)),""),""))))) | M45: =IF($B$2="-","",L45*(F45+I45+K45)) | N45: =IFERROR(INDEX('Projekt-Budget-Übersicht'!$E:$E,MATCH(A45,'Projekt-Budget-Übersicht'!$A:$A,0)),"")
B46: 8200-Prüfen der Ausführung - system. stichprobenart. Kontrolle (Stufe 2)…. | C46: G | D46: 540 | E46: 448 | F46: 8 | G46: 82.96 | I46: =IF(H46=0,"",F46-H46) | K46: =IF('S. Roßkopf'!J9="C. Trapp SV",'S. Roßkopf'!I9,0)+IF('U. Sutter ADM'!J40="C. Trapp SV",'U. Sutter ADM'!I40,0) | L46: =IF($B$2="-","",IF($B$2="Pauschale",IFERROR(INDEX('Projekt-Budget-Übersicht'!$H:$H,MATCH(A46,'Projekt-Budget-Übersicht'!$A:$A,0)),""),IF($B$2="SV",IFERROR(INDEX('Projekt-Budget-Übersicht'!$H:$H,MATCH(A46,'Projekt-Budget-Übersicht'!$A:$A,0)),""),IF($B$2="CAD",IFERROR(INDEX('Projekt-Budget-Übersicht'!$I:$I,MATCH(A46,'Projekt-Budget-Übersicht'!$A:$A,0)),""),IF($B$2="ADM",IFERROR(INDEX('Projekt-Budget-Übersicht'!$J:$J,MATCH(A46,'Projekt-Budget-Übersicht'!$A:$A,0)),""),""))))) | M46: =IF($B$2="-","",L46*(F46+I46+K46)) | N46: =IFERROR(INDEX('Projekt-Budget-Übersicht'!$E:$E,MATCH(A46,'Projekt-Budget-Übersicht'!$A:$A,0)),"")
A47: 7247 Hoepfner-BTB-NL-Grünwinkel | B47: (aN) Pos. 1 Brandschutztechnische Beratung und SOLL-IST-Abgleich (SV) | C47: G | D47: 100 | E47: 19.5 | F47: 6.5 | G47: 19.5 | I47: =IF(H47=0,"",F47-H47) | K47: =IF('S. Schüler'!J72="C. Trapp SV",'S. Schüler'!I72,0) | L47: =IF($B$2="-","",IF($B$2="Pauschale",IFERROR(INDEX('Projekt-Budget-Übersicht'!$H:$H,MATCH(A47,'Projekt-Budget-Übersicht'!$A:$A,0)),""),IF($B$2="SV",IFERROR(INDEX('Projekt-Budget-Übersicht'!$H:$H,MATCH(A47,'Projekt-Budget-Übersicht'!$A:$A,0)),""),IF($B$2="CAD",IFERROR(INDEX('Projekt-Budget-Übersicht'!$I:$I,MATCH(A47,'Projekt-Budget-Übersicht'!$A:$A,0)),""),IF($B$2="ADM",IFERROR(INDEX('Projekt-Budget-Übersicht'!$J:$J,MATCH(A47,'Projekt-Budget-Übersicht'!$A:$A,0)),""),""))))) | M47: =IF($B$2="-","",L47*(F47+I47+K47)) | N47: =IFERROR(INDEX('Projekt-Budget-Übersicht'!$E:$E,MATCH(A47,'Projekt-Budget-Übersicht'!$A:$A,0)),"")
B48: Summe | F48: 149
B49: Bonusberechtigte Stunden | F49: =G49+H49 | G49: 90.25 | H49: =SUM(H33,H34,H35,H36,H37,H38,H39,H40,H41,H42,H43,H44,H45,H46,H47)
B50: Bonusberechtigte Stunden Sonderprojekt | F50: =G50+H50 | G50: 3.5 | H50: =SUM(H32)
B51: Zugeordnete Stunden von anderen MA | F51: =SUM(K32:K47)
B52: Gesamt Bonus Stunden | F52: =F49+F50+F51
A54: --- September 2025 ---
A55: Projekt | B55: Meilenstein | C55: Typ | D55: Soll (h) | E55: Ist (h) | F55: September 2025 (h) | G55: % | H55: Bonus-Anpassung (h) | I55: Differenz (h) | J55: Zuordnen an | K55: Von anderen (h) | L55: Stundensatz (€/h) | M55: Umsatz (€) | N55: Budget Gesamt (€) | O55: Budget Ist (€) | P55: Budget Erwirtschaftet (€)
A56: 0000 Sonderprojekt für Bonus | B56: Angebote-Ausschreibungen-Kalkulationen (max. 8h/Monat pro MA) | C56: M | D56: 8 | E56: 5 | F56: 5 | G56: 62.5 | I56: =IF(H56=0,"",F56-H56) | K56: =IF('A. Kokott'!J85="C. Trapp SV",'A. Kokott'!I85,0)+IF('D. Brucker'!J33="C. Trapp SV",'D. Brucker'!I33,0)+IF('J. Dorn'!J83="C. Trapp SV",'J. Dorn'!I83,0)+IF('O. Haag BS-CAD'!J92="C. Trapp SV",'O. Haag BS-CAD'!I92,0)+IF('S. Schüler'!J93="C. Trapp SV",'S. Schüler'!I93,0)+IF('U. Sutter ADM'!J51="C. Trapp SV",'U. Sutter ADM'!I51,0) | L56: =IF($B$2="-","",IF($B$2="Pauschale",IFERROR(INDEX('Projekt-Budget-Übersicht'!$H:$H,MATCH(A56,'Projekt-Budget-Übersicht'!$A:$A,0)),""),IF($B$2="SV",IFERROR(INDEX('Projekt-Budget-Übersicht'!$H:$H,MATCH(A56,'Projekt-Budget-Übersicht'!$A:$A,0)),""),IF($B$2="CAD",IFERROR(INDEX('Projekt-Budget-Übersicht'!$I:$I,MATCH(A56,'Projekt-Budget-Übersicht'!$A:$A,0)),""),IF($B$2="ADM",IFERROR(INDEX('Projekt-Budget-Übersicht'!$J:$J,MATCH(A56,'Projekt-Budget-Übersicht'!$A:$A,0)),""),""))))) | M56: =IF($B$2="-","",L56*(F56+I56+K56)) | N56: =IFERROR(INDEX('Projekt-Budget-Übersicht'!$E:$E,MATCH(A56,'Projekt-Budget-Übersicht'!$A:$A,0)),"")
B57: Einarbeitung neuer Mitarbeiter (max. 8h/Monat pro MA) | C57: M | D57: 8 | E57: 4 | F57: 4 | G57: 50 | I57: =IF(H57=0,"",F57-H57) | K57: =IF('A. Kokott'!J86="C. Trapp SV",'A. Kokott'!I86,0)+IF('J. Dorn'!J84="C. Trapp SV",'J. Dorn'!I84,0)+IF('M. Bandlofsky'!J45="C. Trapp SV",'M. Bandlofsky'!I45,0)+IF('O. Haag BS-CAD'!J93="C. Trapp SV",'O. Haag BS-CAD'!I93,0)+IF('R. Wagen CAD'!J57="C. Trapp SV",'R. Wagen CAD'!I57,0)+IF('T. Trautmann'!J72="C. Trapp SV",'T. Trautmann'!I72,0)+IF('U. Sutter ADM'!J52="C. Trapp SV",'U. Sutter ADM'!I52,0) | L57: =IF($B$2="-","",IF($B$2="Pauschale",IFERROR(INDEX('Projekt-Budget-Übersicht'!$H:$H,MATCH(A57,'Projekt-Budget-Übersicht'!$A:$A,0)),""),IF($B$2="SV",IFERROR(INDEX('Projekt-Budget-Übersicht'!$H:$H,MATCH(A57,'Projekt-Budget-Übersicht'!$A:$A,0)),""),IF($B$2="CAD",IFERROR(INDEX('Projekt-Budget-Übersicht'!$I:$I,MATCH(A57,'Projekt-Budget-Übersicht'!$A:$A,0)),""),IF($B$2="ADM",IFERROR(INDEX('Projekt-Budget-Übersicht'!$J:$J,MATCH(A57,'Projekt-Budget-Übersicht'!$A:$A,0)),""),""))))) | M57: =IF($B$2="-","",L57*(F57+I57+K57)) | N57: =IFERROR(INDEX('Projekt-Budget-Übersicht'!$E:$E,MATCH(A57,'Projekt-Budget-Übersicht'!$A:$A,0)),"")
B58: Erstellung Vorlagen (übergreifend) (max. 8h/Monat pro MA) | C58: M | D58: 8 | E58: 21.5 | F58: 21.5 | G58: 268.75 | I58: =IF(H58=0,"",F58-H58) | K58: =IF('J. Dorn'!J85="C. Trapp SV",'J. Dorn'!I85,0)+IF('O. Haag BS-CAD'!J94="C. Trapp SV",'O. Haag BS-CAD'!I94,0)+IF('P. Bergner'!J42="C. Trapp SV",'P. Bergner'!I42,0)+IF('T. Trautmann'!J73="C. Trapp SV",'T. Trautmann'!I73,0) | L58: =IF($B$2="-","",IF($B$2="Pauschale",IFERROR(INDEX('Projekt-Budget-Übersicht'!$H:$H,MATCH(A58,'Projekt-Budget-Übersicht'!$A:$A,0)),""),IF($B$2="SV",IFERROR(INDEX('Projekt-Budget-Übersicht'!$H:$H,MATCH(A58,'Projekt-Budget-Übersicht'!$A:$A,0)),""),IF($B$2="CAD",IFERROR(INDEX('Projekt-Budget-Übersicht'!$I:$I,MATCH(A58,'Projekt-Budget-Übersicht'!$A:$A,0)),""),IF($B$2="ADM",IFERROR(INDEX('Projekt-Budget-Übersicht'!$J:$J,MATCH(A58,'Projekt-Budget-Übersicht'!$A:$A,0)),""),""))))) | M58: =IF($B$2="-","",L58*(F58+I58+K58)) | N58: =IFERROR(INDEX('Projekt-Budget-Übersicht'!$E:$E,MATCH(A58,'Projekt-Budget-Übersicht'!$A:$A,0)),"")
B59: Vorträge, Repräsentation (übergreifend) (max. 4h/Quartal pro MA) | C59: Q | D59: 4 | E59: 3.5 | F59: 3.5 | G59: 87.5 | I59: =IF(H59=0,"",F59-H59) | K59: 0 | L59: =IF($B$2="-","",IF($B$2="Pauschale",IFERROR(INDEX('Projekt-Budget-Übersicht'!$H:$H,MATCH(A59,'Projekt-Budget-Übersicht'!$A:$A,0)),""),IF($B$2="SV",IFERROR(INDEX('Projekt-Budget-Übersicht'!$H:$H,MATCH(A59,'Projekt-Budget-Übersicht'!$A:$A,0)),""),IF($B$2="CAD",IFERROR(INDEX('Projekt-Budget-Übersicht'!$I:$I,MATCH(A59,'Projekt-Budget-Übersicht'!$A:$A,0)),""),IF($B$2="ADM",IFERROR(INDEX('Projekt-Budget-Übersicht'!$J:$J,MATCH(A59,'Projekt-Budget-Übersicht'!$A:$A,0)),""),""))))) | M59: =IF($B$2="-","",L59*(F59+I59+K59)) | N59: =IFERROR(INDEX('Projekt-Budget-Übersicht'!$E:$E,MATCH(A59,'Projekt-Budget-Übersicht'!$A:$A,0)),"")
A60: 4436.04 BTB Krankenhaus-Bergstraße-Viernheimer-Straße-2-Heppenheim | B60: 5100-Beraten Planer ausführungsreife Lösungen…. | C60: G | D60: 52 | E60: 201.5 | F60: 7.5 | G60: 387.5 | I60: =IF(H60=0,"",F60-H60) | K60: =IF('S. Schüler'!J94="C. Trapp SV",'S. Schüler'!I94,0) | L60: =IF($B$2="-","",IF($B$2="Pauschale",IFERROR(INDEX('Projekt-Budget-Übersicht'!$H:$H,MATCH(A60,'Projekt-Budget-Übersicht'!$A:$A,0)),""),IF($B$2="SV",IFERROR(INDEX('Projekt-Budget-Übersicht'!$H:$H,MATCH(A60,'Projekt-Budget-Übersicht'!$A:$A,0)),""),IF($B$2="CAD",IFERROR(INDEX('Projekt-Budget-Übersicht'!$I:$I,MATCH(A60,'Projekt-Budget-Übersicht'!$A:$A,0)),""),IF($B$2="ADM",IFERROR(INDEX('Projekt-Budget-Übersicht'!$J:$J,MATCH(A60,'Projekt-Budget-Übersicht'!$A:$A,0)),""),""))))) | M60: =IF($B$2="-","",L60*(F60+I60+K60)) | N60: =IFERROR(INDEX('Projekt-Budget-Übersicht'!$E:$E,MATCH(A60,'Projekt-Budget-Übersicht'!$A:$A,0)),"")
A61: 5328 Flugfeldklinikum-Böblingen | B61: 8200-Prüfen der Ausführung - system. stichprobenart. Kontrolle (Stufe 2)…. | C61: G | D61: 562 | E61: 285.25 | F61: 26.5 | G61: 50.76 | I61: =IF(H61=0,"",F61-H61) | K61: =IF('S. Roßkopf'!J18="C. Trapp SV",'S. Roßkopf'!I18,0) | L61: =IF($B$2="-","",IF($B$2="Pauschale",IFERROR(INDEX('Projekt-Budget-Übersicht'!$H:$H,MATCH(A61,'Projekt-Budget-Übersicht'!$A:$A,0)),""),IF($B$2="SV",IFERROR(INDEX('Projekt-Budget-Übersicht'!$H:$H,MATCH(A61,'Projekt-Budget-Übersicht'!$A:$A,0)),""),IF($B$2="CAD",IFERROR(INDEX('Projekt-Budget-Übersicht'!$I:$I,MATCH(A61,'Projekt-Budget-Übersicht'!$A:$A,0)),""),IF($B$2="ADM",IFERROR(INDEX('Projekt-Budget-Übersicht'!$J:$J,MATCH(A61,'Projekt-Budget-Übersicht'!$A:$A,0)),""),""))))) | M61: =IF($B$2="-","",L61*(F61+I61+K61)) | N61: =IFERROR(INDEX('Projekt-Budget-Übersicht'!$E:$E,MATCH(A61,'Projekt-Budget-Übersicht'!$A:$A,0)),"")
A62: 5607.05 BAB-NB-J4-Zentralinstitut-für-seelische-Gesundheit-Mannheim | B62: (aN) 8200-Prüfen der Ausführung - system. stichprobenart. Kontrolle (Stufe 2)…. | C62: G | D62: 240 | E62: 188.5 | F62: 5 | G62: 78.54 | I62: =IF(H62=0,"",F62-H62) | K62: =IF('S. Roßkopf'!J19="C. Trapp SV",'S. Roßkopf'!I19,0)+IF('U. Sutter ADM'!J56="C. Trapp SV",'U. Sutter ADM'!I56,0) | L62: =IF($B$2="-","",IF($B$2="Pauschale",IFERROR(INDEX('Projekt-Budget-Übersicht'!$H:$H,MATCH(A62,'Projekt-Budget-Übersicht'!$A:$A,0)),""),IF($B$2="SV",IFERROR(INDEX('Projekt-Budget-Übersicht'!$H:$H,MATCH(A62,'Projekt-Budget-Übersicht'!$A:$A,0)),""),IF($B$2="CAD",IFERROR(INDEX('Projekt-Budget-Übersicht'!$I:$I,MATCH(A62,'Projekt-Budget-Übersicht'!$A:$A,0)),""),IF($B$2="ADM",IFERROR(INDEX('Projekt-Budget-Übersicht'!$J:$J,MATCH(A62,'Projekt-Budget-Übersicht'!$A:$A,0)),""),""))))) | M62: =IF($B$2="-","",L62*(F62+I62+K62)) | N62: =IFERROR(INDEX('Projekt-Budget-Übersicht'!$E:$E,MATCH(A62,'Projekt-Budget-Übersicht'!$A:$A,0)),"")
A63: 6564.01 ROB-MCR-Weilerbach-Züblin-TP1 | B63: 8000-Objektüberwachung | C63: G | D63: 3640 | E63: 230 | F63: 25 | G63: 6.32 | I63: =IF(H63=0,"",F63-H63) | K63: =IF('S. Roßkopf'!J20="C. Trapp SV",'S. Roßkopf'!I20,0) | L63: =IF($B$2="-","",IF($B$2="Pauschale",IFERROR(INDEX('Projekt-Budget-Übersicht'!$H:$H,MATCH(A63,'Projekt-Budget-Übersicht'!$A:$A,0)),""),IF($B$2="SV",IFERROR(INDEX('Projekt-Budget-Übersicht'!$H:$H,MATCH(A63,'Projekt-Budget-Übersicht'!$A:$A,0)),""),IF($B$2="CAD",IFERROR(INDEX('Projekt-Budget-Übersicht'!$I:$I,MATCH(A63,'Projekt-Budget-Übersicht'!$A:$A,0)),""),IF($B$2="ADM",IFERROR(INDEX('Projekt-Budget-Übersicht'!$J:$J,MATCH(A63,'Projekt-Budget-Übersicht'!$A:$A,0)),""),""))))) | M63: =IF($B$2="-","",L63*(F63+I63+K63)) | N63: =IFERROR(INDEX('Projekt-Budget-Übersicht'!$E:$E,MATCH(A63,'Projekt-Budget-Übersicht'!$A:$A,0)),"")
A64: 6643 BTB-FRP-FWP-Ersatzneubau-Krankenhaus-Hohenlohe-Öhringen-Vamed | B64: 8200-Prüfen der Ausführung - system. stichprobenart. Kontrolle (Stufe 2)…. | C64: G | D64: 540 | E64: 536.5 | F64: 47 | G64: 99.35 | I64: =IF(H64=0,"",F64-H64) | K64: =IF('S. Roßkopf'!J21="C. Trapp SV",'S. Roßkopf'!I21,0) | L64: =IF($B$2="-","",IF($B$2="Pauschale",IFERROR(INDEX('Projekt-Budget-Übersicht'!$H:$H,MATCH(A64,'Projekt-Budget-Übersicht'!$A:$A,0)),""),IF($B$2="SV",IFERROR(INDEX('Projekt-Budget-Übersicht'!$H:$H,MATCH(A64,'Projekt-Budget-Übersicht'!$A:$A,0)),""),IF($B$2="CAD",IFERROR(INDEX('Projekt-Budget-Übersicht'!$I:$I,MATCH(A64,'Projekt-Budget-Übersicht'!$A:$A,0)),""),IF($B$2="ADM",IFERROR(INDEX('Projekt-Budget-Übersicht'!$J:$J,MATCH(A64,'Projekt-Budget-Übersicht'!$A:$A,0)),""),""))))) | M64: =IF($B$2="-","",L64*(F64+I64+K64)) | N64: =IFERROR(INDEX('Projekt-Budget-Übersicht'!$E:$E,MATCH(A64,'Projekt-Budget-Übersicht'!$A:$A,0)),"")
A65: 6704 BSK-BTB+FWP-FuR-ZsG-Lörrach | B65: 8200-Prüfen der Ausführung - system. stichprobenart. Kontrolle (Stufe 2)…. | C65: G | D65: 80 | E65: 168.25 | F65: 9.5 | G65: 210.31 | I65: =IF(H65=0,"",F65-H65) | K65: 0 | L65: =IF($B$2="-","",IF($B$2="Pauschale",IFERROR(INDEX('Projekt-Budget-Übersicht'!$H:$H,MATCH(A65,'Projekt-Budget-Übersicht'!$A:$A,0)),""),IF($B$2="SV",IFERROR(INDEX('Projekt-Budget-Übersicht'!$H:$H,MATCH(A65,'Projekt-Budget-Übersicht'!$A:$A,0)),""),IF($B$2="CAD",IFERROR(INDEX('Projekt-Budget-Übersicht'!$I:$I,MATCH(A65,'Projekt-Budget-Übersicht'!$A:$A,0)),""),IF($B$2="ADM",IFERROR(INDEX('Projekt-Budget-Übersicht'!$J:$J,MATCH(A65,'Projekt-Budget-Übersicht'!$A:$A,0)),""),""))))) | M65: =IF($B$2="-","",L65*(F65+I65+K65)) | N65: =IFERROR(INDEX('Projekt-Budget-Übersicht'!$E:$E,MATCH(A65,'Projekt-Budget-Übersicht'!$A:$A,0)),"")
B66: Summe | F66: 154.5
B67: Bonusberechtigte Stunden | F67: =G67+H67 | G67: 103.5 | H67: =SUM(H60,H61,H62,H63,H64,H65)
B68: Bonusberechtigte Stunden Sonderprojekt | F68: =G68+H68 | G68: 12.5 | H68: =SUM(H56,H57,H58,H59)
B69: Zugeordnete Stunden von anderen MA | F69: =SUM(K56:K65)
B70: Gesamt Bonus Stunden | F70: =F67+F68+F69
A72: --- Übertragshilfe ---
A73: Monat | B73: Mitarbeiter | C73: Prod. Stunden | D73: Bonusberechtigte Stunden | E73: Bonusberechtigte Stunden Sonderprojekt | F73: Zugeordnet von anderen | G73: Gesamt Bonus
A74: Juli 2025 | B74: C. Trapp SV | C74: =F24 | D74: =F25 | E74: =F26 | F74: =F27 | G74: =F28
A75: August 2025 | B75: C. Trapp SV | C75: =F48 | D75: =F49 | E75: =F50 | F75: =F51 | G75: =F52
A76: September 2025 | B76: C. Trapp SV | C76: =F66 | D76: =F67 | E76: =F68 | F76: =F69 | G76: =F70
A78: --- Quartalsübersicht 2025Q3 ---
A79: Projekt | B79: Meilenstein | C79: Q-Soll (h) | D79: Q-Ist (h) | E79: %
A80: 0000 Sonderprojekt für Bonus | B80: Vorträge, Repräsentation (übergreifend) (max. 4h/Quartal pro MA) | C80: 4 | D80: 3.5 | E80: 87.5
A82: --- Gesamtstunden 2025Q3 ---
A83: Gesamt eingetragene Stunden: | B83: 481.5
A84: Bonusberechtigte Stunden (Quartal): | B84: =SUM(F25,F49,F67)
A85: Bonusberechtigte Stunden Sonderprojekt (Quartal): | B85: =SUM(F26,F50,F68)

Sheet D. Brucker
A1: D. Brucker - Quartalsreport 2025Q3
A2: Position: | B2: SV
A4: --- Juli 2025 ---
A5: Projekt | B5: Meilenstein | C5: Typ | D5: Soll (h) | E5: Ist (h) | F5: Juli 2025 (h) | G5: % | H5: Bonus-Anpassung (h) | I5: Differenz (h) | J5: Zuordnen an | K5: Von anderen (h) | L5: Stundensatz (€/h) | M5: Umsatz (€) | N5: Budget Gesamt (€) | O5: Budget Ist (€) | P5: Budget Erwirtschaftet (€)
A6: 0000 Sonderprojekt für Bonus | B6: Angebote-Ausschreibungen-Kalkulationen (max. 8h/Monat pro MA) | C6: M | D6: 8 | E6: 9 | F6: 9 | G6: 112.5 | I6: =IF(H6=0,"",F6-H6) | K6: =IF('A. Kokott'!J6="D. Brucker",'A. Kokott'!I6,0)+IF('E. Bieler'!J6="D. Brucker",'E. Bieler'!I6,0)+IF('J. Dorchies'!J6="D. Brucker",'J. Dorchies'!I6,0)+IF('O. Haag BS-CAD'!J6="D. Brucker",'O. Haag BS-CAD'!I6,0)+IF('S. Schüler'!J6="D. Brucker",'S. Schüler'!I6,0)+IF('T. Trautmann'!J6="D. Brucker",'T. Trautmann'!I6,0)+IF('U. Sutter ADM'!J6="D. Brucker",'U. Sutter ADM'!I6,0) | L6: =IF($B$2="-","",IF($B$2="Pauschale",IFERROR(INDEX('Projekt-Budget-Übersicht'!$H:$H,MATCH(A6,'Projekt-Budget-Übersicht'!$A:$A,0)),""),IF($B$2="SV",IFERROR(INDEX('Projekt-Budget-Übersicht'!$H:$H,MATCH(A6,'Projekt-Budget-Übersicht'!$A:$A,0)),""),IF($B$2="CAD",IFERROR(INDEX('Projekt-Budget-Übersicht'!$I:$I,MATCH(A6,'Projekt-Budget-Übersicht'!$A:$A,0)),""),IF($B$2="ADM",IFERROR(INDEX('Projekt-Budget-Übersicht'!$J:$J,MATCH(A6,'Projekt-Budget-Übersicht'!$A:$A,0)),""),""))))) | M6: =IF($B$2="-","",L6*(F6+I6+K6)) | N6: =IFERROR(INDEX('Projekt-Budget-Übersicht'!$E:$E,MATCH(A6,'Projekt-Budget-Übersicht'!$A:$A,0)),"")
B7: Einarbeitung neuer Mitarbeiter (max. 8h/Monat pro MA) | C7: M | D7: 8 | E7: 2 | F7: 2 | G7: 25 | I7: =IF(H7=0,"",F7-H7) | K7: =IF('A. Kokott'!J7="D. Brucker",'A. Kokott'!I7,0)+IF('C. Trapp SV'!J6="D. Brucker",'C. Trapp SV'!I6,0)+IF('E. Bieler'!J7="D. Brucker",'E. Bieler'!I7,0)+IF('J. Dorchies'!J7="D. Brucker",'J. Dorchies'!I7,0)+IF('J. Dorn'!J6="D. Brucker",'J. Dorn'!I6,0)+IF('M. Bandlofsky'!J6="D. Brucker",'M. Bandlofsky'!I6,0)+IF('T. Trautmann'!J7="D. Brucker",'T. Trautmann'!I7,0)+IF('U. Sutter ADM'!J7="D. Brucker",'U. Sutter ADM'!I7,0) | L7: =IF($B$2="-","",IF($B$2="Pauschale",IFERROR(INDEX('Projekt-Budget-Übersicht'!$H:$H,MATCH(A7,'Projekt-Budget-Übersicht'!$A:$A,0)),""),IF($B$2="SV",IFERROR(INDEX('Projekt-Budget-Übersicht'!$H:$H,MATCH(A7,'Projekt-Budget-Übersicht'!$A:$A,0)),""),IF($B$2="CAD",IFERROR(INDEX('Projekt-Budget-Übersicht'!$I:$I,MATCH(A7,'Projekt-Budget-Übersicht'!$A:$A,0)),""),IF($B$2="ADM",IFERROR(INDEX('Projekt-Budget-Übersicht'!$J:$J,MATCH(A7,'Projekt-Budget-Übersicht'!$A:$A,0)),""),""))))) | M7: =IF($B$2="-","",L7*(F7+I7+K7)) | N7: =IFERROR(INDEX('Projekt-Budget-Übersicht'!$E:$E,MATCH(A7,'Projekt-Budget-Übersicht'!$A:$A,0)),"")
A8: 5955.05 Ventilationskonzept-Mosbacher-Straße-55-Wiesbaden-Hauptstaatsarchiv | B8: 2202-Erarbeitung Entrauchungskonzept…. | C8: G | D8: 265.5 | E8: 268.5 | F8: 2 | G8: 101.13 | I8: =IF(H8=0,"",F8-H8) | K8: 0 | L8: =IF($B$2="-","",IF($B$2="Pauschale",IFERROR(INDEX('Projekt-Budget-Übersicht'!$H:$H,MATCH(A8,'Projekt-Budget-Übersicht'!$A:$A,0)),""),IF($B$2="SV",IFERROR(INDEX('Projekt-Budget-Übersicht'!$H:$H,MATCH(A8,'Projekt-Budget-Übersicht'!$A:$A,0)),""),IF($B$2="CAD",IFERROR(INDEX('Projekt-Budget-Übersicht'!$I:$I,MATCH(A8,'Projekt-Budget-Übersicht'!$A:$A,0)),""),IF($B$2="ADM",IFERROR(INDEX('Projekt-Budget-Übersicht'!$J:$J,MATCH(A8,'Projekt-Budget-Übersicht'!$A:$A,0)),""),""))))) | M8: =IF($B$2="-","",L8*(F8+I8+K8)) | N8: =IFERROR(INDEX('Projekt-Budget-Übersicht'!$E:$E,MATCH(A8,'Projekt-Budget-Übersicht'!$A:$A,0)),"")
A9: 5955.08 RAK-FWP-Mosbacher-Straße-55-Wiesbaden-Hauptstaatsarchiv | B9: 9200-Erstellen od. Prüfen Feuerwehrpläne…. | C9: G | D9: 80 | E9: 80 | F9: 2 | G9: 100 | I9: =IF(H9=0,"",F9-H9) | K9: 0 | L9: =IF($B$2="-","",IF($B$2="Pauschale",IFERROR(INDEX('Projekt-Budget-Übersicht'!$H:$H,MATCH(A9,'Projekt-Budget-Übersicht'!$A:$A,0)),""),IF($B$2="SV",IFERROR(INDEX('Projekt-Budget-Übersicht'!$H:$H,MATCH(A9,'Projekt-Budget-Übersicht'!$A:$A,0)),""),IF($B$2="CAD",IFERROR(INDEX('Projekt-Budget-Übersicht'!$I:$I,MATCH(A9,'Projekt-Budget-Übersicht'!$A:$A,0)),""),IF($B$2="ADM",IFERROR(INDEX('Projekt-Budget-Übersicht'!$J:$J,MATCH(A9,'Projekt-Budget-Übersicht'!$A:$A,0)),""),""))))) | M9: =IF($B$2="-","",L9*(F9+I9+K9)) | N9: =IFERROR(INDEX('Projekt-Budget-Übersicht'!$E:$E,MATCH(A9,'Projekt-Budget-Übersicht'!$A:$A,0)),"")
A10: 7302.01 PretiumPlus-NAT-BTB-Rheingaustr186-Wiesbaden | B10: SV | C10: G | D10: 20 | E10: 5.25 | F10: 1 | G10: 26.25 | I10: =IF(H10=0,"",F10-H10) | K10: 0 | L10: =IF($B$2="-","",IF($B$2="Pauschale",IFERROR(INDEX('Projekt-Budget-Übersicht'!$H:$H,MATCH(A10,'Projekt-Budget-Übersicht'!$A:$A,0)),""),IF($B$2="SV",IFERROR(INDEX('Projekt-Budget-Übersicht'!$H:$H,MATCH(A10,'Projekt-Budget-Übersicht'!$A:$A,0)),""),IF($B$2="CAD",IFERROR(INDEX('Projekt-Budget-Übersicht'!$I:$I,MATCH(A10,'Projekt-Budget-Übersicht'!$A:$A,0)),""),IF($B$2="ADM",IFERROR(INDEX('Projekt-Budget-Übersicht'!$J:$J,MATCH(A10,'Projekt-Budget-Übersicht'!$A:$A,0)),""),""))))) | M10: =IF($B$2="-","",L10*(F10+I10+K10)) | N10: =IFERROR(INDEX('Projekt-Budget-Übersicht'!$E:$E,MATCH(A10,'Projekt-Budget-Übersicht'!$A:$A,0)),"")
A11: 7384 Brandschutzzentrale-Fireschutz-BSH-Bielefeld | B11: 25-07-01 (p) prakt. Unterweisung (MA250060272) | C11: G | D11: 5 | E11: 3 | F11: 2 | G11: 60 | I11: =IF(H11=0,"",F11-H11) | K11: =IF('E. Bieler'!J30="D. Brucker",'E. Bieler'!I30,0) | L11: =IF($B$2="-","",IF($B$2="Pauschale",IFERROR(INDEX('Projekt-Budget-Übersicht'!$H:$H,MATCH(A11,'Projekt-Budget-Übersicht'!$A:$A,0)),""),IF($B$2="SV",IFERROR(INDEX('Projekt-Budget-Übersicht'!$H:$H,MATCH(A11,'Projekt-Budget-Übersicht'!$A:$A,0)),""),IF($B$2="CAD",IFERROR(INDEX('Projekt-Budget-Übersicht'!$I:$I,MATCH(A11,'Projekt-Budget-Übersicht'!$A:$A,0)),""),IF($B$2="ADM",IFERROR(INDEX('Projekt-Budget-Übersicht'!$J:$J,MATCH(A11,'Projekt-Budget-Übersicht'!$A:$A,0)),""),""))))) | M11: =IF($B$2="-","",L11*(F11+I11+K11)) | N11: =IFERROR(INDEX('Projekt-Budget-Übersicht'!$E:$E,MATCH(A11,'Projekt-Budget-Übersicht'!$A:$A,0)),"")
A12: 7394.01 TCO-BST-divBestandsdächer-Soldev-div.-Standorte | B12: (aN) Pos. 1 Brandschutztechnische Stellungnahmen (SV) | C12: G | D12: 20 | E12: 20.5 | F12: 18.5 | G12: 102.5 | I12: =IF(H12=0,"",F12-H12) | K12: =IF('S. Schüler'!J38="D. Brucker",'S. Schüler'!I38,0) | L12: =IF($B$2="-","",IF($B$2="Pauschale",IFERROR(INDEX('Projekt-Budget-Übersicht'!$H:$H,MATCH(A12,'Projekt-Budget-Übersicht'!$A:$A,0)),""),IF($B$2="SV",IFERROR(INDEX('Projekt-Budget-Übersicht'!$H:$H,MATCH(A12,'Projekt-Budget-Übersicht'!$A:$A,0)),""),IF($B$2="CAD",IFERROR(INDEX('Projekt-Budget-Übersicht'!$I:$I,MATCH(A12,'Projekt-Budget-Übersicht'!$A:$A,0)),""),IF($B$2="ADM",IFERROR(INDEX('Projekt-Budget-Übersicht'!$J:$J,MATCH(A12,'Projekt-Budget-Übersicht'!$A:$A,0)),""),""))))) | M12: =IF($B$2="-","",L12*(F12+I12+K12)) | N12: =IFERROR(INDEX('Projekt-Budget-Übersicht'!$E:$E,MATCH(A12,'Projekt-Budget-Übersicht'!$A:$A,0)),"")
A13: 7414 HJVV-BSK-NB-Wohnanlage-Trier-Ehrang | B13: (aN) Pos. 1 BTB + Abstimmungstermine (SV ~40h á 115€/h) 4.600€ | C13: G | D13: 40 | E13: 2.25 | F13: 1 | G13: 5.62 | I13: =IF(H13=0,"",F13-H13) | K13: 0 | L13: =IF($B$2="-","",IF($B$2="Pauschale",IFERROR(INDEX('Projekt-Budget-Übersicht'!$H:$H,MATCH(A13,'Projekt-Budget-Übersicht'!$A:$A,0)),""),IF($B$2="SV",IFERROR(INDEX('Projekt-Budget-Übersicht'!$H:$H,MATCH(A13,'Projekt-Budget-Übersicht'!$A:$A,0)),""),IF($B$2="CAD",IFERROR(INDEX('Projekt-Budget-Übersicht'!$I:$I,MATCH(A13,'Projekt-Budget-Übersicht'!$A:$A,0)),""),IF($B$2="ADM",IFERROR(INDEX('Projekt-Budget-Übersicht'!$J:$J,MATCH(A13,'Projekt-Budget-Übersicht'!$A:$A,0)),""),""))))) | M13: =IF($B$2="-","",L13*(F13+I13+K13)) | N13: =IFERROR(INDEX('Projekt-Budget-Übersicht'!$E:$E,MATCH(A13,'Projekt-Budget-Übersicht'!$A:$A,0)),"")
B14: SV | C14: G | D14: 40 | E14: 26 | F14: 24 | G14: 65 | I14: =IF(H14=0,"",F14-H14) | K14: =IF('E. Bieler'!J31="D. Brucker",'E. Bieler'!I31,0) | L14: =IF($B$2="-","",IF($B$2="Pauschale",IFERROR(INDEX('Projekt-Budget-Übersicht'!$H:$H,MATCH(A14,'Projekt-Budget-Übersicht'!$A:$A,0)),""),IF($B$2="SV",IFERROR(INDEX('Projekt-Budget-Übersicht'!$H:$H,MATCH(A14,'Projekt-Budget-Übersicht'!$A:$A,0)),""),IF($B$2="CAD",IFERROR(INDEX('Projekt-Budget-Übersicht'!$I:$I,MATCH(A14,'Projekt-Budget-Übersicht'!$A:$A,0)),""),IF($B$2="ADM",IFERROR(INDEX('Projekt-Budget-Übersicht'!$J:$J,MATCH(A14,'Projekt-Budget-Übersicht'!$A:$A,0)),""),""))))) | M14: =IF($B$2="-","",L14*(F14+I14+K14)) | N14: =IFERROR(INDEX('Projekt-Budget-Übersicht'!$E:$E,MATCH(A14,'Projekt-Budget-Übersicht'!$A:$A,0)),"")
A15: 7459 Baupionier-BTB-Prüfung-Details-Garagenparks | B15: 0300-QM, prüfen Plausibilität, Fertigstellung der Unterlagen | C15: G | D15: 2 | E15: 1 | F15: 1 | G15: 50 | I15: =IF(H15=0,"",F15-H15) | K15: 0 | L15: =IF($B$2="-","",IF($B$2="Pauschale",IFERROR(INDEX('Projekt-Budget-Übersicht'!$H:$H,MATCH(A15,'Projekt-Budget-Übersicht'!$A:$A,0)),""),IF($B$2="SV",IFERROR(INDEX('Projekt-Budget-Übersicht'!$H:$H,MATCH(A15,'Projekt-Budget-Übersicht'!$A:$A,0)),""),IF($B$2="CAD",IFERROR(INDEX('Projekt-Budget-Übersicht'!$I:$I,MATCH(A15,'Projekt-Budget-Übersicht'!$A:$A,0)),""),IF($B$2="ADM",IFERROR(INDEX('Projekt-Budget-Übersicht'!$J:$J,MATCH(A15,'Projekt-Budget-Übersicht'!$A:$A,0)),""),""))))) | M15: =IF($B$2="-","",L15*(F15+I15+K15)) | N15: =IFERROR(INDEX('Projekt-Budget-Übersicht'!$E:$E,MATCH(A15,'Projekt-Budget-Übersicht'!$A:$A,0)),"")
B16: Summe | F16: 62.5
B17: Bonusberechtigte Stunden | F17: =G17+H17 | G17: 31 | H17: =SUM(H8,H9,H10,H11,H12,H13,H14,H15)
B18: Bonusberechtigte Stunden Sonderprojekt | F18: =G18+H18 | G18: 2 | H18: =SUM(H6,H7)
B19: Zugeordnete Stunden von anderen MA | F19: =SUM(K6:K15)
B20: Gesamt Bonus Stunden | F20: =F17+F18+F19
A22: --- August 2025 ---
A23: Projekt | B23: Meilenstein | C23: Typ | D23: Soll (h) | E23: Ist (h) | F23: August 2025 (h) | G23: % | H23: Bonus-Anpassung (h) | I23: Differenz (h) | J23: Zuordnen an | K23: Von anderen (h) | L23: Stundensatz (€/h) | M23: Umsatz (€) | N23: Budget Gesamt (€) | O23: Budget Ist (€) | P23: Budget Erwirtschaftet (€)
A24: 7414 HJVV-BSK-NB-Wohnanlage-Trier-Ehrang | B24: (aN) Pos. 1 BTB + Abstimmungstermine (SV ~40h á 115€/h) 4.600€ | C24: G | D24: 40 | E24: 25.25 | F24: 23 | G24: 63.12 | I24: =IF(H24=0,"",F24-H24) | K24: 0 | L24: =IF($B$2="-","",IF($B$2="Pauschale",IFERROR(INDEX('Projekt-Budget-Übersicht'!$H:$H,MATCH(A24,'Projekt-Budget-Übersicht'!$A:$A,0)),""),IF($B$2="SV",IFERROR(INDEX('Projekt-Budget-Übersicht'!$H:$H,MATCH(A24,'Projekt-Budget-Übersicht'!$A:$A,0)),""),IF($B$2="CAD",IFERROR(INDEX('Projekt-Budget-Übersicht'!$I:$I,MATCH(A24,'Projekt-Budget-Übersicht'!$A:$A,0)),""),IF($B$2="ADM",IFERROR(INDEX('Projekt-Budget-Übersicht'!$J:$J,MATCH(A24,'Projekt-Budget-Übersicht'!$A:$A,0)),""),""))))) | M24: =IF($B$2="-","",L24*(F24+I24+K24)) | N24: =IFERROR(INDEX('Projekt-Budget-Übersicht'!$E:$E,MATCH(A24,'Projekt-Budget-Übersicht'!$A:$A,0)),"")
B25: Summe | F25: 23
B26: Bonusberechtigte Stunden | F26: =G26+H26 | G26: 23 | H26: =SUM(H24)
B27: Bonusberechtigte Stunden Sonderprojekt | F27: 0 | G27: 0 | H27: 0
B28: Zugeordnete Stunden von anderen MA | F28: =SUM(K24:K24)
B29: Gesamt Bonus Stunden | F29: =F26+F27+F28
A31: --- September 2025 ---
A32: Projekt | B32: Meilenstein | C32: Typ | D32: Soll (h) | E32: Ist (h) | F32: September 2025 (h) | G32: % | H32: Bonus-Anpassung (h) | I32: Differenz (h) | J32: Zuordnen an | K32: Von anderen (h) | L32: Stundensatz (€/h) | M32: Umsatz (€) | N32: Budget Gesamt (€) | O32: Budget Ist (€) | P32: Budget Erwirtschaftet (€)
A33: 0000 Sonderprojekt für Bonus | B33: Angebote-Ausschreibungen-Kalkulationen (max. 8h/Monat pro MA) | C33: M | D33: 8 | E33: 8 | F33: 8 | G33: 100 | I33: =IF(H33=0,"",F33-H33) | K33: =IF('A. Kokott'!J85="D. Brucker",'A. Kokott'!I85,0)+IF('C. Trapp SV'!J56="D. Brucker",'C. Trapp SV'!I56,0)+IF('J. Dorn'!J83="D. Brucker",'J. Dorn'!I83,0)+IF('O. Haag BS-CAD'!J92="D. Brucker",'O. Haag BS-CAD'!I92,0)+IF('S. Schüler'!J93="D. Brucker",'S. Schüler'!I93,0)+IF('U. Sutter ADM'!J51="D. Brucker",'U. Sutter ADM'!I51,0) | L33: =IF($B$2="-","",IF($B$2="Pauschale",IFERROR(INDEX('Projekt-Budget-Übersicht'!$H:$H,MATCH(A33,'Projekt-Budget-Übersicht'!$A:$A,0)),""),IF($B$2="SV",IFERROR(INDEX('Projekt-Budget-Übersicht'!$H:$H,MATCH(A33,'Projekt-Budget-Übersicht'!$A:$A,0)),""),IF($B$2="CAD",IFERROR(INDEX('Projekt-Budget-Übersicht'!$I:$I,MATCH(A33,'Projekt-Budget-Übersicht'!$A:$A,0)),""),IF($B$2="ADM",IFERROR(INDEX('Projekt-Budget-Übersicht'!$J:$J,MATCH(A33,'Projekt-Budget-Übersicht'!$A:$A,0)),""),""))))) | M33: =IF($B$2="-","",L33*(F33+I33+K33)) | N33: =IFERROR(INDEX('Projekt-Budget-Übersicht'!$E:$E,MATCH(A33,'Projekt-Budget-Übersicht'!$A:$A,0)),"")
A34: 5955 Mosbacher-Straße-55-Wiesbaden-Hauptstaatsarchiv | B34: 5204-Mitwirken Erstellen Lüftungsgesuch.... | C34: G | D34: 34 | E34: 5.5 | F34: 4 | G34: 16.18 | I34: =IF(H34=0,"",F34-H34) | K34: 0 | L34: =IF($B$2="-","",IF($B$2="Pauschale",IFERROR(INDEX('Projekt-Budget-Übersicht'!$H:$H,MATCH(A34,'Projekt-Budget-Übersicht'!$A:$A,0)),""),IF($B$2="SV",IFERROR(INDEX('Projekt-Budget-Übersicht'!$H:$H,MATCH(A34,'Projekt-Budget-Übersicht'!$A:$A,0)),""),IF($B$2="CAD",IFERROR(INDEX('Projekt-Budget-Übersicht'!$I:$I,MATCH(A34,'Projekt-Budget-Übersicht'!$A:$A,0)),""),IF($B$2="ADM",IFERROR(INDEX('Projekt-Budget-Übersicht'!$J:$J,MATCH(A34,'Projekt-Budget-Übersicht'!$A:$A,0)),""),""))))) | M34: =IF($B$2="-","",L34*(F34+I34+K34)) | N34: =IFERROR(INDEX('Projekt-Budget-Übersicht'!$E:$E,MATCH(A34,'Projekt-Budget-Übersicht'!$A:$A,0)),"")
A35: 7384 Brandschutzzentrale-Fireschutz-BSH-Bielefeld | B35: 25-07-04 (p) ind. Schulung BSH Idar-Oberstein (MA250060403) | C35: G | D35: 5 | E35: 5 | F35: 5 | G35: 100 | I35: =IF(H35=0,"",F35-H35) | K35: 0 | L35: =IF($B$2="-","",IF($B$2="Pauschale",IFERROR(INDEX('Projekt-Budget-Übersicht'!$H:$H,MATCH(A35,'Projekt-Budget-Übersicht'!$A:$A,0)),""),IF($B$2="SV",IFERROR(INDEX('Projekt-Budget-Übersicht'!$H:$H,MATCH(A35,'Projekt-Budget-Übersicht'!$A:$A,0)),""),IF($B$2="CAD",IFERROR(INDEX('Projekt-Budget-Übersicht'!$I:$I,MATCH(A35,'Projekt-Budget-Übersicht'!$A:$A,0)),""),IF($B$2="ADM",IFERROR(INDEX('Projekt-Budget-Übersicht'!$J:$J,MATCH(A35,'Projekt-Budget-Übersicht'!$A:$A,0)),""),""))))) | M35: =IF($B$2="-","",L35*(F35+I35+K35)) | N35: =IFERROR(INDEX('Projekt-Budget-Übersicht'!$E:$E,MATCH(A35,'Projekt-Budget-Übersicht'!$A:$A,0)),"")
B36: 25-09-24 (p) ind. Schulung BSH Grünstadt (MA250060272) | C36: G | D36: 5 | E36: 3.5 | F36: 3 | G36: 70 | I36: =IF(H36=0,"",F36-H36) | K36: 0 | L36: =IF($B$2="-","",IF($B$2="Pauschale",IFERROR(INDEX('Projekt-Budget-Übersicht'!$H:$H,MATCH(A36,'Projekt-Budget-Übersicht'!$A:$A,0)),""),IF($B$2="SV",IFERROR(INDEX('Projekt-Budget-Übersicht'!$H:$H,MATCH(A36,'Projekt-Budget-Übersicht'!$A:$A,0)),""),IF($B$2="CAD",IFERROR(INDEX('Projekt-Budget-Übersicht'!$I:$I,MATCH(A36,'Projekt-Budget-Übersicht'!$A:$A,0)),""),IF($B$2="ADM",IFERROR(INDEX('Projekt-Budget-Übersicht'!$J:$J,MATCH(A36,'Projekt-Budget-Übersicht'!$A:$A,0)),""),""))))) | M36: =IF($B$2="-","",L36*(F36+I36+K36)) | N36: =IFERROR(INDEX('Projekt-Budget-Übersicht'!$E:$E,MATCH(A36,'Projekt-Budget-Übersicht'!$A:$A,0)),"")
A37: 7414 HJVV-BSK-NB-Wohnanlage-Trier-Ehrang | B37: (aN) Pos. 1 BTB + Abstimmungstermine (SV ~40h á 115€/h) 4.600€ | C37: G | D37: 40 | E37: 36.75 | F37: 4 | G37: 91.88 | I37: =IF(H37=0,"",F37-H37) | K37: =IF('S. Schüler'!J113="D. Brucker",'S. Schüler'!I113,0) | L37: =IF($B$2="-","",IF($B$2="Pauschale",IFERROR(INDEX('Projekt-Budget-Übersicht'!$H:$H,MATCH(A37,'Projekt-Budget-Übersicht'!$A:$A,0)),""),IF($B$2="SV",IFERROR(INDEX('Projekt-Budget-Übersicht'!$H:$H,MATCH(A37,'Projekt-Budget-Übersicht'!$A:$A,0)),""),IF($B$2="CAD",IFERROR(INDEX('Projekt-Budget-Übersicht'!$I:$I,MATCH(A37,'Projekt-Budget-Übersicht'!$A:$A,0)),""),IF($B$2="ADM",IFERROR(INDEX('Projekt-Budget-Übersicht'!$J:$J,MATCH(A37,'Projekt-Budget-Übersicht'!$A:$A,0)),""),""))))) | M37: =IF($B$2="-","",L37*(F37+I37+K37)) | N37: =IFERROR(INDEX('Projekt-Budget-Übersicht'!$E:$E,MATCH(A37,'Projekt-Budget-Übersicht'!$A:$A,0)),"")
A38: 7448 Seniorenresidenz-Sonnenwinkel-BSH-Im-Füllengarten14-16-Saarbrücken | B38: SV | C38: G | D38: 7.5 | E38: 5 | F38: 5 | G38: 66.67 | I38: =IF(H38=0,"",F38-H38) | K38: 0 | L38: =IF($B$2="-","",IF($B$2="Pauschale",IFERROR(INDEX('Projekt-Budget-Übersicht'!$H:$H,MATCH(A38,'Projekt-Budget-Übersicht'!$A:$A,0)),""),IF($B$2="SV",IFERROR(INDEX('Projekt-Budget-Übersicht'!$H:$H,MATCH(A38,'Projekt-Budget-Übersicht'!$A:$A,0)),""),IF($B$2="CAD",IFERROR(INDEX('Projekt-Budget-Übersicht'!$I:$I,MATCH(A38,'Projekt-Budget-Übersicht'!$A:$A,0)),""),IF($B$2="ADM",IFERROR(INDEX('Projekt-Budget-Übersicht'!$J:$J,MATCH(A38,'Projekt-Budget-Übersicht'!$A:$A,0)),""),""))))) | M38: =IF($B$2="-","",L38*(F38+I38+K38)) | N38: =IFERROR(INDEX('Projekt-Budget-Übersicht'!$E:$E,MATCH(A38,'Projekt-Budget-Übersicht'!$A:$A,0)),"")
B39: Summe | F39: 29
B40: Bonusberechtigte Stunden | F40: =G40+H40 | G40: 21 | H40: =SUM(H34,H35,H36,H37,H38)
B41: Bonusberechtigte Stunden Sonderprojekt | F41: =G41+H41 | G41: 8 | H41: =SUM(H33)
B42: Zugeordnete Stunden von anderen MA | F42: =SUM(K33:K38)
B43: Gesamt Bonus Stunden | F43: =F40+F41+F42
A45: --- Übertragshilfe ---
A46: Monat | B46: Mitarbeiter | C46: Prod. Stunden | D46: Bonusberechtigte Stunden | E46: Bonusberechtigte Stunden Sonderprojekt | F46: Zugeordnet von anderen | G46: Gesamt Bonus
A47: Juli 2025 | B47: D. Brucker | C47: =F16 | D47: =F17 | E47: =F18 | F47: =F19 | G47: =F20
A48: August 2025 | B48: D. Brucker | C48: =F25 | D48: =F26 | E48: =F27 | F48: =F28 | G48: =F29
A49: September 2025 | B49: D. Brucker | C49: =F39 | D49: =F40 | E49: =F41 | F49: =F42 | G49: =F43
A52: --- Gesamtstunden 2025Q3 ---
A53: Gesamt eingetragene Stunden: | B53: 114.5
A54: Bonusberechtigte Stunden (Quartal): | B54: =SUM(F17,F26,F40)
A55: Bonusberechtigte Stunden Sonderprojekt (Quartal): | B55: =SUM(F18,F27,F41)

Sheet E. Bieler
A1: E. Bieler - Quartalsreport 2025Q3
A2: Position: | B2: SV
A4: --- Juli 2025 ---
A5: Projekt | B5: Meilenstein | C5: Typ | D5: Soll (h) | E5: Ist (h) | F5: Juli 2025 (h) | G5: % | H5: Bonus-Anpassung (h) | I5: Differenz (h) | J5: Zuordnen an | K5: Von anderen (h) | L5: Stundensatz (€/h) | M5: Umsatz (€) | N5: Budget Gesamt (€) | O5: Budget Ist (€) | P5: Budget Erwirtschaftet (€)
A6: 0000 Sonderprojekt für Bonus | B6: Angebote-Ausschreibungen-Kalkulationen (max. 8h/Monat pro MA) | C6: M | D6: 8 | E6: 10 | F6: 10 | G6: 125 | I6: =IF(H6=0,"",F6-H6) | K6: =IF('A. Kokott'!J6="E. Bieler",'A. Kokott'!I6,0)+IF('D. Brucker'!J6="E. Bieler",'D. Brucker'!I6,0)+IF('J. Dorchies'!J6="E. Bieler",'J. Dorchies'!I6,0)+IF('O. Haag BS-CAD'!J6="E. Bieler",'O. Haag BS-CAD'!I6,0)+IF('S. Schüler'!J6="E. Bieler",'S. Schüler'!I6,0)+IF('T. Trautmann'!J6="E. Bieler",'T. Trautmann'!I6,0)+IF('U. Sutter ADM'!J6="E. Bieler",'U. Sutter ADM'!I6,0) | L6: =IF($B$2="-","",IF($B$2="Pauschale",IFERROR(INDEX('Projekt-Budget-Übersicht'!$H:$H,MATCH(A6,'Projekt-Budget-Übersicht'!$A:$A,0)),""),IF($B$2="SV",IFERROR(INDEX('Projekt-Budget-Übersicht'!$H:$H,MATCH(A6,'Projekt-Budget-Übersicht'!$A:$A,0)),""),IF($B$2="CAD",IFERROR(INDEX('Projekt-Budget-Übersicht'!$I:$I,MATCH(A6,'Projekt-Budget-Übersicht'!$A:$A,0)),""),IF($B$2="ADM",IFERROR(INDEX('Projekt-Budget-Übersicht'!$J:$J,MATCH(A6,'Projekt-Budget-Übersicht'!$A:$A,0)),""),""))))) | M6: =IF($B$2="-","",L6*(F6+I6+K6)) | N6: =IFERROR(INDEX('Projekt-Budget-Übersicht'!$E:$E,MATCH(A6,'Projekt-Budget-Übersicht'!$A:$A,0)),"")
B7: Einarbeitung neuer Mitarbeiter (max. 8h/Monat pro MA) | C7: M | D7: 8 | E7: 1 | F7: 1 | G7: 12.5 | I7: =IF(H7=0,"",F7-H7) | K7: =IF('A. Kokott'!J7="E. Bieler",'A. Kokott'!I7,0)+IF('C. Trapp SV'!J6="E. Bieler",'C. Trapp SV'!I6,0)+IF('D. Brucker'!J7="E. Bieler",'D. Brucker'!I7,0)+IF('J. Dorchies'!J7="E. Bieler",'J. Dorchies'!I7,0)+IF('J. Dorn'!J6="E. Bieler",'J. Dorn'!I6,0)+IF('M. Bandlofsky'!J6="E. Bieler",'M. Bandlofsky'!I6,0)+IF('T. Trautmann'!J7="E. Bieler",'T. Trautmann'!I7,0)+IF('U. Sutter ADM'!J7="E. Bieler",'U. Sutter ADM'!I7,0) | L7: =IF($B$2="-","",IF($B$2="Pauschale",IFERROR(INDEX('Projekt-Budget-Übersicht'!$H:$H,MATCH(A7,'Projekt-Budget-Übersicht'!$A:$A,0)),""),IF($B$2="SV",IFERROR(INDEX('Projekt-Budget-Übersicht'!$H:$H,MATCH(A7,'Projekt-Budget-Übersicht'!$A:$A,0)),""),IF($B$2="CAD",IFERROR(INDEX('Projekt-Budget-Übersicht'!$I:$I,MATCH(A7,'Projekt-Budget-Übersicht'!$A:$A,0)),""),IF($B$2="ADM",IFERROR(INDEX('Projekt-Budget-Übersicht'!$J:$J,MATCH(A7,'Projekt-Budget-Übersicht'!$A:$A,0)),""),""))))) | M7: =IF($B$2="-","",L7*(F7+I7+K7)) | N7: =IFERROR(INDEX('Projekt-Budget-Übersicht'!$E:$E,MATCH(A7,'Projekt-Budget-Übersicht'!$A:$A,0)),"")
A8: 3869.24 KES-BST-1.OG-Bestandsgebäude-Marktstr1-3-Stuttgart | B8: SV | C8: G | D8: 20 | E8: 18.75 | F8: 0.5 | G8: 93.75 | I8: =IF(H8=0,"",F8-H8) | K8: =IF('T. Trautmann'!J10="E. Bieler",'T. Trautmann'!I10,0) | L8: =IF($B$2="-","",IF($B$2="Pauschale",IFERROR(INDEX('Projekt-Budget-Übersicht'!$H:$H,MATCH(A8,'Projekt-Budget-Übersicht'!$A:$A,0)),""),IF($B$2="SV",IFERROR(INDEX('Projekt-Budget-Übersicht'!$H:$H,MATCH(A8,'Projekt-Budget-Übersicht'!$A:$A,0)),""),IF($B$2="CAD",IFERROR(INDEX('Projekt-Budget-Übersicht'!$I:$I,MATCH(A8,'Projekt-Budget-Übersicht'!$A:$A,0)),""),IF($B$2="ADM",IFERROR(INDEX('Projekt-Budget-Übersicht'!$J:$J,MATCH(A8,'Projekt-Budget-Übersicht'!$A:$A,0)),""),""))))) | M8: =IF($B$2="-","",L8*(F8+I8+K8)) | N8: =IFERROR(INDEX('Projekt-Budget-Übersicht'!$E:$E,MATCH(A8,'Projekt-Budget-Übersicht'!$A:$A,0)),"")
A9: 4436.042 NA001-BSP-Krankenhaus-Bergstraße-Viernheimer-Straße-2-Heppenheim | B9: 4103-Erarbeiten Brandschutzkonzeptpläne…. | C9: G | D9: 20 | E9: 10.75 | F9: 0.25 | G9: 53.75 | I9: =IF(H9=0,"",F9-H9) | K9: 0 | L9: =IF($B$2="-","",IF($B$2="Pauschale",IFERROR(INDEX('Projekt-Budget-Übersicht'!$H:$H,MATCH(A9,'Projekt-Budget-Übersicht'!$A:$A,0)),""),IF($B$2="SV",IFERROR(INDEX('Projekt-Budget-Übersicht'!$H:$H,MATCH(A9,'Projekt-Budget-Übersicht'!$A:$A,0)),""),IF($B$2="CAD",IFERROR(INDEX('Projekt-Budget-Übersicht'!$I:$I,MATCH(A9,'Projekt-Budget-Übersicht'!$A:$A,0)),""),IF($B$2="ADM",IFERROR(INDEX('Projekt-Budget-Übersicht'!$J:$J,MATCH(A9,'Projekt-Budget-Übersicht'!$A:$A,0)),""),""))))) | M9: =IF($B$2="-","",L9*(F9+I9+K9)) | N9: =IFERROR(INDEX('Projekt-Budget-Übersicht'!$E:$E,MATCH(A9,'Projekt-Budget-Übersicht'!$A:$A,0)),"")
A10: 5156.03 LP8-LBBTR-SPES-N-Airbase-Spangdahlem | B10: (p) Pos. 8 LPH 8 Objektüberwachung | C10: G | D10: 295.5 | E10: 108.25 | F10: 13.75 | G10: 36.63 | I10: =IF(H10=0,"",F10-H10) | K10: =IF('J. Dorn'!J9="E. Bieler",'J. Dorn'!I9,0)+IF('P. Bergner'!J6="E. Bieler",'P. Bergner'!I6,0) | L10: =IF($B$2="-","",IF($B$2="Pauschale",IFERROR(INDEX('Projekt-Budget-Übersicht'!$H:$H,MATCH(A10,'Projekt-Budget-Übersicht'!$A:$A,0)),""),IF($B$2="SV",IFERROR(INDEX('Projekt-Budget-Übersicht'!$H:$H,MATCH(A10,'Projekt-Budget-Übersicht'!$A:$A,0)),""),IF($B$2="CAD",IFERROR(INDEX('Projekt-Budget-Übersicht'!$I:$I,MATCH(A10,'Projekt-Budget-Übersicht'!$A:$A,0)),""),IF($B$2="ADM",IFERROR(INDEX('Projekt-Budget-Übersicht'!$J:$J,MATCH(A10,'Projekt-Budget-Übersicht'!$A:$A,0)),""),""))))) | M10: =IF($B$2="-","",L10*(F10+I10+K10)) | N10: =IFERROR(INDEX('Projekt-Budget-Übersicht'!$E:$E,MATCH(A10,'Projekt-Budget-Übersicht'!$A:$A,0)),"")
A11: 5328 Flugfeldklinikum-Böblingen | B11: 5100-Beraten Planer ausführungsreife Lösungen…. | C11: G | D11: 307.5 | E11: 383.75 | F11: 0.5 | G11: 124.8 | I11: =IF(H11=0,"",F11-H11) | K11: =IF('M. Bandlofsky'!J10="E. Bieler",'M. Bandlofsky'!I10,0) | L11: =IF($B$2="-","",IF($B$2="Pauschale",IFERROR(INDEX('Projekt-Budget-Übersicht'!$H:$H,MATCH(A11,'Projekt-Budget-Übersicht'!$A:$A,0)),""),IF($B$2="SV",IFERROR(INDEX('Projekt-Budget-Übersicht'!$H:$H,MATCH(A11,'Projekt-Budget-Übersicht'!$A:$A,0)),""),IF($B$2="CAD",IFERROR(INDEX('Projekt-Budget-Übersicht'!$I:$I,MATCH(A11,'Projekt-Budget-Übersicht'!$A:$A,0)),""),IF($B$2="ADM",IFERROR(INDEX('Projekt-Budget-Übersicht'!$J:$J,MATCH(A11,'Projekt-Budget-Übersicht'!$A:$A,0)),""),""))))) | M11: =IF($B$2="-","",L11*(F11+I11+K11)) | N11: =IFERROR(INDEX('Projekt-Budget-Übersicht'!$E:$E,MATCH(A11,'Projekt-Budget-Übersicht'!$A:$A,0)),"")
A12: 5409.03 BAB-VBL-Campus-Haus1+2-HansThomaStr19-Karlsruhe | B12: 8100-Prüfen der Ausführung auf prinzipielle Übereinstimmung (Stufe 1).... | C12: G | D12: 42 | E12: 41 | F12: 0.5 | G12: 97.62 | I12: =IF(H12=0,"",F12-H12) | K12: 0 | L12: =IF($B$2="-","",IF($B$2="Pauschale",IFERROR(INDEX('Projekt-Budget-Übersicht'!$H:$H,MATCH(A12,'Projekt-Budget-Übersicht'!$A:$A,0)),""),IF($B$2="SV",IFERROR(INDEX('Projekt-Budget-Übersicht'!$H:$H,MATCH(A12,'Projekt-Budget-Übersicht'!$A:$A,0)),""),IF($B$2="CAD",IFERROR(INDEX('Projekt-Budget-Übersicht'!$I:$I,MATCH(A12,'Projekt-Budget-Übersicht'!$A:$A,0)),""),IF($B$2="ADM",IFERROR(INDEX('Projekt-Budget-Übersicht'!$J:$J,MATCH(A12,'Projekt-Budget-Übersicht'!$A:$A,0)),""),""))))) | M12: =IF($B$2="-","",L12*(F12+I12+K12)) | N12: =IFERROR(INDEX('Projekt-Budget-Übersicht'!$E:$E,MATCH(A12,'Projekt-Budget-Übersicht'!$A:$A,0)),"")
A13: 5876 Eppelheimer-Straße-12-Heidelberg-Hotel-Easy-Living | B13: 8000-Objektüberwachung | C13: G | D13: 110 | E13: 45.75 | F13: 1 | G13: 41.59 | I13: =IF(H13=0,"",F13-H13) | K13: =IF('J. Dorn'!J14="E. Bieler",'J. Dorn'!I14,0) | L13: =IF($B$2="-","",IF($B$2="Pauschale",IFERROR(INDEX('Projekt-Budget-Übersicht'!$H:$H,MATCH(A13,'Projekt-Budget-Übersicht'!$A:$A,0)),""),IF($B$2="SV",IFERROR(INDEX('Projekt-Budget-Übersicht'!$H:$H,MATCH(A13,'Projekt-Budget-Übersicht'!$A:$A,0)),""),IF($B$2="CAD",IFERROR(INDEX('Projekt-Budget-Übersicht'!$I:$I,MATCH(A13,'Projekt-Budget-Übersicht'!$A:$A,0)),""),IF($B$2="ADM",IFERROR(INDEX('Projekt-Budget-Übersicht'!$J:$J,MATCH(A13,'Projekt-Budget-Übersicht'!$A:$A,0)),""),""))))) | M13: =IF($B$2="-","",L13*(F13+I13+K13)) | N13: =IFERROR(INDEX('Projekt-Budget-Übersicht'!$E:$E,MATCH(A13,'Projekt-Budget-Übersicht'!$A:$A,0)),"")
A14: 5987.03 E&S-BSK-BT-C-Czernyring15-Heidelberg | B14: 3000-Entwurfsplanung SV | C14: G | D14: 10 | E14: 15.5 | F14: 1 | G14: 155 | I14: =IF(H14=0,"",F14-H14) | K14: 0 | L14: =IF($B$2="-","",IF($B$2="Pauschale",IFERROR(INDEX('Projekt-Budget-Übersicht'!$H:$H,MATCH(A14,'Projekt-Budget-Übersicht'!$A:$A,0)),""),IF($B$2="SV",IFERROR(INDEX('Projekt-Budget-Übersicht'!$H:$H,MATCH(A14,'Projekt-Budget-Übersicht'!$A:$A,0)),""),IF($B$2="CAD",IFERROR(INDEX('Projekt-Budget-Übersicht'!$I:$I,MATCH(A14,'Projekt-Budget-Übersicht'!$A:$A,0)),""),IF($B$2="ADM",IFERROR(INDEX('Projekt-Budget-Übersicht'!$J:$J,MATCH(A14,'Projekt-Budget-Übersicht'!$A:$A,0)),""),""))))) | M14: =IF($B$2="-","",L14*(F14+I14+K14)) | N14: =IFERROR(INDEX('Projekt-Budget-Übersicht'!$E:$E,MATCH(A14,'Projekt-Budget-Übersicht'!$A:$A,0)),"")
A15: 5987.04 E&S-BTB+BSK-BT-A+B-Czernyring15-Heidelberg | B15: SV | C15: G | D15: 30 | E15: 19.5 | F15: 1 | G15: 65 | I15: =IF(H15=0,"",F15-H15) | K15: 0 | L15: =IF($B$2="-","",IF($B$2="Pauschale",IFERROR(INDEX('Projekt-Budget-Übersicht'!$H:$H,MATCH(A15,'Projekt-Budget-Übersicht'!$A:$A,0)),""),IF($B$2="SV",IFERROR(INDEX('Projekt-Budget-Übersicht'!$H:$H,MATCH(A15,'Projekt-Budget-Übersicht'!$A:$A,0)),""),IF($B$2="CAD",IFERROR(INDEX('Projekt-Budget-Übersicht'!$I:$I,MATCH(A15,'Projekt-Budget-Übersicht'!$A:$A,0)),""),IF($B$2="ADM",IFERROR(INDEX('Projekt-Budget-Übersicht'!$J:$J,MATCH(A15,'Projekt-Budget-Übersicht'!$A:$A,0)),""),""))))) | M15: =IF($B$2="-","",L15*(F15+I15+K15)) | N15: =IFERROR(INDEX('Projekt-Budget-Übersicht'!$E:$E,MATCH(A15,'Projekt-Budget-Übersicht'!$A:$A,0)),"")
A16: 6285.081 NAT-FWP-Opernplatz-14-Frankfurt | B16: 1200-Bestandserfassung vor Ort.... | C16: G | D16: 16 | E16: 16.25 | F16: 0.25 | G16: 101.56 | I16: =IF(H16=0,"",F16-H16) | K16: 0 | L16: =IF($B$2="-","",IF($B$2="Pauschale",IFERROR(INDEX('Projekt-Budget-Übersicht'!$H:$H,MATCH(A16,'Projekt-Budget-Übersicht'!$A:$A,0)),""),IF($B$2="SV",IFERROR(INDEX('Projekt-Budget-Übersicht'!$H:$H,MATCH(A16,'Projekt-Budget-Übersicht'!$A:$A,0)),""),IF($B$2="CAD",IFERROR(INDEX('Projekt-Budget-Übersicht'!$I:$I,MATCH(A16,'Projekt-Budget-Übersicht'!$A:$A,0)),""),IF($B$2="ADM",IFERROR(INDEX('Projekt-Budget-Übersicht'!$J:$J,MATCH(A16,'Projekt-Budget-Übersicht'!$A:$A,0)),""),""))))) | M16: =IF($B$2="-","",L16*(F16+I16+K16)) | N16: =IFERROR(INDEX('Projekt-Budget-Übersicht'!$E:$E,MATCH(A16,'Projekt-Budget-Übersicht'!$A:$A,0)),"")
A17: 6313.05 rh-Construction-LG-EnSol-BSK-BAB-Limespark-Sulzbach | B17: (aN) Pos. 1 Abstimmungstermin mit den Behörden und Beratungsleistungen | C17: G | D17: 24 | E17: 18.25 | F17: 3.5 | G17: 76.04 | I17: =IF(H17=0,"",F17-H17) | K17: =IF('R. Böttiger'!J7="E. Bieler",'R. Böttiger'!I7,0) | L17: =IF($B$2="-","",IF($B$2="Pauschale",IFERROR(INDEX('Projekt-Budget-Übersicht'!$H:$H,MATCH(A17,'Projekt-Budget-Übersicht'!$A:$A,0)),""),IF($B$2="SV",IFERROR(INDEX('Projekt-Budget-Übersicht'!$H:$H,MATCH(A17,'Projekt-Budget-Übersicht'!$A:$A,0)),""),IF($B$2="CAD",IFERROR(INDEX('Projekt-Budget-Übersicht'!$I:$I,MATCH(A17,'Projekt-Budget-Übersicht'!$A:$A,0)),""),IF($B$2="ADM",IFERROR(INDEX('Projekt-Budget-Übersicht'!$J:$J,MATCH(A17,'Projekt-Budget-Übersicht'!$A:$A,0)),""),""))))) | M17: =IF($B$2="-","",L17*(F17+I17+K17)) | N17: =IFERROR(INDEX('Projekt-Budget-Übersicht'!$E:$E,MATCH(A17,'Projekt-Budget-Übersicht'!$A:$A,0)),"")
B18: (p) Pos. 3 Brandschutzberatung in der Ausführungsplanung | C18: G | D18: 16 | E18: 22.25 | F18: 1 | G18: 139.06 | I18: =IF(H18=0,"",F18-H18) | K18: =IF('J. Dorn'!J20="E. Bieler",'J. Dorn'!I20,0)+IF('R. Böttiger'!J8="E. Bieler",'R. Böttiger'!I8,0) | L18: =IF($B$2="-","",IF($B$2="Pauschale",IFERROR(INDEX('Projekt-Budget-Übersicht'!$H:$H,MATCH(A18,'Projekt-Budget-Übersicht'!$A:$A,0)),""),IF($B$2="SV",IFERROR(INDEX('Projekt-Budget-Übersicht'!$H:$H,MATCH(A18,'Projekt-Budget-Übersicht'!$A:$A,0)),""),IF($B$2="CAD",IFERROR(INDEX('Projekt-Budget-Übersicht'!$I:$I,MATCH(A18,'Projekt-Budget-Übersicht'!$A:$A,0)),""),IF($B$2="ADM",IFERROR(INDEX('Projekt-Budget-Übersicht'!$J:$J,MATCH(A18,'Projekt-Budget-Übersicht'!$A:$A,0)),""),""))))) | M18: =IF($B$2="-","",L18*(F18+I18+K18)) | N18: =IFERROR(INDEX('Projekt-Budget-Übersicht'!$E:$E,MATCH(A18,'Projekt-Budget-Übersicht'!$A:$A,0)),"")
A19: 6313.06 BSK-Fitseveneleven-Limespark-Sulzbach-1.OG | B19: 8000-Objektüberwachung | C19: G | D19: 16 | E19: 25.25 | F19: 0.5 | G19: 157.81 | I19: =IF(H19=0,"",F19-H19) | K19: =IF('R. Böttiger'!J10="E. Bieler",'R. Böttiger'!I10,0) | L19: =IF($B$2="-","",IF($B$2="Pauschale",IFERROR(INDEX('Projekt-Budget-Übersicht'!$H:$H,MATCH(A19,'Projekt-Budget-Übersicht'!$A:$A,0)),""),IF($B$2="SV",IFERROR(INDEX('Projekt-Budget-Übersicht'!$H:$H,MATCH(A19,'Projekt-Budget-Übersicht'!$A:$A,0)),""),IF($B$2="CAD",IFERROR(INDEX('Projekt-Budget-Übersicht'!$I:$I,MATCH(A19,'Projekt-Budget-Übersicht'!$A:$A,0)),""),IF($B$2="ADM",IFERROR(INDEX('Projekt-Budget-Übersicht'!$J:$J,MATCH(A19,'Projekt-Budget-Übersicht'!$A:$A,0)),""),""))))) | M19: =IF($B$2="-","",L19*(F19+I19+K19)) | N19: =IFERROR(INDEX('Projekt-Budget-Übersicht'!$E:$E,MATCH(A19,'Projekt-Budget-Übersicht'!$A:$A,0)),"")
A20: 6527.01 IO-Anp-BSK-Mühlenfeldstr1-Holzminden-Symotion | B20: SV | C20: G | D20: 6 | E20: 33.75 | F20: 0.25 | G20: 562.5 | I20: =IF(H20=0,"",F20-H20) | K20: =IF('A. Kokott'!J14="E. Bieler",'A. Kokott'!I14,0)+IF('J. Dorchies'!J9="E. Bieler",'J. Dorchies'!I9,0)+IF('J. Dorn'!J23="E. Bieler",'J. Dorn'!I23,0)+IF('P. Bergner'!J7="E. Bieler",'P. Bergner'!I7,0)+IF('R. Böttiger'!J13="E. Bieler",'R. Böttiger'!I13,0) | L20: =IF($B$2="-","",IF($B$2="Pauschale",IFERROR(INDEX('Projekt-Budget-Übersicht'!$H:$H,MATCH(A20,'Projekt-Budget-Übersicht'!$A:$A,0)),""),IF($B$2="SV",IFERROR(INDEX('Projekt-Budget-Übersicht'!$H:$H,MATCH(A20,'Projekt-Budget-Übersicht'!$A:$A,0)),""),IF($B$2="CAD",IFERROR(INDEX('Projekt-Budget-Übersicht'!$I:$I,MATCH(A20,'Projekt-Budget-Übersicht'!$A:$A,0)),""),IF($B$2="ADM",IFERROR(INDEX('Projekt-Budget-Übersicht'!$J:$J,MATCH(A20,'Projekt-Budget-Übersicht'!$A:$A,0)),""),""))))) | M20: =IF($B$2="-","",L20*(F20+I20+K20)) | N20: =IFERROR(INDEX('Projekt-Budget-Übersicht'!$E:$E,MATCH(A20,'Projekt-Budget-Übersicht'!$A:$A,0)),"")
A21: 6995 Telehouse-BSK-TDE-RZ-GebN-Kleyerstraße75-89-FFM | B21: Erarbeiten des Brandschutzkonzept/Nachweis/Stellungnahme | C21: G | D21: 63 | E21: 42 | F21: 1 | G21: 66.67 | I21: =IF(H21=0,"",F21-H21) | K21: 0 | L21: =IF($B$2="-","",IF($B$2="Pauschale",IFERROR(INDEX('Projekt-Budget-Übersicht'!$H:$H,MATCH(A21,'Projekt-Budget-Übersicht'!$A:$A,0)),""),IF($B$2="SV",IFERROR(INDEX('Projekt-Budget-Übersicht'!$H:$H,MATCH(A21,'Projekt-Budget-Übersicht'!$A:$A,0)),""),IF($B$2="CAD",IFERROR(INDEX('Projekt-Budget-Übersicht'!$I:$I,MATCH(A21,'Projekt-Budget-Übersicht'!$A:$A,0)),""),IF($B$2="ADM",IFERROR(INDEX('Projekt-Budget-Übersicht'!$J:$J,MATCH(A21,'Projekt-Budget-Übersicht'!$A:$A,0)),""),""))))) | M21: =IF($B$2="-","",L21*(F21+I21+K21)) | N21: =IFERROR(INDEX('Projekt-Budget-Übersicht'!$E:$E,MATCH(A21,'Projekt-Budget-Übersicht'!$A:$A,0)),"")
A22: 7150 TFS-AHO-Neubau-betrWohnen-Kita-Alberichstraße-Mannheim | B22: SV | C22: G | D22: 13 | E22: 146.75 | F22: 1 | G22: 1128.85 | I22: =IF(H22=0,"",F22-H22) | K22: =IF('J. Dorchies'!J11="E. Bieler",'J. Dorchies'!I11,0)+IF('J. Dorn'!J33="E. Bieler",'J. Dorn'!I33,0)+IF('R. Böttiger'!J14="E. Bieler",'R. Böttiger'!I14,0) | L22: =IF($B$2="-","",IF($B$2="Pauschale",IFERROR(INDEX('Projekt-Budget-Übersicht'!$H:$H,MATCH(A22,'Projekt-Budget-Übersicht'!$A:$A,0)),""),IF($B$2="SV",IFERROR(INDEX('Projekt-Budget-Übersicht'!$H:$H,MATCH(A22,'Projekt-Budget-Übersicht'!$A:$A,0)),""),IF($B$2="CAD",IFERROR(INDEX('Projekt-Budget-Übersicht'!$I:$I,MATCH(A22,'Projekt-Budget-Übersicht'!$A:$A,0)),""),IF($B$2="ADM",IFERROR(INDEX('Projekt-Budget-Übersicht'!$J:$J,MATCH(A22,'Projekt-Budget-Übersicht'!$A:$A,0)),""),""))))) | M22: =IF($B$2="-","",L22*(F22+I22+K22)) | N22: =IFERROR(INDEX('Projekt-Budget-Übersicht'!$E:$E,MATCH(A22,'Projekt-Budget-Übersicht'!$A:$A,0)),"")
A23: 7159.01 TE Connectivity-BSK-Geb2701,2702-Siemensstr18-Speyer | B23: SV | C23: G | D23: 46 | E23: 76.75 | F23: 1 | G23: 166.85 | I23: =IF(H23=0,"",F23-H23) | K23: 0 | L23: =IF($B$2="-","",IF($B$2="Pauschale",IFERROR(INDEX('Projekt-Budget-Übersicht'!$H:$H,MATCH(A23,'Projekt-Budget-Übersicht'!$A:$A,0)),""),IF($B$2="SV",IFERROR(INDEX('Projekt-Budget-Übersicht'!$H:$H,MATCH(A23,'Projekt-Budget-Übersicht'!$A:$A,0)),""),IF($B$2="CAD",IFERROR(INDEX('Projekt-Budget-Übersicht'!$I:$I,MATCH(A23,'Projekt-Budget-Übersicht'!$A:$A,0)),""),IF($B$2="ADM",IFERROR(INDEX('Projekt-Budget-Übersicht'!$J:$J,MATCH(A23,'Projekt-Budget-Übersicht'!$A:$A,0)),""),""))))) | M23: =IF($B$2="-","",L23*(F23+I23+K23)) | N23: =IFERROR(INDEX('Projekt-Budget-Übersicht'!$E:$E,MATCH(A23,'Projekt-Budget-Übersicht'!$A:$A,0)),"")
A24: 7236 Würth - Stundennachweise | B24: SV | C24: G | D24: 0 | E24: 119 | F24: 0.25 | G24: 0 | I24: =IF(H24=0,"",F24-H24) | K24: =IF('M. Bandlofsky'!J13="E. Bieler",'M. Bandlofsky'!I13,0) | L24: =IF($B$2="-","",IF($B$2="Pauschale",IFERROR(INDEX('Projekt-Budget-Übersicht'!$H:$H,MATCH(A24,'Projekt-Budget-Übersicht'!$A:$A,0)),""),IF($B$2="SV",IFERROR(INDEX('Projekt-Budget-Übersicht'!$H:$H,MATCH(A24,'Projekt-Budget-Übersicht'!$A:$A,0)),""),IF($B$2="CAD",IFERROR(INDEX('Projekt-Budget-Übersicht'!$I:$I,MATCH(A24,'Projekt-Budget-Übersicht'!$A:$A,0)),""),IF($B$2="ADM",IFERROR(INDEX('Projekt-Budget-Übersicht'!$J:$J,MATCH(A24,'Projekt-Budget-Übersicht'!$A:$A,0)),""),""))))) | M24: =IF($B$2="-","",L24*(F24+I24+K24)) | N24: =IFERROR(INDEX('Projekt-Budget-Übersicht'!$E:$E,MATCH(A24,'Projekt-Budget-Übersicht'!$A:$A,0)),"")
A25: 7253 JUWI-BSK-WP-Bad-Laasphe-Feudingen | B25: (p) Pos. 1.00 Brandschutzkonzept | C25: G | D25: 10 | E25: 16.25 | F25: 0.5 | G25: 162.5 | I25: =IF(H25=0,"",F25-H25) | K25: =IF('H. Bektas'!J8="E. Bieler",'H. Bektas'!I8,0)+IF('J. Dorchies'!J14="E. Bieler",'J. Dorchies'!I14,0) | L25: =IF($B$2="-","",IF($B$2="Pauschale",IFERROR(INDEX('Projekt-Budget-Übersicht'!$H:$H,MATCH(A25,'Projekt-Budget-Übersicht'!$A:$A,0)),""),IF($B$2="SV",IFERROR(INDEX('Projekt-Budget-Übersicht'!$H:$H,MATCH(A25,'Projekt-Budget-Übersicht'!$A:$A,0)),""),IF($B$2="CAD",IFERROR(INDEX('Projekt-Budget-Übersicht'!$I:$I,MATCH(A25,'Projekt-Budget-Übersicht'!$A:$A,0)),""),IF($B$2="ADM",IFERROR(INDEX('Projekt-Budget-Übersicht'!$J:$J,MATCH(A25,'Projekt-Budget-Übersicht'!$A:$A,0)),""),""))))) | M25: =IF($B$2="-","",L25*(F25+I25+K25)) | N25: =IFERROR(INDEX('Projekt-Budget-Übersicht'!$E:$E,MATCH(A25,'Projekt-Budget-Übersicht'!$A:$A,0)),"")
A26: 7328 LAER-formica-BSK-Lageranalage-Eilinger-Kamp-Menden | B26: SV | C26: G | D26: 16 | E26: 14.25 | F26: 0.25 | G26: 89.06 | I26: =IF(H26=0,"",F26-H26) | K26: =IF('H. Bektas'!J9="E. Bieler",'H. Bektas'!I9,0) | L26: =IF($B$2="-","",IF($B$2="Pauschale",IFERROR(INDEX('Projekt-Budget-Übersicht'!$H:$H,MATCH(A26,'Projekt-Budget-Übersicht'!$A:$A,0)),""),IF($B$2="SV",IFERROR(INDEX('Projekt-Budget-Übersicht'!$H:$H,MATCH(A26,'Projekt-Budget-Übersicht'!$A:$A,0)),""),IF($B$2="CAD",IFERROR(INDEX('Projekt-Budget-Übersicht'!$I:$I,MATCH(A26,'Projekt-Budget-Übersicht'!$A:$A,0)),""),IF($B$2="ADM",IFERROR(INDEX('Projekt-Budget-Übersicht'!$J:$J,MATCH(A26,'Projekt-Budget-Übersicht'!$A:$A,0)),""),""))))) | M26: =IF($B$2="-","",L26*(F26+I26+K26)) | N26: =IFERROR(INDEX('Projekt-Budget-Übersicht'!$E:$E,MATCH(A26,'Projekt-Budget-Übersicht'!$A:$A,0)),"")
A27: 7361 Energieprojekte-DK-BSK-WP-Thalfingen+Repowering-Anlage-Seligweiler-Bayern | B27: SV | C27: G | D27: 19 | E27: 20.75 | F27: 0.25 | G27: 109.21 | I27: =IF(H27=0,"",F27-H27) | K27: =IF('H. Bektas'!J10="E. Bieler",'H. Bektas'!I10,0) | L27: =IF($B$2="-","",IF($B$2="Pauschale",IFERROR(INDEX('Projekt-Budget-Übersicht'!$H:$H,MATCH(A27,'Projekt-Budget-Übersicht'!$A:$A,0)),""),IF($B$2="SV",IFERROR(INDEX('Projekt-Budget-Übersicht'!$H:$H,MATCH(A27,'Projekt-Budget-Übersicht'!$A:$A,0)),""),IF($B$2="CAD",IFERROR(INDEX('Projekt-Budget-Übersicht'!$I:$I,MATCH(A27,'Projekt-Budget-Übersicht'!$A:$A,0)),""),IF($B$2="ADM",IFERROR(INDEX('Projekt-Budget-Übersicht'!$J:$J,MATCH(A27,'Projekt-Budget-Übersicht'!$A:$A,0)),""),""))))) | M27: =IF($B$2="-","",L27*(F27+I27+K27)) | N27: =IFERROR(INDEX('Projekt-Budget-Übersicht'!$E:$E,MATCH(A27,'Projekt-Budget-Übersicht'!$A:$A,0)),"")
A28: 7364 SHE-BSK-WP-Göttingen-Baden-Württemberg | B28: SV | C28: G | D28: 19 | E28: 18.25 | F28: 0.25 | G28: 96.05 | I28: =IF(H28=0,"",F28-H28) | K28: =IF('H. Bektas'!J11="E. Bieler",'H. Bektas'!I11,0) | L28: =IF($B$2="-","",IF($B$2="Pauschale",IFERROR(INDEX('Projekt-Budget-Übersicht'!$H:$H,MATCH(A28,'Projekt-Budget-Übersicht'!$A:$A,0)),""),IF($B$2="SV",IFERROR(INDEX('Projekt-Budget-Übersicht'!$H:$H,MATCH(A28,'Projekt-Budget-Übersicht'!$A:$A,0)),""),IF($B$2="CAD",IFERROR(INDEX('Projekt-Budget-Übersicht'!$I:$I,MATCH(A28,'Projekt-Budget-Übersicht'!$A:$A,0)),""),IF($B$2="ADM",IFERROR(INDEX('Projekt-Budget-Übersicht'!$J:$J,MATCH(A28,'Projekt-Budget-Übersicht'!$A:$A,0)),""),""))))) | M28: =IF($B$2="-","",L28*(F28+I28+K28)) | N28: =IFERROR(INDEX('Projekt-Budget-Übersicht'!$E:$E,MATCH(A28,'Projekt-Budget-Übersicht'!$A:$A,0)),"")
A29: 7380.02 Qualitas-BSK-WEA-Geroldshausen-Uengershausen | B29: SV | C29: G | D29: 2400 | E29: 18 | F29: 0.25 | G29: 0.75 | I29: =IF(H29=0,"",F29-H29) | K29: 0 | L29: =IF($B$2="-","",IF($B$2="Pauschale",IFERROR(INDEX('Projekt-Budget-Übersicht'!$H:$H,MATCH(A29,'Projekt-Budget-Übersicht'!$A:$A,0)),""),IF($B$2="SV",IFERROR(INDEX('Projekt-Budget-Übersicht'!$H:$H,MATCH(A29,'Projekt-Budget-Übersicht'!$A:$A,0)),""),IF($B$2="CAD",IFERROR(INDEX('Projekt-Budget-Übersicht'!$I:$I,MATCH(A29,'Projekt-Budget-Übersicht'!$A:$A,0)),""),IF($B$2="ADM",IFERROR(INDEX('Projekt-Budget-Übersicht'!$J:$J,MATCH(A29,'Projekt-Budget-Übersicht'!$A:$A,0)),""),""))))) | M29: =IF($B$2="-","",L29*(F29+I29+K29)) | N29: =IFERROR(INDEX('Projekt-Budget-Übersicht'!$E:$E,MATCH(A29,'Projekt-Budget-Übersicht'!$A:$A,0)),"")
A30: 7384 Brandschutzzentrale-Fireschutz-BSH-Bielefeld | B30: 25-07-01 (p) prakt. Unterweisung (MA250060272) | C30: G | D30: 5 | E30: 3 | F30: 0.5 | G30: 60 | I30: =IF(H30=0,"",F30-H30) | K30: =IF('D. Brucker'!J11="E. Bieler",'D. Brucker'!I11,0) | L30: =IF($B$2="-","",IF($B$2="Pauschale",IFERROR(INDEX('Projekt-Budget-Übersicht'!$H:$H,MATCH(A30,'Projekt-Budget-Übersicht'!$A:$A,0)),""),IF($B$2="SV",IFERROR(INDEX('Projekt-Budget-Übersicht'!$H:$H,MATCH(A30,'Projekt-Budget-Übersicht'!$A:$A,0)),""),IF($B$2="CAD",IFERROR(INDEX('Projekt-Budget-Übersicht'!$I:$I,MATCH(A30,'Projekt-Budget-Übersicht'!$A:$A,0)),""),IF($B$2="ADM",IFERROR(INDEX('Projekt-Budget-Übersicht'!$J:$J,MATCH(A30,'Projekt-Budget-Übersicht'!$A:$A,0)),""),""))))) | M30: =IF($B$2="-","",L30*(F30+I30+K30)) | N30: =IFERROR(INDEX('Projekt-Budget-Übersicht'!$E:$E,MATCH(A30,'Projekt-Budget-Übersicht'!$A:$A,0)),"")
A31: 7414 HJVV-BSK-NB-Wohnanlage-Trier-Ehrang | B31: SV | C31: G | D31: 40 | E31: 26 | F31: 1 | G31: 65 | I31: =IF(H31=0,"",F31-H31) | K31: =IF('D. Brucker'!J14="E. Bieler",'D. Brucker'!I14,0) | L31: =IF($B$2="-","",IF($B$2="Pauschale",IFERROR(INDEX('Projekt-Budget-Übersicht'!$H:$H,MATCH(A31,'Projekt-Budget-Übersicht'!$A:$A,0)),""),IF($B$2="SV",IFERROR(INDEX('Projekt-Budget-Übersicht'!$H:$H,MATCH(A31,'Projekt-Budget-Übersicht'!$A:$A,0)),""),IF($B$2="CAD",IFERROR(INDEX('Projekt-Budget-Übersicht'!$I:$I,MATCH(A31,'Projekt-Budget-Übersicht'!$A:$A,0)),""),IF($B$2="ADM",IFERROR(INDEX('Projekt-Budget-Übersicht'!$J:$J,MATCH(A31,'Projekt-Budget-Übersicht'!$A:$A,0)),""),""))))) | M31: =IF($B$2="-","",L31*(F31+I31+K31)) | N31: =IFERROR(INDEX('Projekt-Budget-Übersicht'!$E:$E,MATCH(A31,'Projekt-Budget-Übersicht'!$A:$A,0)),"")
A32: 7419.02 Zech-FRP-FWP-Sporthalle-Pestalozzistr10-Eppelheim | B32: CAD | C32: G | D32: 26 | E32: 10.25 | F32: 0.5 | G32: 39.42 | I32: =IF(H32=0,"",F32-H32) | K32: =IF('O. Haag BS-CAD'!J41="E. Bieler",'O. Haag BS-CAD'!I41,0) | L32: =IF($B$2="-","",IF($B$2="Pauschale",IFERROR(INDEX('Projekt-Budget-Übersicht'!$H:$H,MATCH(A32,'Projekt-Budget-Übersicht'!$A:$A,0)),""),IF($B$2="SV",IFERROR(INDEX('Projekt-Budget-Übersicht'!$H:$H,MATCH(A32,'Projekt-Budget-Übersicht'!$A:$A,0)),""),IF($B$2="CAD",IFERROR(INDEX('Projekt-Budget-Übersicht'!$I:$I,MATCH(A32,'Projekt-Budget-Übersicht'!$A:$A,0)),""),IF($B$2="ADM",IFERROR(INDEX('Projekt-Budget-Übersicht'!$J:$J,MATCH(A32,'Projekt-Budget-Übersicht'!$A:$A,0)),""),""))))) | M32: =IF($B$2="-","",L32*(F32+I32+K32)) | N32: =IFERROR(INDEX('Projekt-Budget-Übersicht'!$E:$E,MATCH(A32,'Projekt-Budget-Übersicht'!$A:$A,0)),"")
A33: 7422 Energieprojekte-DK-BSK-WEA-Aschbach-Ilmenau | B33: SV | C33: G | D33: 16 | E33: 15.25 | F33: 0.25 | G33: 95.31 | I33: =IF(H33=0,"",F33-H33) | K33: =IF('H. Bektas'!J16="E. Bieler",'H. Bektas'!I16,0) | L33: =IF($B$2="-","",IF($B$2="Pauschale",IFERROR(INDEX('Projekt-Budget-Übersicht'!$H:$H,MATCH(A33,'Projekt-Budget-Übersicht'!$A:$A,0)),""),IF($B$2="SV",IFERROR(INDEX('Projekt-Budget-Übersicht'!$H:$H,MATCH(A33,'Projekt-Budget-Übersicht'!$A:$A,0)),""),IF($B$2="CAD",IFERROR(INDEX('Projekt-Budget-Übersicht'!$I:$I,MATCH(A33,'Projekt-Budget-Übersicht'!$A:$A,0)),""),IF($B$2="ADM",IFERROR(INDEX('Projekt-Budget-Übersicht'!$J:$J,MATCH(A33,'Projekt-Budget-Übersicht'!$A:$A,0)),""),""))))) | M33: =IF($B$2="-","",L33*(F33+I33+K33)) | N33: =IFERROR(INDEX('Projekt-Budget-Übersicht'!$E:$E,MATCH(A33,'Projekt-Budget-Übersicht'!$A:$A,0)),"")
A34: 7426 MPI-BTB-Biophysik-Max-von-Laue-Str3-FFM | B34: (aN) Pos. 1 Brandschutztechnische Beratung | C34: G | D34: 26 | E34: 29 | F34: 0.5 | G34: 111.54 | I34: =IF(H34=0,"",F34-H34) | K34: =IF('M. Bandlofsky'!J14="E. Bieler",'M. Bandlofsky'!I14,0) | L34: =IF($B$2="-","",IF($B$2="Pauschale",IFERROR(INDEX('Projekt-Budget-Übersicht'!$H:$H,MATCH(A34,'Projekt-Budget-Übersicht'!$A:$A,0)),""),IF($B$2="SV",IFERROR(INDEX('Projekt-Budget-Übersicht'!$H:$H,MATCH(A34,'Projekt-Budget-Übersicht'!$A:$A,0)),""),IF($B$2="CAD",IFERROR(INDEX('Projekt-Budget-Übersicht'!$I:$I,MATCH(A34,'Projekt-Budget-Übersicht'!$A:$A,0)),""),IF($B$2="ADM",IFERROR(INDEX('Projekt-Budget-Übersicht'!$J:$J,MATCH(A34,'Projekt-Budget-Übersicht'!$A:$A,0)),""),""))))) | M34: =IF($B$2="-","",L34*(F34+I34+K34)) | N34: =IFERROR(INDEX('Projekt-Budget-Übersicht'!$E:$E,MATCH(A34,'Projekt-Budget-Übersicht'!$A:$A,0)),"")
A35: 7435 wiwi-BSK-WEA-Spiesheim-Wörrstadt-Ost | B35: SV | C35: G | D35: 17 | E35: 16.25 | F35: 0.25 | G35: 95.59 | I35: =IF(H35=0,"",F35-H35) | K35: =IF('H. Bektas'!J17="E. Bieler",'H. Bektas'!I17,0) | L35: =IF($B$2="-","",IF($B$2="Pauschale",IFERROR(INDEX('Projekt-Budget-Übersicht'!$H:$H,MATCH(A35,'Projekt-Budget-Übersicht'!$A:$A,0)),""),IF($B$2="SV",IFERROR(INDEX('Projekt-Budget-Übersicht'!$H:$H,MATCH(A35,'Projekt-Budget-Übersicht'!$A:$A,0)),""),IF($B$2="CAD",IFERROR(INDEX('Projekt-Budget-Übersicht'!$I:$I,MATCH(A35,'Projekt-Budget-Übersicht'!$A:$A,0)),""),IF($B$2="ADM",IFERROR(INDEX('Projekt-Budget-Übersicht'!$J:$J,MATCH(A35,'Projekt-Budget-Übersicht'!$A:$A,0)),""),""))))) | M35: =IF($B$2="-","",L35*(F35+I35+K35)) | N35: =IFERROR(INDEX('Projekt-Budget-Übersicht'!$E:$E,MATCH(A35,'Projekt-Budget-Übersicht'!$A:$A,0)),"")
A36: 7437 MVV-BSK-UW3-Käfertal-Mannheim | B36: Erarbeiten des Brandschutzkonzept/Nachweis/Stellungnahme | C36: G | D36: 31 | E36: 35.25 | F36: 2 | G36: 113.71 | I36: =IF(H36=0,"",F36-H36) | K36: =IF('J. Dorn'!J35="E. Bieler",'J. Dorn'!I35,0)+IF('M. Bandlofsky'!J16="E. Bieler",'M. Bandlofsky'!I16,0) | L36: =IF($B$2="-","",IF($B$2="Pauschale",IFERROR(INDEX('Projekt-Budget-Übersicht'!$H:$H,MATCH(A36,'Projekt-Budget-Übersicht'!$A:$A,0)),""),IF($B$2="SV",IFERROR(INDEX('Projekt-Budget-Übersicht'!$H:$H,MATCH(A36,'Projekt-Budget-Übersicht'!$A:$A,0)),""),IF($B$2="CAD",IFERROR(INDEX('Projekt-Budget-Übersicht'!$I:$I,MATCH(A36,'Projekt-Budget-Übersicht'!$A:$A,0)),""),IF($B$2="ADM",IFERROR(INDEX('Projekt-Budget-Übersicht'!$J:$J,MATCH(A36,'Projekt-Budget-Übersicht'!$A:$A,0)),""),""))))) | M36: =IF($B$2="-","",L36*(F36+I36+K36)) | N36: =IFERROR(INDEX('Projekt-Budget-Übersicht'!$E:$E,MATCH(A36,'Projekt-Budget-Übersicht'!$A:$A,0)),"")
A37: 7441 Baupionier-Garagenpark-Öhringen-BSK | B37: SV | C37: G | D37: 17 | E37: 13.5 | F37: 0.5 | G37: 79.41 | I37: =IF(H37=0,"",F37-H37) | K37: =IF('H. Bektas'!J18="E. Bieler",'H. Bektas'!I18,0) | L37: =IF($B$2="-","",IF($B$2="Pauschale",IFERROR(INDEX('Projekt-Budget-Übersicht'!$H:$H,MATCH(A37,'Projekt-Budget-Übersicht'!$A:$A,0)),""),IF($B$2="SV",IFERROR(INDEX('Projekt-Budget-Übersicht'!$H:$H,MATCH(A37,'Projekt-Budget-Übersicht'!$A:$A,0)),""),IF($B$2="CAD",IFERROR(INDEX('Projekt-Budget-Übersicht'!$I:$I,MATCH(A37,'Projekt-Budget-Übersicht'!$A:$A,0)),""),IF($B$2="ADM",IFERROR(INDEX('Projekt-Budget-Übersicht'!$J:$J,MATCH(A37,'Projekt-Budget-Übersicht'!$A:$A,0)),""),""))))) | M37: =IF($B$2="-","",L37*(F37+I37+K37)) | N37: =IFERROR(INDEX('Projekt-Budget-Übersicht'!$E:$E,MATCH(A37,'Projekt-Budget-Übersicht'!$A:$A,0)),"")
A38: 7459 Baupionier-BTB-Prüfung-Details-Garagenparks | B38: 3100-Erarbeiten des Brandschutzkonzept/Nachweis/Stellungnahme | C38: G | D38: 14 | E38: 15.5 | F38: 0.5 | G38: 110.71 | I38: =IF(H38=0,"",F38-H38) | K38: =IF('A. Kokott'!J30="E. Bieler",'A. Kokott'!I30,0)+IF('M. Bandlofsky'!J17="E. Bieler",'M. Bandlofsky'!I17,0) | L38: =IF($B$2="-","",IF($B$2="Pauschale",IFERROR(INDEX('Projekt-Budget-Übersicht'!$H:$H,MATCH(A38,'Projekt-Budget-Übersicht'!$A:$A,0)),""),IF($B$2="SV",IFERROR(INDEX('Projekt-Budget-Übersicht'!$H:$H,MATCH(A38,'Projekt-Budget-Übersicht'!$A:$A,0)),""),IF($B$2="CAD",IFERROR(INDEX('Projekt-Budget-Übersicht'!$I:$I,MATCH(A38,'Projekt-Budget-Übersicht'!$A:$A,0)),""),IF($B$2="ADM",IFERROR(INDEX('Projekt-Budget-Übersicht'!$J:$J,MATCH(A38,'Projekt-Budget-Übersicht'!$A:$A,0)),""),""))))) | M38: =IF($B$2="-","",L38*(F38+I38+K38)) | N38: =IFERROR(INDEX('Projekt-Budget-Übersicht'!$E:$E,MATCH(A38,'Projekt-Budget-Übersicht'!$A:$A,0)),"")
A39: 7600.01 Altus-BSK-FWP-WP-Padberg | B39: SV | C39: G | D39: 0 | E39: 0 | F39: 0.25 | G39: 0 | I39: =IF(H39=0,"",F39-H39) | K39: 0 | L39: =IF($B$2="-","",IF($B$2="Pauschale",IFERROR(INDEX('Projekt-Budget-Übersicht'!$H:$H,MATCH(A39,'Projekt-Budget-Übersicht'!$A:$A,0)),""),IF($B$2="SV",IFERROR(INDEX('Projekt-Budget-Übersicht'!$H:$H,MATCH(A39,'Projekt-Budget-Übersicht'!$A:$A,0)),""),IF($B$2="CAD",IFERROR(INDEX('Projekt-Budget-Übersicht'!$I:$I,MATCH(A39,'Projekt-Budget-Übersicht'!$A:$A,0)),""),IF($B$2="ADM",IFERROR(INDEX('Projekt-Budget-Übersicht'!$J:$J,MATCH(A39,'Projekt-Budget-Übersicht'!$A:$A,0)),""),""))))) | M39: =IF($B$2="-","",L39*(F39+I39+K39)) | N39: =IFERROR(INDEX('Projekt-Budget-Übersicht'!$E:$E,MATCH(A39,'Projekt-Budget-Übersicht'!$A:$A,0)),"")
A40: 7700.01 EAM-BSK-WEA-Herborn | B40: SV | C40: G | D40: 16 | E40: 8.25 | F40: 0.25 | G40: 51.56 | I40: =IF(H40=0,"",F40-H40) | K40: 0 | L40: =IF($B$2="-","",IF($B$2="Pauschale",IFERROR(INDEX('Projekt-Budget-Übersicht'!$H:$H,MATCH(A40,'Projekt-Budget-Übersicht'!$A:$A,0)),""),IF($B$2="SV",IFERROR(INDEX('Projekt-Budget-Übersicht'!$H:$H,MATCH(A40,'Projekt-Budget-Übersicht'!$A:$A,0)),""),IF($B$2="CAD",IFERROR(INDEX('Projekt-Budget-Übersicht'!$I:$I,MATCH(A40,'Projekt-Budget-Übersicht'!$A:$A,0)),""),IF($B$2="ADM",IFERROR(INDEX('Projekt-Budget-Übersicht'!$J:$J,MATCH(A40,'Projekt-Budget-Übersicht'!$A:$A,0)),""),""))))) | M40: =IF($B$2="-","",L40*(F40+I40+K40)) | N40: =IFERROR(INDEX('Projekt-Budget-Übersicht'!$E:$E,MATCH(A40,'Projekt-Budget-Übersicht'!$A:$A,0)),"")
A41: 8100 UStrich-Stunden-für-Mosaik-/Kaarst-Projekte | B41: Pos. 1.003: Abgleich FRP – 400€ | C41: G | D41: 0 | E41: 3.25 | F41: 0.25 | G41: 0 | I41: =IF(H41=0,"",F41-H41) | K41: =IF('M. Bandlofsky CAD'!J7="E. Bieler",'M. Bandlofsky CAD'!I7,0) | L41: =IF($B$2="-","",IF($B$2="Pauschale",IFERROR(INDEX('Projekt-Budget-Übersicht'!$H:$H,MATCH(A41,'Projekt-Budget-Übersicht'!$A:$A,0)),""),IF($B$2="SV",IFERROR(INDEX('Projekt-Budget-Übersicht'!$H:$H,MATCH(A41,'Projekt-Budget-Übersicht'!$A:$A,0)),""),IF($B$2="CAD",IFERROR(INDEX('Projekt-Budget-Übersicht'!$I:$I,MATCH(A41,'Projekt-Budget-Übersicht'!$A:$A,0)),""),IF($B$2="ADM",IFERROR(INDEX('Projekt-Budget-Übersicht'!$J:$J,MATCH(A41,'Projekt-Budget-Übersicht'!$A:$A,0)),""),""))))) | M41: =IF($B$2="-","",L41*(F41+I41+K41)) | N41: =IFERROR(INDEX('Projekt-Budget-Übersicht'!$E:$E,MATCH(A41,'Projekt-Budget-Übersicht'!$A:$A,0)),"")
B42: Summe | F42: 46.5
B43: Bonusberechtigte Stunden | F43: =G43+H43 | G43: 26.25 | H43: =SUM(H8,H9,H10,H11,H12,H13,H14,H15,H16,H17,H18,H19,H20,H21,H22,H23,H24,H25,H26,H27,H28,H29,H30,H31,H32,H33,H34,H35,H36,H37,H38,H39,H40,H41)
B44: Bonusberechtigte Stunden Sonderprojekt | F44: =G44+H44 | G44: 1 | H44: =SUM(H6,H7)
B45: Zugeordnete Stunden von anderen MA | F45: =SUM(K6:K41)
B46: Gesamt Bonus Stunden | F46: =F43+F44+F45
A48: --- August 2025 ---
A49: Projekt | B49: Meilenstein | C49: Typ | D49: Soll (h) | E49: Ist (h) | F49: August 2025 (h) | G49: % | H49: Bonus-Anpassung (h) | I49: Differenz (h) | J49: Zuordnen an | K49: Von anderen (h) | L49: Stundensatz (€/h) | M49: Umsatz (€) | N49: Budget Gesamt (€) | O49: Budget Ist (€) | P49: Budget Erwirtschaftet (€)
A50: 5328 Flugfeldklinikum-Böblingen | B50: 5100-Beraten Planer ausführungsreife Lösungen…. | C50: G | D50: 307.5 | E50: 390.25 | F50: 2 | G50: 126.91 | I50: =IF(H50=0,"",F50-H50) | K50: =IF('C. Trapp SV'!J35="E. Bieler",'C. Trapp SV'!I35,0)+IF('M. Bandlofsky'!J31="E. Bieler",'M. Bandlofsky'!I31,0) | L50: =IF($B$2="-","",IF($B$2="Pauschale",IFERROR(INDEX('Projekt-Budget-Übersicht'!$H:$H,MATCH(A50,'Projekt-Budget-Übersicht'!$A:$A,0)),""),IF($B$2="SV",IFERROR(INDEX('Projekt-Budget-Übersicht'!$H:$H,MATCH(A50,'Projekt-Budget-Übersicht'!$A:$A,0)),""),IF($B$2="CAD",IFERROR(INDEX('Projekt-Budget-Übersicht'!$I:$I,MATCH(A50,'Projekt-Budget-Übersicht'!$A:$A,0)),""),IF($B$2="ADM",IFERROR(INDEX('Projekt-Budget-Übersicht'!$J:$J,MATCH(A50,'Projekt-Budget-Übersicht'!$A:$A,0)),""),""))))) | M50: =IF($B$2="-","",L50*(F50+I50+K50)) | N50: =IFERROR(INDEX('Projekt-Budget-Übersicht'!$E:$E,MATCH(A50,'Projekt-Budget-Übersicht'!$A:$A,0)),"")
B51: 8100-Prüfen der Ausführung auf prinzipielle Übereinstimmung (Stufe 1).... | C51: G | D51: 610 | E51: 65.5 | F51: 5.75 | G51: 10.74 | I51: =IF(H51=0,"",F51-H51) | K51: =IF('C. Trapp SV'!J36="E. Bieler",'C. Trapp SV'!I36,0) | L51: =IF($B$2="-","",IF($B$2="Pauschale",IFERROR(INDEX('Projekt-Budget-Übersicht'!$H:$H,MATCH(A51,'Projekt-Budget-Übersicht'!$A:$A,0)),""),IF($B$2="SV",IFERROR(INDEX('Projekt-Budget-Übersicht'!$H:$H,MATCH(A51,'Projekt-Budget-Übersicht'!$A:$A,0)),""),IF($B$2="CAD",IFERROR(INDEX('Projekt-Budget-Übersicht'!$I:$I,MATCH(A51,'Projekt-Budget-Übersicht'!$A:$A,0)),""),IF($B$2="ADM",IFERROR(INDEX('Projekt-Budget-Übersicht'!$J:$J,MATCH(A51,'Projekt-Budget-Übersicht'!$A:$A,0)),""),""))))) | M51: =IF($B$2="-","",L51*(F51+I51+K51)) | N51: =IFERROR(INDEX('Projekt-Budget-Übersicht'!$E:$E,MATCH(A51,'Projekt-Budget-Übersicht'!$A:$A,0)),"")
A52: 6643 BTB-FRP-FWP-Ersatzneubau-Krankenhaus-Hohenlohe-Öhringen-Vamed | B52: 5100-Beraten Planer ausführungsreife Lösungen…. | C52: G | D52: 144 | E52: 106.5 | F52: 2 | G52: 73.96 | I52: =IF(H52=0,"",F52-H52) | K52: =IF('C. Trapp SV'!J43="E. Bieler",'C. Trapp SV'!I43,0) | L52: =IF($B$2="-","",IF($B$2="Pauschale",IFERROR(INDEX('Projekt-Budget-Übersicht'!$H:$H,MATCH(A52,'Projekt-Budget-Übersicht'!$A:$A,0)),""),IF($B$2="SV",IFERROR(INDEX('Projekt-Budget-Übersicht'!$H:$H,MATCH(A52,'Projekt-Budget-Übersicht'!$A:$A,0)),""),IF($B$2="CAD",IFERROR(INDEX('Projekt-Budget-Übersicht'!$I:$I,MATCH(A52,'Projekt-Budget-Übersicht'!$A:$A,0)),""),IF($B$2="ADM",IFERROR(INDEX('Projekt-Budget-Übersicht'!$J:$J,MATCH(A52,'Projekt-Budget-Übersicht'!$A:$A,0)),""),""))))) | M52: =IF($B$2="-","",L52*(F52+I52+K52)) | N52: =IFERROR(INDEX('Projekt-Budget-Übersicht'!$E:$E,MATCH(A52,'Projekt-Budget-Übersicht'!$A:$A,0)),"")
B53: Summe | F53: 9.75
B54: Bonusberechtigte Stunden | F54: =G54+H54 | G54: 7.75 | H54: =SUM(H50,H51,H52)
B55: Bonusberechtigte Stunden Sonderprojekt | F55: 0 | G55: 0 | H55: 0
B56: Zugeordnete Stunden von anderen MA | F56: =SUM(K50:K52)
B57: Gesamt Bonus Stunden | F57: =F54+F55+F56
A59: --- September 2025 ---
A60: Projekt | B60: Meilenstein | C60: Typ | D60: Soll (h) | E60: Ist (h) | F60: September 2025 (h) | G60: % | H60: Bonus-Anpassung (h) | I60: Differenz (h) | J60: Zuordnen an | K60: Von anderen (h) | L60: Stundensatz (€/h) | M60: Umsatz (€) | N60: Budget Gesamt (€) | O60: Budget Ist (€) | P60: Budget Erwirtschaftet (€)
A61: 5328 Flugfeldklinikum-Böblingen | B61: 4202-Fortschreiben BSK aufgrund Vorprüfung Behörden | C61: G | D61: 24 | E61: 64.25 | F61: 1.5 | G61: 267.71 | I61: =IF(H61=0,"",F61-H61) | K61: 0 | L61: =IF($B$2="-","",IF($B$2="Pauschale",IFERROR(INDEX('Projekt-Budget-Übersicht'!$H:$H,MATCH(A61,'Projekt-Budget-Übersicht'!$A:$A,0)),""),IF($B$2="SV",IFERROR(INDEX('Projekt-Budget-Übersicht'!$H:$H,MATCH(A61,'Projekt-Budget-Übersicht'!$A:$A,0)),""),IF($B$2="CAD",IFERROR(INDEX('Projekt-Budget-Übersicht'!$I:$I,MATCH(A61,'Projekt-Budget-Übersicht'!$A:$A,0)),""),IF($B$2="ADM",IFERROR(INDEX('Projekt-Budget-Übersicht'!$J:$J,MATCH(A61,'Projekt-Budget-Übersicht'!$A:$A,0)),""),""))))) | M61: =IF($B$2="-","",L61*(F61+I61+K61)) | N61: =IFERROR(INDEX('Projekt-Budget-Übersicht'!$E:$E,MATCH(A61,'Projekt-Budget-Übersicht'!$A:$A,0)),"")
B62: 5100-Beraten Planer ausführungsreife Lösungen…. | C62: G | D62: 307.5 | E62: 398.25 | F62: 2 | G62: 129.51 | I62: =IF(H62=0,"",F62-H62) | K62: =IF('M. Bandlofsky'!J51="E. Bieler",'M. Bandlofsky'!I51,0) | L62: =IF($B$2="-","",IF($B$2="Pauschale",IFERROR(INDEX('Projekt-Budget-Übersicht'!$H:$H,MATCH(A62,'Projekt-Budget-Übersicht'!$A:$A,0)),""),IF($B$2="SV",IFERROR(INDEX('Projekt-Budget-Übersicht'!$H:$H,MATCH(A62,'Projekt-Budget-Übersicht'!$A:$A,0)),""),IF($B$2="CAD",IFERROR(INDEX('Projekt-Budget-Übersicht'!$I:$I,MATCH(A62,'Projekt-Budget-Übersicht'!$A:$A,0)),""),IF($B$2="ADM",IFERROR(INDEX('Projekt-Budget-Übersicht'!$J:$J,MATCH(A62,'Projekt-Budget-Übersicht'!$A:$A,0)),""),""))))) | M62: =IF($B$2="-","",L62*(F62+I62+K62)) | N62: =IFERROR(INDEX('Projekt-Budget-Übersicht'!$E:$E,MATCH(A62,'Projekt-Budget-Übersicht'!$A:$A,0)),"")
B63: Summe | F63: 3.5
B64: Bonusberechtigte Stunden | F64: =G64+H64 | G64: 0 | H64: =SUM(H61,H62)
B65: Bonusberechtigte Stunden Sonderprojekt | F65: 0 | G65: 0 | H65: 0
B66: Zugeordnete Stunden von anderen MA | F66: =SUM(K61:K62)
B67: Gesamt Bonus Stunden | F67: =F64+F65+F66
A69: --- Übertragshilfe ---
A70: Monat | B70: Mitarbeiter | C70: Prod. Stunden | D70: Bonusberechtigte Stunden | E70: Bonusberechtigte Stunden Sonderprojekt | F70: Zugeordnet von anderen | G70: Gesamt Bonus
A71: Juli 2025 | B71: E. Bieler | C71: =F42 | D71: =F43 | E71: =F44 | F71: =F45 | G71: =F46
A72: August 2025 | B72: E. Bieler | C72: =F53 | D72: =F54 | E72: =F55 | F72: =F56 | G72: =F57
A73: September 2025 | B73: E. Bieler | C73: =F63 | D73: =F64 | E73: =F65 | F73: =F66 | G73: =F67
A76: --- Gesamtstunden 2025Q3 ---
A77: Gesamt eingetragene Stunden: | B77: 59.75
A78: Bonusberechtigte Stunden (Quartal): | B78: =SUM(F43,F54,F64)
A79: Bonusberechtigte Stunden Sonderprojekt (Quartal): | B79: =SUM(F44,F55,F65)

Sheet E. Iago Barros de Oliveira
A1: E. Iago Barros de Oliveira - Quartalsreport 2025Q3
A2: Position: | B2: SV
A4: --- Juli 2025 ---
A5: Projekt | B5: Meilenstein | C5: Typ | D5: Soll (h) | E5: Ist (h) | F5: Juli 2025 (h) | G5: % | H5: Bonus-Anpassung (h) | I5: Differenz (h) | J5: Zuordnen an | K5: Von anderen (h) | L5: Stundensatz (€/h) | M5: Umsatz (€) | N5: Budget Gesamt (€) | O5: Budget Ist (€) | P5: Budget Erwirtschaftet (€)
A6: 0.2420 LUD Allgemeinprojekt | B6: 11 Stunden, die auf Projekte umgetragen werden müssen | C6: G | D6: 0 | E6: 0 | F6: 12.5 | G6: 0 | I6: =IF(H6=0,"",F6-H6) | K6: 0 | L6: =IF($B$2="-","",IF($B$2="Pauschale",IFERROR(INDEX('Projekt-Budget-Übersicht'!$H:$H,MATCH(A6,'Projekt-Budget-Übersicht'!$A:$A,0)),""),IF($B$2="SV",IFERROR(INDEX('Projekt-Budget-Übersicht'!$H:$H,MATCH(A6,'Projekt-Budget-Übersicht'!$A:$A,0)),""),IF($B$2="CAD",IFERROR(INDEX('Projekt-Budget-Übersicht'!$I:$I,MATCH(A6,'Projekt-Budget-Übersicht'!$A:$A,0)),""),IF($B$2="ADM",IFERROR(INDEX('Projekt-Budget-Übersicht'!$J:$J,MATCH(A6,'Projekt-Budget-Übersicht'!$A:$A,0)),""),""))))) | M6: =IF($B$2="-","",L6*(F6+I6+K6)) | N6: =IFERROR(INDEX('Projekt-Budget-Übersicht'!$E:$E,MATCH(A6,'Projekt-Budget-Übersicht'!$A:$A,0)),"")
A7: 4436.04 BTB Krankenhaus-Bergstraße-Viernheimer-Straße-2-Heppenheim | B7: 2101-Erarbeiten Eckdaten Brandschutzkonzept…. | C7: G | D7: 31.5 | E7: 100.5 | F7: 32 | G7: 319.05 | I7: =IF(H7=0,"",F7-H7) | K7: =IF('S. Schüler'!J9="E. Iago Barros de Oliveira",'S. Schüler'!I9,0) | L7: =IF($B$2="-","",IF($B$2="Pauschale",IFERROR(INDEX('Projekt-Budget-Übersicht'!$H:$H,MATCH(A7,'Projekt-Budget-Übersicht'!$A:$A,0)),""),IF($B$2="SV",IFERROR(INDEX('Projekt-Budget-Übersicht'!$H:$H,MATCH(A7,'Projekt-Budget-Übersicht'!$A:$A,0)),""),IF($B$2="CAD",IFERROR(INDEX('Projekt-Budget-Übersicht'!$I:$I,MATCH(A7,'Projekt-Budget-Übersicht'!$A:$A,0)),""),IF($B$2="ADM",IFERROR(INDEX('Projekt-Budget-Übersicht'!$J:$J,MATCH(A7,'Projekt-Budget-Übersicht'!$A:$A,0)),""),""))))) | M7: =IF($B$2="-","",L7*(F7+I7+K7)) | N7: =IFERROR(INDEX('Projekt-Budget-Übersicht'!$E:$E,MATCH(A7,'Projekt-Budget-Übersicht'!$A:$A,0)),"")
B8: Summe | F8: 44.5
B9: Bonusberechtigte Stunden | F9: =G9+H9 | G9: 12.5 | H9: =SUM(H6,H7)
B10: Bonusberechtigte Stunden Sonderprojekt | F10: 0 | G10: 0 | H10: 0
B11: Zugeordnete Stunden von anderen MA | F11: =SUM(K6:K7)
B12: Gesamt Bonus Stunden | F12: =F9+F10+F11
A14: --- Übertragshilfe ---
A15: Monat | B15: Mitarbeiter | C15: Prod. Stunden | D15: Bonusberechtigte Stunden | E15: Bonusberechtigte Stunden Sonderprojekt | F15: Zugeordnet von anderen | G15: Gesamt Bonus
A16: Juli 2025 | B16: E. Iago Barros de Oliveira | C16: =F8 | D16: =F9 | E16: =F10 | F16: =F11 | G16: =F12
A19: --- Gesamtstunden 2025Q3 ---
A20: Gesamt eingetragene Stunden: | B20: 44.5
A21: Bonusberechtigte Stunden (Quartal): | B21: =SUM(F9)
A22: Bonusberechtigte Stunden Sonderprojekt (Quartal): | B22: =SUM(F10)

Sheet H. Bektas
A1: H. Bektas - Quartalsreport 2025Q3
A2: Position: | B2: SV
A4: --- Juli 2025 ---
A5: Projekt | B5: Meilenstein | C5: Typ | D5: Soll (h) | E5: Ist (h) | F5: Juli 2025 (h) | G5: % | H5: Bonus-Anpassung (h) | I5: Differenz (h) | J5: Zuordnen an | K5: Von anderen (h) | L5: Stundensatz (€/h) | M5: Umsatz (€) | N5: Budget Gesamt (€) | O5: Budget Ist (€) | P5: Budget Erwirtschaftet (€)
A6: 6769.01 Juwi-Anp-BSK-Selser-Berg | B6: (p) Anp. BSK | C6: G | D6: 2 | E6: 3.5 | F6: 2 | G6: 175 | I6: =IF(H6=0,"",F6-H6) | K6: =IF('A. Kokott'!J15="H. Bektas",'A. Kokott'!I15,0) | L6: =IF($B$2="-","",IF($B$2="Pauschale",IFERROR(INDEX('Projekt-Budget-Übersicht'!$H:$H,MATCH(A6,'Projekt-Budget-Übersicht'!$A:$A,0)),""),IF($B$2="SV",IFERROR(INDEX('Projekt-Budget-Übersicht'!$H:$H,MATCH(A6,'Projekt-Budget-Übersicht'!$A:$A,0)),""),IF($B$2="CAD",IFERROR(INDEX('Projekt-Budget-Übersicht'!$I:$I,MATCH(A6,'Projekt-Budget-Übersicht'!$A:$A,0)),""),IF($B$2="ADM",IFERROR(INDEX('Projekt-Budget-Übersicht'!$J:$J,MATCH(A6,'Projekt-Budget-Übersicht'!$A:$A,0)),""),""))))) | M6: =IF($B$2="-","",L6*(F6+I6+K6)) | N6: =IFERROR(INDEX('Projekt-Budget-Übersicht'!$E:$E,MATCH(A6,'Projekt-Budget-Übersicht'!$A:$A,0)),"")
